Workbook

Sheet Drivers
A1: SMC 62730 — Drivers
A2: BLUE = input/actual; BLACK = same-sheet formula; GREEN = cross-sheet; YELLOW bg = forecast cell
A4: 1. Sales QoQ Growth Assumptions (%) — adjust to flex PL forecast
B5: FY24Q2 | C5: FY24Q3 | D5: FY24Q4 | E5: FY25Q1 | F5: FY25Q2 | G5: FY25Q3 | H5: FY25Q4 | I5: FY26Q1 | J5: FY26Q2 | K5: FY26Q3 | L5: FY26Q4 | M5: FY27Q1 | N5: FY27Q2 | O5: FY27Q3 | P5: FY27Q4 | Q5: FY28Q1 | T5: FY24 | U5: FY25 | V5: FY26 | W5: FY27 | X5: FY28
A6: AutomaticControlEquipment | C6: =FS!C4/FS!B4-1 -> 0.016226337 | D6: =FS!D4/FS!C4-1 -> 0.03198567 | E6: =FS!E4/FS!D4-1 -> -0.0072898587 | F6: =FS!F4/FS!E4-1 -> -0.00044959536 | G6: =FS!G4/FS!F4-1 -> 0.047828477 | H6: =FS!H4/FS!G4-1 -> 0.10946294 | I6: =FS!I4/FS!H4-1 -> 0.16499721 | J6: 10 | K6: -3 | L6: 5 | M6: 3 | N6: 0 | O6: 0 | P6: 6.8 | Q6: 2.9
A8: Consolidated OPM (%) — drives OP (Sales × OPM) | B8: =FS!B9/FS!B4 -> 0.2451633 | C8: =FS!C9/FS!C4 -> 0.22159672 | D8: =FS!D9/FS!D4 -> 0.2353087 | E8: =FS!E9/FS!E4 -> 0.22210011 | F8: =FS!F9/FS!F4 -> 0.23149583 | G8: =FS!G9/FS!G4 -> 0.22312315 | H8: =FS!H9/FS!H4 -> 0.2278062 | I8: =FS!I9/FS!I4 -> 0.27303591 | J8: 29 | K8: 25 | L8: 28 | M8: 27 | N8: 27 | O8: 27 | P8: 27 | Q8: 24.49
A9: USDJPY
A11: 2. Sales by Segment (億円) — historical actuals from deck
B12: FY24Q2 | C12: FY24Q3 | D12: FY24Q4 | E12: FY25Q1 | F12: FY25Q2 | G12: FY25Q3 | H12: FY25Q4 | I12: FY26Q1 | T12: FY24 | U12: FY25 | V12: FY26
A13: AutomaticControlEquipment | B13: 1922.8 | C13: 1953.99 | D13: 2016.48 | E13: 2001.8 | F13: 2000.92 | G13: 2096.61 | H13: 2326.08 | I13: 2709.87 | T13: =IF(COUNT(B13:D13)=0,"",SUM(B13:D13)) -> 5893.27 | U13: =IF(COUNT(E13:H13)=0,"",SUM(E13:H13)) -> 8425.41 | V13: =IF(COUNT(I13:L13)=0,"",SUM(I13:L13)) -> 2709.87 | W13: =IF(COUNT(M13:P13)=0,"",SUM(M13:P13)) | X13: =IF(COUNT(Q13:Q13)=0,"",SUM(Q13:Q13))
A14: TOTAL | B14: =SUM(B13:B13) -> 1922.8 | C14: =SUM(C13:C13) -> 1953.99 | D14: =SUM(D13:D13) -> 2016.48 | E14: =SUM(E13:E13) -> 2001.8 | F14: =SUM(F13:F13) -> 2000.92 | G14: =SUM(G13:G13) -> 2096.61 | H14: =SUM(H13:H13) -> 2326.08 | I14: =SUM(I13:I13) -> 2709.87 | T14: =IF(COUNT(B14:D14)=0,"",SUM(B14:D14)) -> 5893.27 | U14: =IF(COUNT(E14:H14)=0,"",SUM(E14:H14)) -> 8425.41 | V14: =IF(COUNT(I14:L14)=0,"",SUM(I14:L14)) -> 2709.87 | W14: =IF(COUNT(M14:P14)=0,"",SUM(M14:P14)) | X14: =IF(COUNT(Q14:Q14)=0,"",SUM(Q14:Q14))
A16: ↳ Segment OP (factbook 営業利益, 億)
A17: AutomaticControlEquipment OP | B17: 471.4 | C17: 433 | D17: 474.5 | E17: 444.6 | F17: 463.2 | G17: 467.8 | H17: 529.9 | I17: 739.9 | T17: =IF(COUNT(B17:D17)=0,"",SUM(B17:D17)) -> 1378.9 | U17: =IF(COUNT(E17:H17)=0,"",SUM(E17:H17)) -> 1905.5 | V17: =IF(COUNT(I17:L17)=0,"",SUM(I17:L17)) -> 739.9 | W17: =IF(COUNT(M17:P17)=0,"",SUM(M17:P17)) | X17: =IF(COUNT(Q17:Q17)=0,"",SUM(Q17:Q17))
A18: OP TOTAL (= consolidated) | B18: =SUM(B17:B17) -> 471.4 | C18: =SUM(C17:C17) -> 433 | D18: =SUM(D17:D17) -> 474.5 | E18: =SUM(E17:E17) -> 444.6 | F18: =SUM(F17:F17) -> 463.2 | G18: =SUM(G17:G17) -> 467.8 | H18: =SUM(H17:H17) -> 529.9 | I18: =SUM(I17:I17) -> 739.9 | T18: =IF(COUNT(B18:D18)=0,"",SUM(B18:D18)) -> 1378.9 | U18: =IF(COUNT(E18:H18)=0,"",SUM(E18:H18)) -> 1905.5 | V18: =IF(COUNT(I18:L18)=0,"",SUM(I18:L18)) -> 739.9 | W18: =IF(COUNT(M18:P18)=0,"",SUM(M18:P18)) | X18: =IF(COUNT(Q18:Q18)=0,"",SUM(Q18:Q18))
A20: 4. Sales by Region (億円)
B21: FY24Q2 | C21: FY24Q3 | D21: FY24Q4 | E21: FY25Q1 | F21: FY25Q2 | G21: FY25Q3 | H21: FY25Q4 | I21: FY26Q1 | T21: FY24 | U21: FY25 | V21: FY26
A22: Japan | T22: =IF(COUNT(B22:D22)=0,"",SUM(B22:D22)) | U22: =IF(COUNT(E22:H22)=0,"",SUM(E22:H22)) | V22: =IF(COUNT(I22:L22)=0,"",SUM(I22:L22)) | W22: =IF(COUNT(M22:P22)=0,"",SUM(M22:P22)) | X22: =IF(COUNT(Q22:Q22)=0,"",SUM(Q22:Q22))
A23: NorthAmerica | T23: =IF(COUNT(B23:D23)=0,"",SUM(B23:D23)) | U23: =IF(COUNT(E23:H23)=0,"",SUM(E23:H23)) | V23: =IF(COUNT(I23:L23)=0,"",SUM(I23:L23)) | W23: =IF(COUNT(M23:P23)=0,"",SUM(M23:P23)) | X23: =IF(COUNT(Q23:Q23)=0,"",SUM(Q23:Q23))
A24: Europe | T24: =IF(COUNT(B24:D24)=0,"",SUM(B24:D24)) | U24: =IF(COUNT(E24:H24)=0,"",SUM(E24:H24)) | V24: =IF(COUNT(I24:L24)=0,"",SUM(I24:L24)) | W24: =IF(COUNT(M24:P24)=0,"",SUM(M24:P24)) | X24: =IF(COUNT(Q24:Q24)=0,"",SUM(Q24:Q24))
A25: GreaterChina | T25: =IF(COUNT(B25:D25)=0,"",SUM(B25:D25)) | U25: =IF(COUNT(E25:H25)=0,"",SUM(E25:H25)) | V25: =IF(COUNT(I25:L25)=0,"",SUM(I25:L25)) | W25: =IF(COUNT(M25:P25)=0,"",SUM(M25:P25)) | X25: =IF(COUNT(Q25:Q25)=0,"",SUM(Q25:Q25))
A26: OtherAsia | T26: =IF(COUNT(B26:D26)=0,"",SUM(B26:D26)) | U26: =IF(COUNT(E26:H26)=0,"",SUM(E26:H26)) | V26: =IF(COUNT(I26:L26)=0,"",SUM(I26:L26)) | W26: =IF(COUNT(M26:P26)=0,"",SUM(M26:P26)) | X26: =IF(COUNT(Q26:Q26)=0,"",SUM(Q26:Q26))
A27: RestOfWorld | T27: =IF(COUNT(B27:D27)=0,"",SUM(B27:D27)) | U27: =IF(COUNT(E27:H27)=0,"",SUM(E27:H27)) | V27: =IF(COUNT(I27:L27)=0,"",SUM(I27:L27)) | W27: =IF(COUNT(M27:P27)=0,"",SUM(M27:P27)) | X27: =IF(COUNT(Q27:Q27)=0,"",SUM(Q27:Q27))
A28: TOTAL | B28: =SUM(B22:B27) -> 0 | C28: =SUM(C22:C27) -> 0 | D28: =SUM(D22:D27) -> 0 | E28: =SUM(E22:E27) -> 0 | F28: =SUM(F22:F27) -> 0 | G28: =SUM(G22:G27) -> 0 | H28: =SUM(H22:H27) -> 0 | I28: =SUM(I22:I27) -> 0 | T28: =IF(COUNT(B28:D28)=0,"",SUM(B28:D28)) -> 0 | U28: =IF(COUNT(E28:H28)=0,"",SUM(E28:H28)) -> 0 | V28: =IF(COUNT(I28:L28)=0,"",SUM(I28:L28)) -> 0 | W28: =IF(COUNT(M28:P28)=0,"",SUM(M28:P28)) | X28: =IF(COUNT(Q28:Q28)=0,"",SUM(Q28:Q28))
A31: 6. Margin Assumptions (OP = Sales × per-Q consolidated OPM)
A32: Per-Segment OPM (reference; consolidated PL)
A33: Segment | B33: OPM
A34: AutomaticControlEquipment | B34: 0.241
A36: Consolidated SG&A / Sales | B36: 0.195

Sheet FS
A1: P&L (億円, EPS in JPY) — BLUE=actual/input, BLACK=formula, GREEN=cross-sheet, ORANGE=guide
A3: Line Item | B3: FY24Q2 | C3: FY24Q3 | D3: FY24Q4 | E3: FY25Q1 | F3: FY25Q2 | G3: FY25Q3 | H3: FY25Q4 | I3: FY26Q1 | J3: FY26Q2 | K3: FY26Q3 | L3: FY26Q4 | M3: FY27Q1 | N3: FY27Q2 | O3: FY27Q3 | P3: FY27Q4 | Q3: FY28Q1 | T3: FY24 | U3: FY25 | V3: FY26 | W3: FY27 | X3: FY28 | Y3: FY26 GUIDE | Z3: Model vs Guide | AA3: Forecast Formula (plain English)
A4: Sales | B4: 1922.8 | C4: 1954 | D4: 2016.5 | E4: 2001.8 | F4: 2000.9 | G4: 2096.6 | H4: 2326.1 | I4: 2709.9 | J4: =I4*(1+-2.47/100) -> 2642.9655 | K4: =J4*(1+-0.1/100) -> 2640.3225 | L4: =K4*(1+6.85/100) -> 2821.1846 | M4: =L4*(1+2.9/100) -> 2902.9989 | N4: =M4*(1+-2.47/100) -> 2831.2949 | O4: =N4*(1+-0.16/100) -> 2826.7648 | P4: =O4*(1+6.8/100) -> 3018.9848 | Q4: =P4*(1+2.9/100) -> 3106.5354 | T4: =IF(COUNTBLANK(B4:D4)>0,"",SUM(B4:D4)) -> 5893.3 | U4: =IF(COUNTBLANK(E4:H4)>0,"",SUM(E4:H4)) -> 8425.4 | V4: =IF(COUNTBLANK(I4:L4)>0,"",SUM(I4:L4)) -> 10814.373 | W4: =IF(COUNTBLANK(M4:P4)>0,"",SUM(M4:P4)) -> 11580.043 | X4: =IF(COUNTBLANK(Q4:Q4)>0,"",SUM(Q4:Q4)) -> 3106.5354 | Y4: 10000 | Z4: =(J4+K4+L4+I4)/Y4-1 -> 0.081437257 | AA4: prior Sales × QoQ growth (mean of cfg.order_growth_qoq across segments)
A5: COGS | B5: =B4-B6 -> 1034.3 | C5: =C4-C6 -> 1089.3 | D5: =D4-D6 -> 1106.1 | E5: =E4-E6 -> 1115.3 | F5: =F4-F6 -> 1077 | G5: =G4-G6 -> 1141.8 | H5: =H4-H6 -> 1276.8 | I5: =I4-I6 -> 1440.6 | ... Q5: =Q4-Q6 -> 1739.9705 | T5: =IF(COUNTBLANK(B5:D5)>0,"",SUM(B5:D5)) -> 3229.7 | U5: =IF(COUNTBLANK(E5:H5)>0,"",SUM(E5:H5)) -> 4610.9 | V5: =IF(COUNTBLANK(I5:L5)>0,"",SUM(I5:L5)) -> 5626.661 | W5: =IF(COUNTBLANK(M5:P5)>0,"",SUM(M5:P5)) -> 6195.3232 | X5: =IF(COUNTBLANK(Q5:Q5)>0,"",SUM(Q5:Q5)) -> 1739.9705 | AA5: Sales − Gross Profit
A6: Gross Profit | B6: 888.5 | C6: 864.7 | D6: 910.4 | E6: 886.5 | F6: 923.9 | G6: 954.8 | H6: 1049.3 | I6: 1269.3 | J6: =J9+J8 -> 1321.4827 | K6: =K9+K8 -> 1214.5484 | L6: =L9+L8 -> 1382.3805 | M6: =M9+M8 -> 1349.8945 | N6: =N9+N8 -> 1316.5521 | O6: =O9+O8 -> 1314.4456 | P6: =P9+P8 -> 1403.8279 | Q6: =Q9+Q8 -> 1366.5649 | T6: =IF(COUNTBLANK(B6:D6)>0,"",SUM(B6:D6)) -> 2663.6 | U6: =IF(COUNTBLANK(E6:H6)>0,"",SUM(E6:H6)) -> 3814.5 | V6: =IF(COUNTBLANK(I6:L6)>0,"",SUM(I6:L6)) -> 5187.7115 | W6: =IF(COUNTBLANK(M6:P6)>0,"",SUM(M6:P6)) -> 5384.7202 | X6: =IF(COUNTBLANK(Q6:Q6)>0,"",SUM(Q6:Q6)) -> 1366.5649 | AA6: OP + SG&A (OPM-driven: GP is derived, not an input)
A7: GPM % | B7: =B6/B4*100 -> 46.208654 | C7: =C6/C4*100 -> 44.252815 | D7: =D6/D4*100 -> 45.147533 | E7: =E6/E4*100 -> 44.285143 | F7: =F6/F4*100 -> 46.174222 | G7: =G6/G4*100 -> 45.540399 | H7: =H6/H4*100 -> 45.109841 | I7: =I6/I4*100 -> 46.839367 | ... Q7: =Q6/Q4*100 -> 43.99 | T7: =IF(OR(COUNTBLANK(B6:D6)>0,COUNTBLANK(B4:D4)>0),"",SUM(B6:D6)/SUM(B4:D4)*100) -> 45.197088 | U7: =IF(OR(COUNTBLANK(E6:H6)>0,COUNTBLANK(E4:H4)>0),"",SUM(E6:H6)/SUM(E4:H4)*100) -> 45.273815 | V7: =IF(OR(COUNTBLANK(I6:L6)>0,COUNTBLANK(I4:L4)>0),"",SUM(I6:L6)/SUM(I4:L4)*100) -> 47.970527 | W7: =IF(OR(COUNTBLANK(M6:P6)>0,COUNTBLANK(M4:P4)>0),"",SUM(M6:P6)/SUM(M4:P4)*100) -> 46.5 | X7: =IF(OR(COUNTBLANK(Q6:Q6)>0,COUNTBLANK(Q4:Q4)>0),"",SUM(Q6:Q6)/SUM(Q4:Q4)*100) -> 43.99 | AA7: Gross Profit ÷ Sales
A8: SG&A | B8: =B6-B9 -> 417.1 | C8: =C6-C9 -> 431.7 | D8: =D6-D9 -> 435.9 | E8: =E6-E9 -> 441.9 | F8: =F6-F9 -> 460.7 | G8: =G6-G9 -> 487 | H8: =H6-H9 -> 519.4 | I8: =I6-I9 -> 529.4 | J8: =J4*0.21 -> 555.02275 | K8: =K4*0.21 -> 554.46773 | L8: =L4*0.21 -> 592.44877 | M8: =M4*0.195 -> 566.0848 | N8: =N4*0.195 -> 552.1025 | O8: =O4*0.195 -> 551.21914 | P8: =P4*0.195 -> 588.70204 | Q8: =Q4*0.195 -> 605.7744 | T8: =IF(COUNTBLANK(B8:D8)>0,"",SUM(B8:D8)) -> 1284.7 | U8: =IF(COUNTBLANK(E8:H8)>0,"",SUM(E8:H8)) -> 1909 | V8: =IF(COUNTBLANK(I8:L8)>0,"",SUM(I8:L8)) -> 2231.3392 | W8: =IF(COUNTBLANK(M8:P8)>0,"",SUM(M8:P8)) -> 2258.1085 | X8: =IF(COUNTBLANK(Q8:Q8)>0,"",SUM(Q8:Q8)) -> 605.7744 | AA8: Sales × 19.5% (yaml override (recent run-rate))
A9: Operating Profit | B9: 471.4 | C9: 433 | D9: 474.5 | E9: 444.6 | F9: 463.2 | G9: 467.8 | H9: 529.9 | I9: 739.9 | J9: =J4*Drivers!J8/100 -> 766.45999 | K9: =K4*Drivers!K8/100 -> 660.08063 | L9: =L4*Drivers!L8/100 -> 789.93169 | M9: =M4*Drivers!M8/100 -> 783.80972 | N9: =N4*Drivers!N8/100 -> 764.44962 | O9: =O4*Drivers!O8/100 -> 763.2265 | P9: =P4*Drivers!P8/100 -> 815.1259 | Q9: =Q4*Drivers!Q8/100 -> 760.79051 | T9: =IF(COUNTBLANK(B9:D9)>0,"",SUM(B9:D9)) -> 1378.9 | U9: =IF(COUNTBLANK(E9:H9)>0,"",SUM(E9:H9)) -> 1905.5 | V9: =IF(COUNTBLANK(I9:L9)>0,"",SUM(I9:L9)) -> 2956.3723 | W9: =IF(COUNTBLANK(M9:P9)>0,"",SUM(M9:P9)) -> 3126.6117 | X9: =IF(COUNTBLANK(Q9:Q9)>0,"",SUM(Q9:Q9)) -> 760.79051 | Y9: 2190 | Z9: =(J9+K9+L9+I9)/Y9-1 -> 0.34994169 | AA9: Sales × per-Q consolidated OPM (Drivers)
A10: OPM % | B10: =B9/B4*100 -> 24.51633 | C10: =C9/C4*100 -> 22.159672 | D10: =D9/D4*100 -> 23.53087 | E10: =E9/E4*100 -> 22.210011 | F10: =F9/F4*100 -> 23.149583 | G10: =G9/G4*100 -> 22.312315 | H10: =H9/H4*100 -> 22.78062 | I10: =I9/I4*100 -> 27.303591 | ... Q10: =Q9/Q4*100 -> 24.49 | T10: =IF(OR(COUNTBLANK(B9:D9)>0,COUNTBLANK(B4:D4)>0),"",SUM(B9:D9)/SUM(B4:D4)*100) -> 23.397757 | U10: =IF(OR(COUNTBLANK(E9:H9)>0,COUNTBLANK(E4:H4)>0),"",SUM(E9:H9)/SUM(E4:H4)*100) -> 22.616137 | V10: =IF(OR(COUNTBLANK(I9:L9)>0,COUNTBLANK(I4:L4)>0),"",SUM(I9:L9)/SUM(I4:L4)*100) -> 27.337437 | W10: =IF(OR(COUNTBLANK(M9:P9)>0,COUNTBLANK(M4:P4)>0),"",SUM(M9:P9)/SUM(M4:P4)*100) -> 27 | X10: =IF(OR(COUNTBLANK(Q9:Q9)>0,COUNTBLANK(Q4:Q4)>0),"",SUM(Q9:Q9)/SUM(Q4:Q4)*100) -> 24.49 | Y10: 21.9 | Z10: =(J9+K9+L9+M9)/(J4+K4+L4+M4)*100-Y10 -> 5.3567775 | AA10: OP ÷ Sales
A11: ± Non-Op / 特別 (net) | B11: =B12-B9 -> -112.6 | C11: =C12-C9 -> 193.5 | D11: =D12-D9 -> -29.8 | E11: =E12-E9 -> 50.5 | F11: =F12-F9 -> 147.2 | G11: =G12-G9 -> 149.4 | H11: =H12-H9 -> 117.2 | I11: =I12-I9 -> 198.3 | J11: 0 | K11: 0 | L11: 0 | M11: =M9*FS!$B$86/100 -> 164.60004 | N11: =N9*FS!$B$86/100 -> 160.53442 | O11: =O9*FS!$B$86/100 -> 160.27756 | P11: =P9*FS!$B$86/100 -> 171.17644 | Q11: =Q9*FS!$B$86/100 -> 159.76601 | T11: =IF(COUNTBLANK(B11:D11)>0,"",SUM(B11:D11)) -> 51.1 | U11: =IF(COUNTBLANK(E11:H11)>0,"",SUM(E11:H11)) -> 464.3 | V11: =IF(COUNTBLANK(I11:L11)>0,"",SUM(I11:L11)) -> 198.3 | W11: =IF(COUNTBLANK(M11:P11)>0,"",SUM(M11:P11)) -> 656.58846 | X11: =IF(COUNTBLANK(Q11:Q11)>0,"",SUM(Q11:Q11)) -> 159.76601 | AA11: Hist: Pretax−OP (実際 金融/持分法/特別); Fcst: OP × 21.0%
A12: Pretax Profit (税前) | B12: 358.8 | C12: 626.5 | D12: 444.7 | E12: 495.1 | F12: 610.4 | G12: 617.2 | H12: 647.1 | I12: 938.2 | J12: =J9+J11 -> 766.45999 | K12: =K9+K11 -> 660.08063 | L12: =L9+L11 -> 789.93169 | M12: =M9+M11 -> 948.40976 | N12: =N9+N11 -> 924.98404 | O12: =O9+O11 -> 923.50406 | P12: =P9+P11 -> 986.30234 | Q12: =Q9+Q11 -> 920.55652 | T12: =IF(COUNTBLANK(B12:D12)>0,"",SUM(B12:D12)) -> 1430 | U12: =IF(COUNTBLANK(E12:H12)>0,"",SUM(E12:H12)) -> 2369.8 | V12: =IF(COUNTBLANK(I12:L12)>0,"",SUM(I12:L12)) -> 3154.6723 | W12: =IF(COUNTBLANK(M12:P12)>0,"",SUM(M12:P12)) -> 3783.2002 | X12: =IF(COUNTBLANK(Q12:Q12)>0,"",SUM(Q12:Q12)) -> 920.55652 | Y12: 2390 | Z12: =(J12+K12+L12+I12)/Y12-1 -> 0.31994657 | AA12: Pretax (税前): Hist=disclosed actual; Fcst=OP + Non-Op
A13: Pretax M % | B13: =B12/B4*100 -> 18.660287 | C13: =C12/C4*100 -> 32.062436 | D13: =D12/D4*100 -> 22.053062 | E13: =E12/E4*100 -> 24.732741 | F13: =F12/F4*100 -> 30.506272 | G13: =G12/G4*100 -> 29.438138 | H13: =H12/H4*100 -> 27.819096 | I13: =I12/I4*100 -> 34.621204 | ... Q13: =Q12/Q4*100 -> 29.6329 | T13: =IF(OR(COUNTBLANK(B12:D12)>0,COUNTBLANK(B4:D4)>0),"",SUM(B12:D12)/SUM(B4:D4)*100) -> 24.264843 | U13: =IF(OR(COUNTBLANK(E12:H12)>0,COUNTBLANK(E4:H4)>0),"",SUM(E12:H12)/SUM(E4:H4)*100) -> 28.126855 | V13: =IF(OR(COUNTBLANK(I12:L12)>0,COUNTBLANK(I4:L4)>0),"",SUM(I12:L12)/SUM(I4:L4)*100) -> 29.171108 | W13: =IF(OR(COUNTBLANK(M12:P12)>0,COUNTBLANK(M4:P4)>0),"",SUM(M12:P12)/SUM(M4:P4)*100) -> 32.67 | X13: =IF(OR(COUNTBLANK(Q12:Q12)>0,COUNTBLANK(Q4:Q4)>0),"",SUM(Q12:Q12)/SUM(Q4:Q4)*100) -> 29.6329 | AA13: Pretax ÷ Sales
A14: − Income Tax | B14: 62.9 | C14: 204.6 | D14: 85.1 | E14: 148.7 | F14: 165 | G14: 192.8 | H14: 190.3 | I14: 259.5 | J14: =J12*FS!$B$85/100 -> 221.50694 | K14: =K12*FS!$B$85/100 -> 190.7633 | L14: =L12*FS!$B$85/100 -> 228.29026 | M14: =M12*FS!$B$85/100 -> 274.09042 | N14: =N12*FS!$B$85/100 -> 267.32039 | O14: =O12*FS!$B$85/100 -> 266.89267 | P14: =P12*FS!$B$85/100 -> 285.04138 | Q14: =Q12*FS!$B$85/100 -> 266.04083 | T14: =IF(COUNTBLANK(B14:D14)>0,"",SUM(B14:D14)) -> 352.6 | U14: =IF(COUNTBLANK(E14:H14)>0,"",SUM(E14:H14)) -> 696.8 | V14: =IF(COUNTBLANK(I14:L14)>0,"",SUM(I14:L14)) -> 900.06049 | W14: =IF(COUNTBLANK(M14:P14)>0,"",SUM(M14:P14)) -> 1093.3449 | X14: =IF(COUNTBLANK(Q14:Q14)>0,"",SUM(Q14:Q14)) -> 266.04083 | AA14: Hist: actual 法人税等; Fcst: Pretax × 28.2% (auto)
A15: Tax rate % | B15: =IF(B12=0,"",B14/B12*100) -> 17.530658 | C15: =IF(C12=0,"",C14/C12*100) -> 32.657622 | D15: =IF(D12=0,"",D14/D12*100) -> 19.136497 | E15: =IF(E12=0,"",E14/E12*100) -> 30.034336 | F15: =IF(F12=0,"",F14/F12*100) -> 27.031455 | G15: =IF(G12=0,"",G14/G12*100) -> 31.237848 | H15: =IF(H12=0,"",H14/H12*100) -> 29.408129 | I15: =IF(I12=0,"",I14/I12*100) -> 27.659348 | J15: =FS!$B$85 -> 28.9 | K15: =FS!$B$85 -> 28.9 | L15: =FS!$B$85 -> 28.9 | M15: =FS!$B$85 -> 28.9 | N15: =FS!$B$85 -> 28.9 | O15: =FS!$B$85 -> 28.9 | P15: =FS!$B$85 -> 28.9 | Q15: =FS!$B$85 -> 28.9 | T15: =IF(OR(COUNTBLANK(B14:D14)>0,COUNTBLANK(B12:D12)>0),"",SUM(B14:D14)/SUM(B12:D12)*100) -> 24.657343 | U15: =IF(OR(COUNTBLANK(E14:H14)>0,COUNTBLANK(E12:H12)>0),"",SUM(E14:H14)/SUM(E12:H12)*100) -> 29.403325 | V15: =IF(OR(COUNTBLANK(I14:L14)>0,COUNTBLANK(I12:L12)>0),"",SUM(I14:L14)/SUM(I12:L12)*100) -> 28.53103 | W15: =IF(OR(COUNTBLANK(M14:P14)>0,COUNTBLANK(M12:P12)>0),"",SUM(M14:P14)/SUM(M12:P12)*100) -> 28.9 | X15: =IF(OR(COUNTBLANK(Q14:Q14)>0,COUNTBLANK(Q12:Q12)>0),"",SUM(Q14:Q14)/SUM(Q12:Q12)*100) -> 28.9 | AA15: Hist: Income Tax ÷ Pretax (実効税率); Fcst: flat 28.2% assumption (Summary)
A16: − Minority Int. (NCI) | B16: =B12-B14-B18 -> 1.1 | C16: =C12-C14-C18 -> 0 | D16: =D12-D14-D18 -> 0 | E16: =E12-E14-E18 -> 0 | F16: =F12-F14-F18 -> 0 | G16: =G12-G14-G18 -> 0 | H16: =H12-H14-H18 -> 0 | I16: =I12-I14-I18 -> 0.1 | J16: =J12*FS!$B$101/100 -> 0 | K16: =K12*FS!$B$101/100 -> 0 | L16: =L12*FS!$B$101/100 -> 0 | M16: =M12*FS!$B$101/100 -> 0 | N16: =N12*FS!$B$101/100 -> 0 | O16: =O12*FS!$B$101/100 -> 0 | P16: =P12*FS!$B$101/100 -> 0 | Q16: =Q12*FS!$B$101/100 -> 0 | T16: =IF(COUNTBLANK(B16:D16)>0,"",SUM(B16:D16)) -> 1.1 | U16: =IF(COUNTBLANK(E16:H16)>0,"",SUM(E16:H16)) -> 0 | V16: =IF(COUNTBLANK(I16:L16)>0,"",SUM(I16:L16)) -> 0.1 | W16: =IF(COUNTBLANK(M16:P16)>0,"",SUM(M16:P16)) -> 0 | X16: =IF(COUNTBLANK(Q16:Q16)>0,"",SUM(Q16:Q16)) -> 0 | AA16: Hist: Pretax−Tax−NP; Fcst: Pretax × 0.0%
A18: Net Income | B18: 294.8 | C18: 421.9 | D18: 359.6 | E18: 346.4 | F18: 445.4 | G18: 424.4 | H18: 456.8 | I18: 678.6 | J18: =J12-J14-J16 -> 544.95305 | K18: =K12-K14-K16 -> 469.31733 | L18: =L12-L14-L16 -> 561.64143 | M18: =M12-M14-M16 -> 674.31934 | N18: =N12-N14-N16 -> 657.66365 | O18: =O12-O14-O16 -> 656.61139 | P18: =P12-P14-P16 -> 701.26096 | Q18: =Q12-Q14-Q16 -> 654.51569 | T18: =IF(COUNTBLANK(B18:D18)>0,"",SUM(B18:D18)) -> 1076.3 | U18: =IF(COUNTBLANK(E18:H18)>0,"",SUM(E18:H18)) -> 1673 | V18: =IF(COUNTBLANK(I18:L18)>0,"",SUM(I18:L18)) -> 2254.5118 | W18: =IF(COUNTBLANK(M18:P18)>0,"",SUM(M18:P18)) -> 2689.8553 | X18: =IF(COUNTBLANK(Q18:Q18)>0,"",SUM(Q18:Q18)) -> 654.51569 | Y18: 1700 | Z18: =(J18+K18+L18+I18)/Y18-1 -> 0.32618341 | AA18: Pretax − Tax − Minority (親会社株主帰属)
A19: NPM % | B19: =B18/B4*100 -> 15.331808 | C19: =C18/C4*100 -> 21.591607 | D19: =D18/D4*100 -> 17.832879 | E19: =E18/E4*100 -> 17.304426 | F19: =F18/F4*100 -> 22.259983 | G19: =G18/G4*100 -> 20.242297 | H19: =H18/H4*100 -> 19.638021 | I19: =I18/I4*100 -> 25.041514 | ... Q19: =Q18/Q4*100 -> 21.068992 | T19: =IF(OR(COUNTBLANK(B18:D18)>0,COUNTBLANK(B4:D4)>0),"",SUM(B18:D18)/SUM(B4:D4)*100) -> 18.263112 | U19: =IF(OR(COUNTBLANK(E18:H18)>0,COUNTBLANK(E4:H4)>0),"",SUM(E18:H18)/SUM(E4:H4)*100) -> 19.856624 | V19: =IF(OR(COUNTBLANK(I18:L18)>0,COUNTBLANK(I4:L4)>0),"",SUM(I18:L18)/SUM(I4:L4)*100) -> 20.847366 | W19: =IF(OR(COUNTBLANK(M18:P18)>0,COUNTBLANK(M4:P4)>0),"",SUM(M18:P18)/SUM(M4:P4)*100) -> 23.22837 | X19: =IF(OR(COUNTBLANK(Q18:Q18)>0,COUNTBLANK(Q4:Q4)>0),"",SUM(Q18:Q18)/SUM(Q4:Q4)*100) -> 21.068992 | AA19: NP ÷ Sales
A21: Diluted Shares (M) | B21: 64.1 | C21: 64 | D21: 64 | E21: 63.7 | F21: 63.6 | G21: 63.4 | H21: 63.4 | I21: 63.1 | J21: =I21-FS!J76*100/FS!$B$99 -> 62.912832 | K21: =J21-FS!K76*100/FS!$B$99 -> 62.725664 | L21: =K21-FS!L76*100/FS!$B$99 -> 62.538497 | M21: =L21-FS!M76*100/FS!$B$99 -> 62.351329 | N21: =M21-FS!N76*100/FS!$B$99 -> 62.164161 | O21: =N21-FS!O76*100/FS!$B$99 -> 61.976993 | P21: =O21-FS!P76*100/FS!$B$99 -> 61.789826 | Q21: =P21-FS!Q76*100/FS!$B$99 -> 61.602658 | T21: =IF(ISBLANK(D21),"",D21) -> 64 | U21: =IF(ISBLANK(H21),"",H21) -> 63.4 | V21: =IF(ISBLANK(L21),"",L21) -> 62.538497 | W21: =IF(ISBLANK(P21),"",P21) -> 61.789826 | X21: =IF(ISBLANK(Q21),"",Q21) -> 61.602658 | AA21: Hist: per-Q AvgSh from fins_summary; Fcst: prior − Buyback×100÷AvgPx (B26)
A22: EPS (¥) | B22: =B18*100/B21 -> 459.9064 | C22: =C18*100/C21 -> 659.21875 | D22: =D18*100/D21 -> 561.875 | E22: =E18*100/E21 -> 543.79906 | F22: =F18*100/F21 -> 700.31447 | G22: =G18*100/G21 -> 669.40063 | H22: =H18*100/H21 -> 720.50473 | I22: =I18*100/I21 -> 1075.4358 | ... Q22: =Q18*100/Q21 -> 1062.4796 | T22: =IF(COUNTBLANK(B22:D22)>0,"",SUM(B22:D22)) -> 1681.0001 | U22: =IF(COUNTBLANK(E22:H22)>0,"",SUM(E22:H22)) -> 2634.0189 | V22: =IF(COUNTBLANK(I22:L22)>0,"",SUM(I22:L22)) -> 3587.9185 | W22: =IF(COUNTBLANK(M22:P22)>0,"",SUM(M22:P22)) -> 4333.7872 | X22: =IF(COUNTBLANK(Q22:Q22)>0,"",SUM(Q22:Q22)) -> 1062.4796 | Y22: 2692.46 | Z22: =(J22+K22+L22+I22)/Y22-1 -> 0.33258006 | AA22: NP × 100 ÷ Shares (oku → yen)
A23: DPS (¥) | B23: 500 | C23: 0 | D23: 500 | E23: 0 | F23: 500 | G23: 0 | H23: 500 | I23: =I22*0.37 -> 397.91125 | J23: =J22*FS!$B$88/100 -> 320.49523 | K23: =K22*FS!$B$88/100 -> 276.8363 | L23: =L22*FS!$B$88/100 -> 332.28706 | M23: =M22*FS!$B$88/100 -> 400.1489 | N23: =N22*FS!$B$88/100 -> 391.44025 | O23: =O22*FS!$B$88/100 -> 391.99419 | P23: =P22*FS!$B$88/100 -> 419.91793 | Q23: =Q22*FS!$B$88/100 -> 393.11746 | T23: =IF(COUNTBLANK(B23:D23)>0,"",SUM(B23:D23)) -> 1000 | U23: =IF(COUNTBLANK(E23:H23)>0,"",SUM(E23:H23)) -> 1000 | V23: =IF(COUNTBLANK(I23:L23)>0,"",SUM(I23:L23)) -> 1327.5298 | W23: =IF(COUNTBLANK(M23:P23)>0,"",SUM(M23:P23)) -> 1603.5013 | X23: =IF(COUNTBLANK(Q23:Q23)>0,"",SUM(Q23:Q23)) -> 393.11746 | AA23: Disclosed DPS (実績/会社予想): interim@Q2, year-end@Q4; else EPS×payout
A24: Payout % | B24: =IF(B22=0,"",B23/B22*100) -> 108.71777 | C24: =IF(C22=0,"",C23/C22*100) -> 0 | D24: =IF(D22=0,"",D23/D22*100) -> 88.987764 | E24: =IF(E22=0,"",E23/E22*100) -> 0 | F24: =IF(F22=0,"",F23/F22*100) -> 71.396498 | G24: =IF(G22=0,"",G23/G22*100) -> 0 | H24: =IF(H22=0,"",H23/H22*100) -> 69.395797 | I24: =IF(I22=0,"",I23/I22*100) -> 37 | ... Q24: =IF(Q22=0,"",Q23/Q22*100) -> 37 | T24: =IF(OR(COUNTBLANK(B23:D23)>0,COUNTBLANK(B22:D22)>0),"",SUM(B23:D23)/SUM(B22:D22)*100) -> 59.488395 | U24: =IF(OR(COUNTBLANK(E23:H23)>0,COUNTBLANK(E22:H22)>0),"",SUM(E23:H23)/SUM(E22:H22)*100) -> 37.9648 | V24: =IF(OR(COUNTBLANK(I23:L23)>0,COUNTBLANK(I22:L22)>0),"",SUM(I23:L23)/SUM(I22:L22)*100) -> 37 | W24: =IF(OR(COUNTBLANK(M23:P23)>0,COUNTBLANK(M22:P22)>0),"",SUM(M23:P23)/SUM(M22:P22)*100) -> 37 | X24: =IF(OR(COUNTBLANK(Q23:Q23)>0,COUNTBLANK(Q22:Q22)>0),"",SUM(Q23:Q23)/SUM(Q22:Q22)*100) -> 37 | AA24: DPS ÷ EPS
A27: Balance Sheet (億) — BLUE=actual/input, BLACK=formula, GREEN=cross-sheet, ORANGE=guide/end-of-FY
A29: Line Item | B29: FY24Q2 | C29: FY24Q3 | D29: FY24Q4 | E29: FY25Q1 | F29: FY25Q2 | G29: FY25Q3 | H29: FY25Q4 | I29: FY26Q1 | J29: FY26Q2 | K29: FY26Q3 | L29: FY26Q4 | M29: FY27Q1 | N29: FY27Q2 | O29: FY27Q3 | P29: FY27Q4 | Q29: FY28Q1 | T29: FY24 | U29: FY25 | V29: FY26 | W29: FY27 | X29: FY28 | Y29: FY26 EoFY | AA29: Forecast Formula (plain English)
A30: Cash & Equivalents | B30: 5213.6 | C30: 5666.4 | D30: 6557.8 | E30: 6691.4 | F30: 6599.7 | G30: 6557.4 | H30: 6638.7 | I30: 7110.9 | J30: =I30+FS!J63+FS!J64+FS!J65 -> 7721.3017 | K30: =J30+FS!K63+FS!K64+FS!K65 -> 7479.0903 | L30: =K30+FS!L63+FS!L64+FS!L65 -> 7411.3751 | M30: =L30+FS!M63+FS!M64+FS!M65 -> 7185.1067 | N30: =M30+FS!N63+FS!N64+FS!N65 -> 7601.9924 | O30: =N30+FS!O63+FS!O64+FS!O65 -> 7835.5796 | P30: =O30+FS!P63+FS!P64+FS!P65 -> 7558.7833 | Q30: =P30+FS!Q63+FS!Q64+FS!Q65 -> 7287.2188 | T30: =IF(ISBLANK(D30),"",D30) -> 6557.8 | U30: =IF(ISBLANK(H30),"",H30) -> 6638.7 | V30: =IF(ISBLANK(L30),"",L30) -> 7411.3751 | W30: =IF(ISBLANK(P30),"",P30) -> 7558.7833 | X30: =IF(ISBLANK(Q30),"",Q30) -> 7287.2188 | Y30: =Q30 -> 7287.2188 | AA30: Prior Cash + OCF + ICF + Financing CF (rolled from CF sheet; NOT Free CF — that is the separate OCF+ICF row)
A31: Trade Receivables | B31: 1978 | C31: 2063.1 | D31: 2079.7 | E31: 2077.4 | F31: 2022.7 | G31: 2141.9 | H31: 2353.2 | I31: 2714.3 | J31: =J55*FS!J4/91 -> 2642.9655 | K31: =K55*FS!K4/91 -> 2640.3225 | L31: =L55*FS!L4/91 -> 2821.1846 | M31: =M55*FS!M4/91 -> 2902.9989 | N31: =N55*FS!N4/91 -> 2831.2949 | O31: =O55*FS!O4/91 -> 2826.7648 | P31: =P55*FS!P4/91 -> 3018.9848 | Q31: =Q55*FS!Q4/91 -> 3106.5354 | T31: =IF(ISBLANK(D31),"",D31) -> 2079.7 | U31: =IF(ISBLANK(H31),"",H31) -> 2353.2 | V31: =IF(ISBLANK(L31),"",L31) -> 2821.1846 | W31: =IF(ISBLANK(P31),"",P31) -> 3018.9848 | X31: =IF(ISBLANK(Q31),"",Q31) -> 3106.5354 | AA31: Sales × DSO / 91 (or actual when available)
A32: Inventory | B32: 5059.6 | C32: 5174.1 | D32: 4896.6 | E32: 4834.7 | F32: 4876.3 | G32: 5082.3 | H32: 5067 | I32: 5132.1 | J32: =J56*FS!J5/91 -> 4705.0594 | K32: =K56*FS!K5/91 -> 5076.3827 | L32: =L56*FS!L5/91 -> 5122.7752 | M32: =M56*FS!M5/91 -> 5529.7345 | N32: =N56*FS!N5/91 -> 5393.15 | O32: =O56*FS!O5/91 -> 5384.521 | P32: =P56*FS!P5/91 -> 5750.6684 | Q32: =Q56*FS!Q5/91 -> 6195.0597 | T32: =IF(ISBLANK(D32),"",D32) -> 4896.6 | U32: =IF(ISBLANK(H32),"",H32) -> 5067 | V32: =IF(ISBLANK(L32),"",L32) -> 5122.7752 | W32: =IF(ISBLANK(P32),"",P32) -> 5750.6684 | X32: =IF(ISBLANK(Q32),"",Q32) -> 6195.0597 | AA32: COGS × DIO / 91
A33: Other CA | B33: 1261.4 | C33: 697.7 | D33: 684.3 | E33: 808.9 | F33: 898.4 | G33: 923 | H33: 984 | I33: 895.6 | J33: =I33 -> 895.6 | K33: =J33 -> 895.6 | L33: =K33 -> 895.6 | M33: =L33 -> 895.6 | N33: =M33 -> 895.6 | O33: =N33 -> 895.6 | P33: =O33 -> 895.6 | Q33: =P33 -> 895.6 | T33: =IF(ISBLANK(D33),"",D33) -> 684.3 | U33: =IF(ISBLANK(H33),"",H33) -> 984 | V33: =IF(ISBLANK(L33),"",L33) -> 895.6 | W33: =IF(ISBLANK(P33),"",P33) -> 895.6 | X33: =IF(ISBLANK(Q33),"",Q33) -> 895.6 | AA33: Held constant from prior (roll-forward, NOT zeroed)
A34: Current Assets | B34: =B30+B31+B32+B33 -> 13512.6 | C34: =C30+C31+C32+C33 -> 13601.3 | D34: =D30+D31+D32+D33 -> 14218.4 | E34: =E30+E31+E32+E33 -> 14412.4 | F34: =F30+F31+F32+F33 -> 14397.1 | G34: =G30+G31+G32+G33 -> 14704.6 | H34: =H30+H31+H32+H33 -> 15042.9 | I34: =I30+I31+I32+I33 -> 15852.9 | ... Q34: =Q30+Q31+Q32+Q33 -> 17484.414 | T34: =IF(ISBLANK(D34),"",D34) -> 14218.4 | U34: =IF(ISBLANK(H34),"",H34) -> 15042.9 | V34: =IF(ISBLANK(L34),"",L34) -> 16250.935 | W34: =IF(ISBLANK(P34),"",P34) -> 17224.037 | X34: =IF(ISBLANK(Q34),"",Q34) -> 17484.414 | AA34: Cash + AR + Inv + OtherCA
A36: PPE (rolled) | B36: 4312.6 | C36: 4732.6 | D36: 4787.2 | E36: 5254.6 | F36: 5878.4 | G36: 6064.8 | H36: 6180.1 | I36: 6243.1 | J36: =I36-FS!J64-I36*FS!$B$100 -> 6320.2822 | K36: =J36-FS!K64-J36*FS!$B$100 -> 6395.4267 | L36: =K36-FS!L64-K36*FS!$B$100 -> 6468.5874 | M36: =L36-FS!M64-L36*FS!$B$100 -> 6539.8167 | N36: =M36-FS!N64-M36*FS!$B$100 -> 6609.1656 | O36: =N36-FS!O64-N36*FS!$B$100 -> 6676.6836 | P36: =O36-FS!P64-O36*FS!$B$100 -> 6742.4192 | Q36: =P36-FS!Q64-P36*FS!$B$100 -> 6806.4193 | T36: =IF(ISBLANK(D36),"",D36) -> 4787.2 | U36: =IF(ISBLANK(H36),"",H36) -> 6180.1 | V36: =IF(ISBLANK(L36),"",L36) -> 6468.5874 | W36: =IF(ISBLANK(P36),"",P36) -> 6742.4192 | X36: =IF(ISBLANK(Q36),"",Q36) -> 6806.4193 | AA36: Prior PPE + Capex − D&A (Prior PPE × 2.64%/Q (calibrated to the disclosed guide 165億/Q at the latest PPE; rises with PPE thereafter))
A37: Other NCA | B37: =B38-B34-B36 -> 2791.4 | C37: =C38-C34-C36 -> 2911.8 | D37: =D38-D34-D36 -> 2002.1 | E37: =E38-E34-E36 -> 1398.4 | F37: =F38-F34-F36 -> 1710.5 | G37: =G38-G34-G36 -> 1781.8 | H37: =H38-H34-H36 -> 1895.4 | I37: =I38-I34-I36 -> 1589.8 | J37: =I37 -> 1589.8 | K37: =J37 -> 1589.8 | L37: =K37 -> 1589.8 | M37: =L37 -> 1589.8 | N37: =M37 -> 1589.8 | O37: =N37 -> 1589.8 | P37: =O37 -> 1589.8 | Q37: =P37 -> 1589.8 | T37: =IF(ISBLANK(D37),"",D37) -> 2002.1 | U37: =IF(ISBLANK(H37),"",H37) -> 1895.4 | V37: =IF(ISBLANK(L37),"",L37) -> 1589.8 | W37: =IF(ISBLANK(P37),"",P37) -> 1589.8 | X37: =IF(ISBLANK(Q37),"",Q37) -> 1589.8 | AA37: Held constant from prior
A38: TOTAL ASSETS | B38: 20616.6 | C38: 21245.7 | D38: 21007.7 | E38: 21065.4 | F38: 21986 | G38: 22551.2 | H38: 23118.4 | I38: 23685.8 | J38: =J34+J36+J37 -> 23875.009 | K38: =K34+K36+K37 -> 24076.622 | L38: =L34+L36+L37 -> 24309.322 | M38: =M34+M36+M37 -> 24643.057 | N38: =N34+N36+N37 -> 24921.003 | O38: =O34+O36+O37 -> 25208.949 | P38: =P34+P36+P37 -> 25556.256 | Q38: =Q34+Q36+Q37 -> 25880.633 | T38: =IF(ISBLANK(D38),"",D38) -> 21007.7 | U38: =IF(ISBLANK(H38),"",H38) -> 23118.4 | V38: =IF(ISBLANK(L38),"",L38) -> 24309.322 | W38: =IF(ISBLANK(P38),"",P38) -> 25556.256 | X38: =IF(ISBLANK(Q38),"",Q38) -> 25880.633 | Y38: =Q38 -> 25880.633 | AA38: CA + PPE + OtherNCA
A40: Trade Payables | B40: 482.8 | C40: 529.8 | D40: 469 | E40: 519.9 | F40: 501.8 | G40: 356.3 | H40: 318.2 | I40: 421.2 | J40: =J57*FS!J5/91 -> 392.08828 | K40: =K57*FS!K5/91 -> 423.03189 | L40: =L57*FS!L5/91 -> 426.89793 | M40: =M57*FS!M5/91 -> 460.81121 | N40: =N57*FS!N5/91 -> 449.42917 | O40: =O57*FS!O5/91 -> 448.71008 | P40: =P57*FS!P5/91 -> 479.22237 | Q40: =Q57*FS!Q5/91 -> 516.25497 | T40: =IF(ISBLANK(D40),"",D40) -> 469 | U40: =IF(ISBLANK(H40),"",H40) -> 318.2 | V40: =IF(ISBLANK(L40),"",L40) -> 426.89793 | W40: =IF(ISBLANK(P40),"",P40) -> 479.22237 | X40: =IF(ISBLANK(Q40),"",Q40) -> 516.25497 | AA40: COGS × DPO / 91 (or actual)
A41: Debt | B41: 119.4 | C41: 50.4 | D41: 50.4 | E41: 50 | F41: 50 | G41: 350.9 | H41: 50.9 | I41: 50 | J41: =I41+FS!J77 -> 50 | K41: =J41+FS!K77 -> 50 | L41: =K41+FS!L77 -> 50 | M41: =L41+FS!M77 -> 50 | N41: =M41+FS!N77 -> 50 | O41: =N41+FS!O77 -> 50 | P41: =O41+FS!P77 -> 50 | Q41: =P41+FS!Q77 -> 50 | T41: =IF(ISBLANK(D41),"",D41) -> 50.4 | U41: =IF(ISBLANK(H41),"",H41) -> 50.9 | V41: =IF(ISBLANK(L41),"",L41) -> 50 | W41: =IF(ISBLANK(P41),"",P41) -> 50 | X41: =IF(ISBLANK(Q41),"",Q41) -> 50 | AA41: Prior Debt + Net Debt Issuance (held flat unless a schedule is set)
A42: Other Liab | B42: =B43-B40-B41 -> 1227.6 | C42: =C43-C40-C41 -> 1206.5 | D42: =D43-D40-D41 -> 1205.2 | E42: =E43-E40-E41 -> 1308.3 | F42: =F43-F40-F41 -> 1699.4 | G42: =G43-G40-G41 -> 1420.3 | H42: =H43-H40-H41 -> 1596.9 | I42: =I43-I40-I41 -> 1666.3 | J42: =I42 -> 1666.3 | K42: =J42 -> 1666.3 | L42: =K42 -> 1666.3 | M42: =L42 -> 1666.3 | N42: =M42 -> 1666.3 | O42: =N42 -> 1666.3 | P42: =O42 -> 1666.3 | Q42: =P42 -> 1666.3 | T42: =IF(ISBLANK(D42),"",D42) -> 1205.2 | U42: =IF(ISBLANK(H42),"",H42) -> 1596.9 | V42: =IF(ISBLANK(L42),"",L42) -> 1666.3 | W42: =IF(ISBLANK(P42),"",P42) -> 1666.3 | X42: =IF(ISBLANK(Q42),"",Q42) -> 1666.3 | AA42: Held constant from prior (roll-forward)
A43: TOTAL LIAB | B43: 1829.8 | C43: 1786.7 | D43: 1724.6 | E43: 1878.2 | F43: 2251.2 | G43: 2127.5 | H43: 1966 | I43: 2137.5 | J43: =J40+J41+J42 -> 2108.3883 | K43: =K40+K41+K42 -> 2139.3319 | L43: =L40+L41+L42 -> 2143.1979 | M43: =M40+M41+M42 -> 2177.1112 | N43: =N40+N41+N42 -> 2165.7292 | O43: =O40+O41+O42 -> 2165.0101 | P43: =P40+P41+P42 -> 2195.5224 | Q43: =Q40+Q41+Q42 -> 2232.555 | T43: =IF(ISBLANK(D43),"",D43) -> 1724.6 | U43: =IF(ISBLANK(H43),"",H43) -> 1966 | V43: =IF(ISBLANK(L43),"",L43) -> 2143.1979 | W43: =IF(ISBLANK(P43),"",P43) -> 2195.5224 | X43: =IF(ISBLANK(Q43),"",Q43) -> 2232.555 | AA43: AP + Debt + OtherL (independent components)
A45: Shareholders Eq | B45: 18781.7 | C45: 19461 | D45: 19285 | E45: 19190.6 | F45: 19743.4 | G45: 20431.4 | H45: 21153.3 | I45: 21554 | J45: =I45+FS!J18-FS!J23*FS!J21/100-FS!J76 -> 21772.32 | K45: =J45+FS!K18-FS!K23*FS!K21/100-FS!K76 -> 21942.99 | L45: =K45+FS!L18-FS!L23*FS!L21/100-FS!L76 -> 22171.824 | M45: =L45+FS!M18-FS!M23*FS!M21/100-FS!M76 -> 22471.646 | N45: =M45+FS!N18-FS!N23*FS!N21/100-FS!N76 -> 22760.974 | O45: =N45+FS!O18-FS!O23*FS!O21/100-FS!O76 -> 23049.639 | P45: =O45+FS!P18-FS!P23*FS!P21/100-FS!P76 -> 23366.433 | Q45: =P45+FS!Q18-FS!Q23*FS!Q21/100-FS!Q76 -> 23653.778 | T45: =IF(ISBLANK(D45),"",D45) -> 19285 | U45: =IF(ISBLANK(H45),"",H45) -> 21153.3 | V45: =IF(ISBLANK(L45),"",L45) -> 22171.824 | W45: =IF(ISBLANK(P45),"",P45) -> 23366.433 | X45: =IF(ISBLANK(Q45),"",Q45) -> 23653.778 | Y45: =Q45 -> 23653.778 | AA45: Prior Eq + NI − Dividends − Buyback
A46: Retained Earnings | B46: 17624.7 | C46: 17726.7 | D46: 18086.3 | E46: 16084.6 | F46: 16530.4 | G46: 16642.4 | H46: 17099.4 | I46: 17462.2 | J46: =I46+FS!J18-FS!J75-FS!J76 -> 17680.52 | K46: =J46+FS!K18-FS!K75-FS!K76 -> 17851.19 | L46: =K46+FS!L18-FS!L75-FS!L76 -> 18080.024 | M46: =L46+FS!M18-FS!M75-FS!M76 -> 18379.846 | N46: =M46+FS!N18-FS!N75-FS!N76 -> 18669.174 | O46: =N46+FS!O18-FS!O75-FS!O76 -> 18957.839 | P46: =O46+FS!P18-FS!P75-FS!P76 -> 19274.633 | Q46: =P46+FS!Q18-FS!Q75-FS!Q76 -> 19561.978 | T46: =IF(ISBLANK(D46),"",D46) -> 18086.3 | U46: =IF(ISBLANK(H46),"",H46) -> 17099.4 | V46: =IF(ISBLANK(L46),"",L46) -> 18080.024 | W46: =IF(ISBLANK(P46),"",P46) -> 19274.633 | X46: =IF(ISBLANK(Q46),"",Q46) -> 19561.978 | AA46: Prior RE + NI − Dividends − Buyback
A47: Non-controlling | B47: 5.1 | C47: -2.1 | D47: -2 | E47: -3.4 | F47: -8.6 | G47: -7.7 | H47: -0.9 | I47: -5.8 | J47: =I47 -> -5.8 | K47: =J47 -> -5.8 | L47: =K47 -> -5.8 | M47: =L47 -> -5.8 | N47: =M47 -> -5.8 | O47: =N47 -> -5.8 | P47: =O47 -> -5.8 | Q47: =P47 -> -5.8 | T47: =IF(ISBLANK(D47),"",D47) -> -2 | U47: =IF(ISBLANK(H47),"",H47) -> -0.9 | V47: =IF(ISBLANK(L47),"",L47) -> -5.8 | W47: =IF(ISBLANK(P47),"",P47) -> -5.8 | X47: =IF(ISBLANK(Q47),"",Q47) -> -5.8 | AA47: Held constant from prior (roll-forward, NOT zeroed)
A48: TOTAL EQUITY | B48: =B45+B47 -> 18786.8 | C48: =C45+C47 -> 19458.9 | D48: =D45+D47 -> 19283 | E48: =E45+E47 -> 19187.2 | F48: =F45+F47 -> 19734.8 | G48: =G45+G47 -> 20423.7 | H48: =H45+H47 -> 21152.4 | I48: =I45+I47 -> 21548.2 | ... Q48: =Q45+Q47 -> 23647.978 | T48: =IF(ISBLANK(D48),"",D48) -> 19283 | U48: =IF(ISBLANK(H48),"",H48) -> 21152.4 | V48: =IF(ISBLANK(L48),"",L48) -> 22166.024 | W48: =IF(ISBLANK(P48),"",P48) -> 23360.633 | X48: =IF(ISBLANK(Q48),"",Q48) -> 23647.978 | AA48: Eq + NCI
A50: BS Check (TA-TL-TE) | B50: =B38-B43-B48 -> 0 | C50: =C38-C43-C48 -> 0.1 | D50: =D38-D43-D48 -> 0.1 | E50: =E38-E43-E48 -> 0 | F50: =F38-F43-F48 -> 0 | G50: =G38-G43-G48 -> 0 | H50: =H38-H43-H48 -> 0 | I50: =I38-I43-I48 -> 0.1 | ... Q50: =Q38-Q43-Q48 -> 0.1 | AA50: TA − TL − TE (must = 0; non-zero ⇒ roll-forward inconsistency)
A53: WC Days (Historical = formula from BS÷PL; Forecast = key input)
B54: FY24Q2 | C54: FY24Q3 | D54: FY24Q4 | E54: FY25Q1 | F54: FY25Q2 | G54: FY25Q3 | H54: FY25Q4 | I54: FY26Q1 | J54: FY26Q2 | K54: FY26Q3 | L54: FY26Q4 | M54: FY27Q1 | N54: FY27Q2 | O54: FY27Q3 | P54: FY27Q4 | Q54: FY28Q1 | T54: FY24 | U54: FY25 | V54: FY26 | W54: FY27 | X54: FY28
A55: DSO (AR÷Sales×91) | B55: =FS!B31/FS!B4*91 -> 93.61244 | C55: =FS!C31/FS!C4*91 -> 96.080911 | D55: =FS!D31/FS!D4*91 -> 93.85207 | E55: =FS!E31/FS!E4*91 -> 94.436707 | F55: =FS!F31/FS!F4*91 -> 91.991454 | G55: =FS!G31/FS!G4*91 -> 92.966183 | H55: =FS!H31/FS!H4*91 -> 92.060187 | I55: =FS!I31/FS!I4*91 -> 91.147755 | J55: =FS!$B$92 -> 91 | K55: =FS!$B$92 -> 91 | L55: =FS!$B$92 -> 91 | M55: =FS!$B$92 -> 91 | N55: =FS!$B$92 -> 91 | O55: =FS!$B$92 -> 91 | P55: =FS!$B$92 -> 91 | Q55: =FS!$B$92 -> 91 | T55: =IF(ISBLANK(D55),"",D55) -> 93.85207 | U55: =IF(ISBLANK(H55),"",H55) -> 92.060187 | V55: =IF(ISBLANK(L55),"",L55) -> 91 | W55: =IF(ISBLANK(P55),"",P55) -> 91 | X55: =IF(ISBLANK(Q55),"",Q55) -> 91 | AA55: Key user input (yellow); historical = AR ÷ Sales × 91
A56: DIO (Inv÷COGS×91) | B56: =FS!B32/FS!B5*91 -> 445.15479 | C56: =FS!C32/FS!C5*91 -> 432.24373 | D56: =FS!D32/FS!D5*91 -> 402.84839 | E56: =FS!E32/FS!E5*91 -> 394.47476 | F56: =FS!F32/FS!F5*91 -> 412.01792 | G56: =FS!G32/FS!G5*91 -> 405.05281 | H56: =FS!H32/FS!H5*91 -> 361.13487 | I56: =FS!I32/FS!I5*91 -> 324.18513 | J56: =FS!$B$93 -> 324 | K56: =FS!$B$93 -> 324 | L56: =FS!$B$93 -> 324 | M56: =FS!$B$93 -> 324 | N56: =FS!$B$93 -> 324 | O56: =FS!$B$93 -> 324 | P56: =FS!$B$93 -> 324 | Q56: =FS!$B$93 -> 324 | T56: =IF(ISBLANK(D56),"",D56) -> 402.84839 | U56: =IF(ISBLANK(H56),"",H56) -> 361.13487 | V56: =IF(ISBLANK(L56),"",L56) -> 324 | W56: =IF(ISBLANK(P56),"",P56) -> 324 | X56: =IF(ISBLANK(Q56),"",Q56) -> 324 | AA56: Key user input (yellow); historical = Inv ÷ COGS × 91
A57: DPO (AP÷COGS×91) | B57: =FS!B40/FS!B5*91 -> 42.477811 | C57: =FS!C40/FS!C5*91 -> 44.259433 | D57: =FS!D40/FS!D5*91 -> 38.585119 | E57: =FS!E40/FS!E5*91 -> 42.419887 | F57: =FS!F40/FS!F5*91 -> 42.399071 | G57: =FS!G40/FS!G5*91 -> 28.396654 | H57: =FS!H40/FS!H5*91 -> 22.678728 | I57: =FS!I40/FS!I5*91 -> 26.606414 | J57: =FS!$B$94 -> 27 | K57: =FS!$B$94 -> 27 | L57: =FS!$B$94 -> 27 | M57: =FS!$B$94 -> 27 | N57: =FS!$B$94 -> 27 | O57: =FS!$B$94 -> 27 | P57: =FS!$B$94 -> 27 | Q57: =FS!$B$94 -> 27 | T57: =IF(ISBLANK(D57),"",D57) -> 38.585119 | U57: =IF(ISBLANK(H57),"",H57) -> 22.678728 | V57: =IF(ISBLANK(L57),"",L57) -> 27 | W57: =IF(ISBLANK(P57),"",P57) -> 27 | X57: =IF(ISBLANK(Q57),"",Q57) -> 27 | AA57: Key user input (yellow); historical = AP ÷ COGS × 91
A60: Cash Flow (億) — JP cos report CF only at H1+FY. BLUE=actual, BLACK=formula, GREEN=cross-sheet, ORANGE=disclosed-FY.
A62: Line Item | B62: FY24Q2 | C62: FY24Q3 | D62: FY24Q4 | E62: FY25Q1 | F62: FY25Q2 | G62: FY25Q3 | H62: FY25Q4 | I62: FY26Q1 | J62: FY26Q2 | K62: FY26Q3 | L62: FY26Q4 | M62: FY27Q1 | N62: FY27Q2 | O62: FY27Q3 | P62: FY27Q4 | Q62: FY28Q1 | T62: FY24 | U62: FY25 | V62: FY26 | W62: FY27 | X62: FY28 | Y62: FY26 TOTAL | AA62: Forecast Formula (plain English)
A63: OCF (営業CF) | B63: 979.9 | C63: =FS!C18+FS!B36*FS!$B$100-(FS!C31-FS!B31)-(FS!C32-FS!B32)+(FS!C40-FS!B40) -> 383.15264 | D63: 1966.6 | E63: =FS!E18+FS!D36*FS!$B$100-(FS!E31-FS!D31)-(FS!E32-FS!D32)+(FS!E40-FS!D40) -> 587.88208 | F63: 1186.6 | G63: =FS!G18+FS!F36*FS!$B$100-(FS!G31-FS!F31)-(FS!G32-FS!F32)+(FS!G40-FS!F40) -> 108.88976 | H63: 1889.2 | I63: =FS!I18+FS!H36*FS!$B$100-(FS!I31-FS!H31)-(FS!I32-FS!H32)+(FS!I40-FS!H40) -> 518.55464 | J63: =J69+J70+J71 -> 1179.0343 | K63: =K69+K70+K71 -> 298.43606 | L63: =L69+L70+L71 -> 507.09215 | M63: =M69+M70+M71 -> 390.22968 | N63: =N69+N70+N71 -> 1027.2213 | O63: =O69+O70+O71 -> 843.53338 | P63: =P69+P70+P71 -> 349.67026 | Q63: =Q69+Q70+Q71 -> 337.60636 | T63: 1966.6 | U63: 1889.2 | V63: =IF(AND(ISBLANK(J63),ISBLANK(L63)),"",SUM(I63:L63)) -> 2503.1171 | W63: =IF(AND(ISBLANK(N63),ISBLANK(P63)),"",SUM(M63:P63)) -> 2610.6546 | X63: =IF(COUNTBLANK(Q63:Q63)>0,"",SUM(Q63:Q63)) -> 337.60636 | Y63: =J63+K63+L63+M63+N63+O63+P63+Q63 -> 4932.8235 | AA63: NI + D&A + ΔWC
A64: ICF (投資CF) | B64: -580.4 | C64: =-$B$80 -> -242 | D64: 352.3 | E64: =-$B$80 -> -242 | F64: -666.3 | G64: =-$B$80 -> -242 | H64: -1075.1 | I64: =-$B$80 -> -242 | J64: =-J73 -> -242 | K64: =-K73 -> -242 | L64: =-L73 -> -242 | M64: =-M73 -> -242 | N64: =-N73 -> -242 | O64: =-O73 -> -242 | P64: =-P73 -> -242 | Q64: =-Q73 -> -242 | T64: 352.3 | U64: -1075.1 | V64: =IF(AND(ISBLANK(J64),ISBLANK(L64)),"",SUM(I64:L64)) -> -968 | W64: =IF(AND(ISBLANK(N64),ISBLANK(P64)),"",SUM(M64:P64)) -> -968 | X64: =IF(COUNTBLANK(Q64:Q64)>0,"",SUM(Q64:Q64)) -> -242 | Y64: =J64+K64+L64+M64+N64+O64+P64+Q64 -> -1936 | AA64: − Capex
A65: Financing CF (財務CF) | B65: -459.1 | C65: =-FS!C23*FS!C21/100-$B$81 -> -125 | D65: -1002 | E65: =-FS!E23*FS!E21/100-$B$81 -> -125 | F65: -541.1 | G65: =-FS!G23*FS!G21/100-$B$81 -> -125 | H65: -941.2 | I65: =-FS!I23*FS!I21/100-$B$81 -> -376.082 | J65: =-J75-J76+J77 -> -326.63263 | K65: =-K75-K76+K77 -> -298.64741 | L65: =-L75-L76+L77 -> -332.80733 | M65: =-M75-M76+M77 -> -374.49815 | N65: =-N75-N76+N77 -> -368.33555 | O65: =-O75-O76+O77 -> -367.94621 | P65: =-P75-P76+P77 -> -384.46656 | Q65: =-Q75-Q76+Q77 -> -367.1708 | T65: -1002 | U65: -941.2 | V65: =IF(AND(ISBLANK(J65),ISBLANK(L65)),"",SUM(I65:L65)) -> -1334.1694 | W65: =IF(AND(ISBLANK(N65),ISBLANK(P65)),"",SUM(M65:P65)) -> -1495.2465 | X65: =IF(COUNTBLANK(Q65:Q65)>0,"",SUM(Q65:Q65)) -> -367.1708 | Y65: =J65+K65+L65+M65+N65+O65+P65+Q65 -> -2820.5046 | AA65: Financing CF (財務CF): − Dividends − Buyback + Net Debt Issuance
A66: Net Δcash | B66: =B63+B64+B65 -> -59.6 | C66: =C63+C64+C65 -> 16.15264 | D66: =D63+D64+D65 -> 1316.9 | E66: =E63+E64+E65 -> 220.88208 | F66: =F63+F64+F65 -> -20.8 | G66: =G63+G64+G65 -> -258.11024 | H66: =H63+H64+H65 -> -127.1 | I66: =I63+I64+I65 -> -99.52736 | ... Q66: =Q63+Q64+Q65 -> -271.56444 | T66: =IF(COUNTBLANK(B66:D66)>0,"",SUM(B66:D66)) -> 1273.4526 | U66: =IF(AND(ISBLANK(F66),ISBLANK(H66)),"",SUM(E66:H66)) -> -185.12816 | V66: =IF(AND(ISBLANK(J66),ISBLANK(L66)),"",SUM(I66:L66)) -> 200.94777 | W66: =IF(AND(ISBLANK(N66),ISBLANK(P66)),"",SUM(M66:P66)) -> 147.40814 | X66: =IF(COUNTBLANK(Q66:Q66)>0,"",SUM(Q66:Q66)) -> -271.56444 | Y66: =J66+K66+L66+M66+N66+O66+P66+Q66 -> 176.31883 | AA66: OCF + ICF + Financing CF
A67: Free CF (OCF+ICF) | B67: =B63+B64 -> 399.5 | C67: =C63+C64 -> 141.15264 | D67: =D63+D64 -> 2318.9 | E67: =E63+E64 -> 345.88208 | F67: =F63+F64 -> 520.3 | G67: =G63+G64 -> -133.11024 | H67: =H63+H64 -> 814.1 | I67: =I63+I64 -> 276.55464 | ... Q67: =Q63+Q64 -> 95.606361 | T67: =T63+T64 -> 2318.9 | U67: =U63+U64 -> 814.1 | V67: =V63+V64 -> 1535.1171 | W67: =W63+W64 -> 1642.6546 | X67: =X63+X64 -> 95.606361 | Y67: =Y63+Y64 -> 2996.8235 | AA67: Free CF = OCF + ICF (= 会社フリーCF)
A69: + NI | B69: =FS!B18 -> 294.8 | C69: =FS!C18 -> 421.9 | D69: =FS!D18 -> 359.6 | E69: =FS!E18 -> 346.4 | F69: =FS!F18 -> 445.4 | G69: =FS!G18 -> 424.4 | H69: =FS!H18 -> 456.8 | I69: =FS!I18 -> 678.6 | ... Q69: =FS!Q18 -> 654.51569 | T69: =IF(COUNTBLANK(B69:D69)>0,"",SUM(B69:D69)) -> 1076.3 | U69: =IF(AND(ISBLANK(F69),ISBLANK(H69)),"",SUM(E69:H69)) -> 1673 | V69: =IF(AND(ISBLANK(J69),ISBLANK(L69)),"",SUM(I69:L69)) -> 2254.5118 | W69: =IF(AND(ISBLANK(N69),ISBLANK(P69)),"",SUM(M69:P69)) -> 2689.8553 | X69: =IF(COUNTBLANK(Q69:Q69)>0,"",SUM(Q69:Q69)) -> 654.51569 | AA69: from PL Net Income
A70: + D&A | B70: 155.1 | D70: 188 | F70: 201.9 | H70: 246.5 | J70: =FS!I36*FS!$B$100 -> 164.81784 | K70: =FS!J36*FS!$B$100 -> 166.85545 | L70: =FS!K36*FS!$B$100 -> 168.83927 | M70: =FS!L36*FS!$B$100 -> 170.77071 | N70: =FS!M36*FS!$B$100 -> 172.65116 | O70: =FS!N36*FS!$B$100 -> 174.48197 | P70: =FS!O36*FS!$B$100 -> 176.26445 | Q70: =FS!P36*FS!$B$100 -> 177.99987 | T70: =IF(COUNTBLANK(B70:D70)>0,"",SUM(B70:D70)) | U70: =IF(AND(ISBLANK(F70),ISBLANK(H70)),"",SUM(E70:H70)) -> 448.4 | V70: =IF(AND(ISBLANK(J70),ISBLANK(L70)),"",SUM(I70:L70)) -> 500.51255 | W70: =IF(AND(ISBLANK(N70),ISBLANK(P70)),"",SUM(M70:P70)) -> 694.16829 | X70: =IF(COUNTBLANK(Q70:Q70)>0,"",SUM(Q70:Q70)) -> 177.99987 | AA70: Prior PPE × 2.64%/Q (calibrated to the disclosed guide 165億/Q at the latest PPE; rises with PPE thereafter) (depreciation)
A71: + ΔWC | C71: =-(FS!C31-FS!B31)-(FS!C32-FS!B32)+(FS!C40-FS!B40) -> -152.6 | D71: =-(FS!D31-FS!C31)-(FS!D32-FS!C32)+(FS!D40-FS!C40) -> 200.1 | E71: =-(FS!E31-FS!D31)-(FS!E32-FS!D32)+(FS!E40-FS!D40) -> 115.1 | F71: =-(FS!F31-FS!E31)-(FS!F32-FS!E32)+(FS!F40-FS!E40) -> -5 | G71: =-(FS!G31-FS!F31)-(FS!G32-FS!F32)+(FS!G40-FS!F40) -> -470.7 | H71: =-(FS!H31-FS!G31)-(FS!H32-FS!G32)+(FS!H40-FS!G40) -> -234.1 | I71: =-(FS!I31-FS!H31)-(FS!I32-FS!H32)+(FS!I40-FS!H40) -> -323.2 | J71: =-(FS!J31-FS!I31)-(FS!J32-FS!I32)+(FS!J40-FS!I40) -> 469.26341 | ... Q71: =-(FS!Q31-FS!P31)-(FS!Q32-FS!P32)+(FS!Q40-FS!P40) -> -494.90919 | T71: =IF(COUNTBLANK(B71:D71)>0,"",SUM(B71:D71)) | U71: =IF(AND(ISBLANK(F71),ISBLANK(H71)),"",SUM(E71:H71)) -> -594.7 | V71: =IF(AND(ISBLANK(J71),ISBLANK(L71)),"",SUM(I71:L71)) -> -415.06186 | W71: =IF(AND(ISBLANK(N71),ISBLANK(P71)),"",SUM(M71:P71)) -> -773.36901 | X71: =IF(COUNTBLANK(Q71:Q71)>0,"",SUM(Q71:Q71)) -> -494.90919 | AA71: − ΔAR − ΔInv + ΔAP (working capital change)
A73: − Capex | B73: 429.5 | D73: 637.9 | F73: 791.1 | H73: 735.9 | J73: =$B$80 -> 242 | K73: =$B$80 -> 242 | L73: =$B$80 -> 242 | M73: =$B$80 -> 242 | N73: =$B$80 -> 242 | O73: =$B$80 -> 242 | P73: =$B$80 -> 242 | Q73: =$B$80 -> 242 | T73: =IF(COUNTBLANK(B73:D73)>0,"",SUM(B73:D73)) | U73: =IF(AND(ISBLANK(F73),ISBLANK(H73)),"",SUM(E73:H73)) -> 1527 | V73: =IF(AND(ISBLANK(J73),ISBLANK(L73)),"",SUM(I73:L73)) -> 726 | W73: =IF(AND(ISBLANK(N73),ISBLANK(P73)),"",SUM(M73:P73)) -> 968 | X73: =IF(COUNTBLANK(Q73:Q73)>0,"",SUM(Q73:Q73)) -> 242 | Y73: =J73+K73+L73+M73+N73+O73+P73+Q73 -> 1936 | AA73: Capex/Q assumption (242.0億, edit on Summary)
A75: − Dividends | B75: 320.7 | D75: 319.8 | F75: 318.8 | H75: 316.6 | J75: =FS!J23*FS!J21/100 -> 201.63263 | K75: =FS!K23*FS!K21/100 -> 173.64741 | L75: =FS!L23*FS!L21/100 -> 207.80733 | M75: =FS!M23*FS!M21/100 -> 249.49815 | N75: =FS!N23*FS!N21/100 -> 243.33555 | O75: =FS!O23*FS!O21/100 -> 242.94621 | P75: =FS!P23*FS!P21/100 -> 259.46656 | Q75: =FS!Q23*FS!Q21/100 -> 242.1708 | T75: =IF(COUNTBLANK(B75:D75)>0,"",SUM(B75:D75)) | U75: =IF(AND(ISBLANK(F75),ISBLANK(H75)),"",SUM(E75:H75)) -> 635.4 | V75: =IF(AND(ISBLANK(J75),ISBLANK(L75)),"",SUM(I75:L75)) -> 583.08737 | W75: =IF(AND(ISBLANK(N75),ISBLANK(P75)),"",SUM(M75:P75)) -> 995.24647 | X75: =IF(COUNTBLANK(Q75:Q75)>0,"",SUM(Q75:Q75)) -> 242.1708 | Y75: =J75+K75+L75+M75+N75+O75+P75+Q75 -> 1820.5046 | AA75: DPS × Shares (M) / 100
A76: − Buyback | B76: 96.5 | D76: 153.7 | F76: 218 | H76: 82.2 | J76: =$B$81 -> 125 | K76: =$B$81 -> 125 | L76: =$B$81 -> 125 | M76: =$B$81 -> 125 | N76: =$B$81 -> 125 | O76: =$B$81 -> 125 | P76: =$B$81 -> 125 | Q76: =$B$81 -> 125 | T76: =IF(COUNTBLANK(B76:D76)>0,"",SUM(B76:D76)) | U76: =IF(AND(ISBLANK(F76),ISBLANK(H76)),"",SUM(E76:H76)) -> 300.2 | V76: =IF(AND(ISBLANK(J76),ISBLANK(L76)),"",SUM(I76:L76)) -> 375 | W76: =IF(AND(ISBLANK(N76),ISBLANK(P76)),"",SUM(M76:P76)) -> 500 | X76: =IF(COUNTBLANK(Q76:Q76)>0,"",SUM(Q76:Q76)) -> 125 | AA76: Buyback/Q assumption (edit on Summary; seeded from tdnet when announced)
A77: + Net Debt Iss | C77: =FS!C41-FS!B41 -> -69 | D77: =FS!D41-FS!C41 -> 0 | E77: =FS!E41-FS!D41 -> -0.4 | F77: =FS!F41-FS!E41 -> 0 | G77: =FS!G41-FS!F41 -> 300.9 | H77: =FS!H41-FS!G41 -> -300 | I77: =FS!I41-FS!H41 -> -0.9 | J77: 0 | K77: 0 | L77: 0 | M77: 0 | N77: 0 | O77: 0 | P77: 0 | Q77: 0 | T77: =IF(COUNTBLANK(B77:D77)>0,"",SUM(B77:D77)) | U77: =IF(AND(ISBLANK(F77),ISBLANK(H77)),"",SUM(E77:H77)) -> 0.5 | V77: =IF(AND(ISBLANK(J77),ISBLANK(L77)),"",SUM(I77:L77)) -> -0.9 | W77: =IF(AND(ISBLANK(N77),ISBLANK(P77)),"",SUM(M77:P77)) -> 0 | X77: =IF(COUNTBLANK(Q77:Q77)>0,"",SUM(Q77:Q77)) -> 0 | AA77: Held = 0
A80: Capex per Q (億) [edit on Summary B22] | B80: =FS!$B$95 -> 242
A81: Buyback per Q (億) [edit on Summary B23] | B81: =FS!$B$96 -> 125
A84: Live Assumptions ─ edit cells in column B; only forward periods recompute
A85: Tax rate % | B85: 28.9 | C85: ΣTax/ΣPretax actual (ratio-of-sums), n=19
A86: NonOp/OP % | B86: 21 | C86: 5y ΣOdP/ΣOP−1 (ratio-of-sums), n=20
A87: SG&A/Sales % | B87: 19.5 | C87: yaml override (recent run-rate)
A88: Payout % | B88: 37 | C88: config: fixed policy
A89: Shares (M) | B89: 62.9 | C89: fins_summary ShOutFY(64M)-TrShFY(1M)
A90: PPE/TA ratio | B90: 0.202 | C90: 5y mean PPE/TA from fins_details, n=19
A91: RE/Eq ratio | B91: 0.888 | C91: 5y mean RE/Eq from fins_details, n=19
A92: DSO (days) | B92: 91 | C92: 26/1Q BS: AR 2,714億 ÷ Sales 2,709億 × 91
A93: DIO (days) | B93: 324 | C93: 26/1Q BS: Inv 5,132億 ÷ COGS 1,440億 × 91 (FY25末 361d, trending down)
A94: DPO (days) | B94: 27 | C94: 26/1Q BS: AP 421億 ÷ COGS 1,440億 × 91
A95: Capex/Q (億) | B95: 242 | C95: yaml override (disclosed)
A96: Buyback/Q (億) | B96: 125 | C96: tdnet 2026-05-14: max 500.0億 over 2026-05-20~2027-03-24 ÷4Q
... A101: Minority/Pretax % | B101: 0 | C101: FY25 pretax−tax−NP = 0.0; NCI equity −5.8億

Sheet Valuation
A1: SMC Valuation — LEFT=DCF/PE/PB + verdict; RIGHT=5y multiples history
A2: BLUE=input, BLACK=formula, GREEN=cross-sheet
A3: Method 1: DCF (FCFF, equity-only) | F3: MULTIPLES HISTORY (5y, split-adjusted)
A4: FY+1 FCF (億, OCF+ICF) | B4: =IFERROR((FS!I63+FS!J63+FS!K63+FS!L63)+(FS!I64+FS!J64+FS!K64+FS!L64),"") -> 1535.1171 | F4: Stat | G4: P/E | H4: P/B
A5: FCF growth Y2-Y5 % | B5: 5 | F5: Mean | G5: 23.26 | H5: 2.4
A6: Terminal growth % | B6: 2 | F6: Median | G6: 22.71 | H6: 2.48
A7: Rf % (10y JGB) | B7: 1.5 | F7: StdDev | G7: 3.6 | H7: 0.49
A8: ERP % (JP equity premium) | B8: 5 | F8: Mean +1SD | G8: 26.86 | H8: 2.89
A9: Beta (5y vs TOPIX) | B9: 1.249 | F9: Mean −1SD | G9: 19.65 | H9: 1.92
A10: WACC % = Rf + β × ERP | B10: =B7+B9*B8 -> 7.745 | F10: CURRENT | G10: 21.36 | H10: 2.03
A11: Stub: days to FY end ÷ 365.25 | B11: =(DATE(YEAR(TODAY())+IF(MONTH(TODAY())>3,1,0),3+1,0)-TODAY())/365.25 -> 0.55304586 | F11: Pct Rank % | G11: 29.97 | H11: 26.39
A12: Mid-year convention: Y1 discount=stub/2, Yn≥2 = stub + (n-1) - 0.5
A13: Y1 | B13: =B4 -> 1535.1171 | C13: =1/(1+$B$10/100)^($B$11/2) -> 0.97958348 | D13: =B13*C13 -> 1503.7754 | F13: Current Price (¥) | G13: 67890
A14: Y2 | B14: =B13*(1+$B$5/100) -> 1611.873 | C14: =1/(1+$B$10/100)^($B$11+2-1-0.5) -> 0.92445195 | D14: =B14*C14 -> 1490.0991 | F14: Current TTM EPS (¥) | G14: 3178.79
A15: Y3 | B15: =B14*(1+$B$5/100) -> 1692.4666 | C15: =1/(1+$B$10/100)^($B$11+3-1-0.5) -> 0.85799986 | D15: =B15*C15 -> 1452.1361 | F15: Current BPS (¥) | G15: 33498.9
A16: Y4 | B16: =B15*(1+$B$5/100) -> 1777.09 | C16: =1/(1+$B$10/100)^($B$11+4-1-0.5) -> 0.79632452 | D16: =B16*C16 -> 1415.1403
A17: Y5 | B17: =B16*(1+$B$5/100) -> 1865.9445 | C17: =1/(1+$B$10/100)^($B$11+5-1-0.5) -> 0.73908258 | D17: =B17*C17 -> 1379.0871 | F17: Recent 30 days
F18: Date | G18: Close | H18: TTM EPS | I18: BPS | J18: P/E | K18: P/B
A19: Terminal (discounted at end-of-Y5 = stub + 4.5) | B19: =B17*(1+$B$6/100)/(($B$10-$B$6)/100) -> 33129.04 | C19: =1/(1+$B$10/100)^($B$11+4.5) -> 0.68595534 | D19: =B19*C19 -> 22725.042 | F19: 2026-07-29 | G19: 64930 | H19: 2643.89 | I19: 33498.9 | J19: 24.56 | K19: 1.94
F20: 2026-07-30 | G20: 66160 | H20: 2643.89 | I20: 33498.9 | J20: 25.02 | K20: 1.97
A21: Enterprise Value (億) | B21: =SUM(D13:D17)+D19 -> 29965.28 | F21: 2026-07-31 | G21: 70480 | H21: 2643.89 | I21: 33498.9 | J21: 26.66 | K21: 2.1
A22: Net Cash = Cash − Debt (FY26Q1 actual) | B22: =FS!I30-FS!I41 -> 7060.9 | F22: 2026-08-03 | G22: 70980 | H22: 2643.89 | I22: 33498.9 | J22: 26.85 | K22: 2.12
A23: Equity Value (億) | B23: =B21+B22 -> 37026.18 | F23: 2026-08-04 | G23: 73650 | H23: 2643.89 | I23: 33498.9 | J23: 27.86 | K23: 2.2
A24: Shares (M) | B24: 62.87 | F24: 2026-08-05 | G24: 75790 | H24: 2643.89 | I24: 33498.9 | J24: 28.67 | K24: 2.26
A25: DCF implied price (¥) | B25: =B23*100/B24 -> 58893.24 | F25: 2026-08-06 | G25: 75350 | H25: 2643.89 | I25: 33498.9 | J25: 28.5 | K25: 2.25
A26: Net Cash floor (¥) | B26: =B22*100/B24 -> 11230.953 | F26: 2026-08-07 | G26: 74190 | H26: 3178.79 | I26: 33498.9 | J26: 23.34 | K26: 2.21
F27: 2026-08-10 | G27: 78340 | H27: 3178.79 | I27: 33498.9 | J27: 24.64 | K27: 2.34
A28: Method 2: P/E range (NTM blend) | F28: 2026-08-12 | G28: 78320 | H28: 3178.79 | I28: 33498.9 | J28: 24.64 | K28: 2.34
A29: Blend weight on FY+1 (auto = days→FY end / 365) | B29: =MAX(0,MIN(1,1-(TODAY()-DATE(YEAR(TODAY())-IF(MONTH(TODAY())>3,0,1),3+1,0))/365.25)) -> 0.55373032 | F29: 2026-08-13 | G29: 77330 | H29: 3178.79 | I29: 33498.9 | J29: 24.33 | K29: 2.31
A30: FY+1 EPS forecast (¥, sum of 4Q) | B30: =FS!I22+FS!J22+FS!K22+FS!L22 -> 3587.9185 | F30: 2026-08-14 | G30: 76430 | H30: 3178.79 | I30: 33498.9 | J30: 24.04 | K30: 2.28
A31: FY+2 EPS forecast (¥, sum of 4Q) | B31: =FS!M22+FS!N22+FS!O22+FS!P22 -> 4333.7872 | F31: 2026-08-17 | G31: 77610 | H31: 3178.79 | I31: 33498.9 | J31: 24.41 | K31: 2.32
A32: NTM EPS = w·FY+1 + (1−w)·FY+2 | B32: =B29*B30+(1-B29)*B31 -> 3920.7771 | F32: 2026-08-18 | G32: 75200 | H32: 3178.79 | I32: 33498.9 | J32: 23.66 | K32: 2.24
A33: 5y mean P/E | B33: =Valuation!G5 -> 23.26 | F33: 2026-08-19 | G33: 70910 | H33: 3178.79 | I33: 33498.9 | J33: 22.31 | K33: 2.12
A34: 5y +1SD P/E | B34: =Valuation!G8 -> 26.86 | F34: 2026-08-20 | G34: 70690 | H34: 3178.79 | I34: 33498.9 | J34: 22.24 | K34: 2.11
A35: 5y −1SD P/E | B35: =Valuation!G9 -> 19.65 | F35: 2026-08-21 | G35: 71090 | H35: 3178.79 | I35: 33498.9 | J35: 22.36 | K35: 2.12
A36: Implied @mean (NTM) | B36: =B32*B33 -> 91197.275 | F36: 2026-08-24 | G36: 71800 | H36: 3178.79 | I36: 33498.9 | J36: 22.59 | K36: 2.14
A37: Implied @+1SD | B37: =B32*B34 -> 105312.07 | F37: 2026-08-25 | G37: 72090 | H37: 3178.79 | I37: 33498.9 | J37: 22.68 | K37: 2.15
A38: Implied @−1SD | B38: =B32*B35 -> 77043.27 | F38: 2026-08-26 | G38: 71520 | H38: 3178.79 | I38: 33498.9 | J38: 22.5 | K38: 2.13
F39: 2026-08-27 | G39: 71020 | H39: 3178.79 | I39: 33498.9 | J39: 22.34 | K39: 2.12
F40: 2026-08-28 | G40: 70300 | H40: 3178.79 | I40: 33498.9 | J40: 22.12 | K40: 2.1
A41: Method 3: P/B range (NTM blend) | F41: 2026-08-31 | G41: 70710 | H41: 3178.79 | I41: 33498.9 | J41: 22.24 | K41: 2.11
A42: Current BPS (latest, ¥/share) | B42: =Valuation!G15 -> 33498.9 | F42: 2026-09-01 | G42: 69850 | H42: 3178.79 | I42: 33498.9 | J42: 21.97 | K42: 2.09
A43: + FY+1 ΔBPS (4Q NI × retention / shares) | B43: =(FS!J18+FS!K18+FS!L18)*(1-FS!B88/100)*100/FS!B89 -> 1578.4172 | F43: 2026-09-02 | G43: 66500 | H43: 3178.79 | I43: 33498.9 | J43: 20.92 | K43: 1.99
A44: + FY+2 ΔBPS (only when blend leans to FY+2) | B44: =(FS!M18+FS!N18+FS!O18+FS!P18)*(1-FS!B88/100)*100/FS!B89 -> 2694.1317 | F44: 2026-09-03 | G44: 67020 | H44: 3178.79 | I44: 33498.9 | J44: 21.08 | K44: 2
A45: NTM BPS = (current + ΔFY1 + (1−w)·ΔFY2) | B45: =B42+B43+(1-B29)*B44 -> 36279.627 | F45: 2026-09-04 | G45: 67140 | H45: 3178.79 | I45: 33498.9 | J45: 21.12 | K45: 2
A46: 5y mean P/B | B46: =Valuation!H5 -> 2.4 | F46: 2026-09-07 | G46: 68590 | H46: 3178.79 | I46: 33498.9 | J46: 21.58 | K46: 2.05
A47: 5y +1SD P/B | B47: =Valuation!H8 -> 2.89 | F47: 2026-09-08 | G47: 65650 | H47: 3178.79 | I47: 33498.9 | J47: 20.65 | K47: 1.96
A48: 5y −1SD P/B | B48: =Valuation!H9 -> 1.92 | F48: 2026-09-09 | G48: 67890 | H48: 3178.79 | I48: 33498.9 | J48: 21.36 | K48: 2.03
A49: Implied @mean (NTM) | B49: =B45*B46 -> 87071.104
A50: Implied @+1SD | B50: =B45*B47 -> 104848.12
A51: Implied @−1SD | B51: =B45*B48 -> 69656.883
A54: VERDICT (NTM target)
A55: Current Price (¥) | B55: =Valuation!G13 -> 67890
A56: DCF target | B56: =B25 -> 58893.24 | C56: =IF(B55<B56*0.9,"Cheap",IF(B55>B56*1.1,"Rich","Fair")) -> Rich
A57: P/E target (NTM) | B57: =B36 -> 91197.275 | C57: =IF(B55<B38,"Cheap",IF(B55>B37,"Rich","Fair")) -> Cheap
A58: P/B target (NTM) | B58: =B49 -> 87071.104 | C58: =IF(B55<B51,"Cheap",IF(B55>B50,"Rich","Fair")) -> Cheap
A59: Composite | B59: =IF(AND(C56="Cheap",C57="Cheap",C58="Cheap"),"CHEAP — buy",IF(AND(C56="Rich",C57="Rich",C58="Rich"),"RICH — sell",IF(OR(C56="Rich",C57="Rich",C58="Rich"),"Mixed-rich","Fair / Mixed-cheap"))) -> Mixed-rich

Sheet Industry
A1: Industry / Macro Indicators — context for SMC (¥億, monthly)
A2: Rows = indicators; Cols = months (latest right). Easy to plot. Sources: JMTBA + MOF 貿易統計
A4: Indicator | B4: 202407 | C4: 202408 | D4: 202409 | E4: 202410 | F4: 202411 | G4: 202412 | H4: 202501 | I4: 202502 | J4: 202503 | K4: 202504 | L4: 202505 | M4: 202506 | N4: 202507 | O4: 202508 | P4: 202509 | Q4: 202510 | R4: 202511 | S4: 202512 | T4: 202601 | U4: 202602 | V4: 202603 | W4: 202604 | X4: 202605 | Y4: 202606 | Z4: 202607
A5: JMTBA total (億) | B5: 1239.4 | C5: 1107.7 | D5: 1253.6 | E5: 1225.5 | F5: 1193.3 | G5: 1430.9 | H5: 1161.5 | I5: 1182 | J5: 1511 | K5: 1302.1 | L5: 1287.2 | M5: 1331.6 | N5: 1283.6 | O5: 1201.7 | P5: 1391.5 | Q5: 1434.6 | R5: 1370 | S5: 1586.4 | T5: 1455.8 | U5: 1467.4 | V5: 1934.7 | W5: 1889.7 | X5: 1770.1 | Y5: 2033.8
A6: total YoY % | N6: =IFERROR(N5/B5-1,"") -> 0.035662417 | O6: =IFERROR(O5/C5-1,"") -> 0.084860522 | P6: =IFERROR(P5/D5-1,"") -> 0.11000319 | Q6: =IFERROR(Q5/E5-1,"") -> 0.17062424 | R6: =IFERROR(R5/F5-1,"") -> 0.14807676 | S6: =IFERROR(S5/G5-1,"") -> 0.10867286 | T6: =IFERROR(T5/H5-1,"") -> 0.25337925 | U6: =IFERROR(U5/I5-1,"") -> 0.24145516 | ... Z6: =IFERROR(Z5/N5-1,"") -> -1
A7: JMTBA domestic (億) | B7: 357 | C7: 321.9 | D7: 415.3 | E7: 334.4 | F7: 343.3 | G7: 399.2 | H7: 320 | I7: 337.7 | J7: 492.6 | K7: 343.8 | L7: 330.2 | M7: 398.7 | N7: 354.5 | O7: 318.9 | P7: 436.4 | Q7: 356.9 | R7: 319.9 | S7: 399.1 | T7: 326.2 | U7: 371.6 | V7: 504.7 | W7: 492.9 | X7: 453.3 | Y7: 580.2
A8: domestic YoY % | N8: =IFERROR(N7/B7-1,"") -> -0.0070028011 | O8: =IFERROR(O7/C7-1,"") -> -0.0093196645 | P8: =IFERROR(P7/D7-1,"") -> 0.050806646 | Q8: =IFERROR(Q7/E7-1,"") -> 0.067284689 | R8: =IFERROR(R7/F7-1,"") -> -0.068161957 | S8: =IFERROR(S7/G7-1,"") -> -0.000250501 | T8: =IFERROR(T7/H7-1,"") -> 0.019375 | U8: =IFERROR(U7/I7-1,"") -> 0.10038496 | ... Z8: =IFERROR(Z7/N7-1,"") -> -1
A9: JMTBA foreign (億) | B9: 882.4 | C9: 785.8 | D9: 838.3 | E9: 891.1 | F9: 850 | G9: 1031.7 | H9: 841.5 | I9: 844.3 | J9: 1018.4 | K9: 958.4 | L9: 957 | M9: 932.9 | N9: 929.1 | O9: 882.8 | P9: 955 | Q9: 1077.6 | R9: 1050.2 | S9: 1187.4 | T9: 1129.5 | U9: 1095.8 | V9: 1430 | W9: 1396.8 | X9: 1316.8 | Y9: 1453.5
A10: foreign YoY % | N10: =IFERROR(N9/B9-1,"") -> 0.052923844 | O10: =IFERROR(O9/C9-1,"") -> 0.12344108 | P10: =IFERROR(P9/D9-1,"") -> 0.13921031 | Q10: =IFERROR(Q9/E9-1,"") -> 0.20929189 | R10: =IFERROR(R9/F9-1,"") -> 0.23552941 | S10: =IFERROR(S9/G9-1,"") -> 0.15091596 | T10: =IFERROR(T9/H9-1,"") -> 0.34224599 | U10: =IFERROR(U9/I9-1,"") -> 0.2978799 | ... Z10: =IFERROR(Z9/N9-1,"") -> -1
A11: JMTBA backlog (億) | B11: 8137.1 | C11: 8005.3 | D11: 7677.2 | E11: 7751.9 | F11: 7700 | G11: 7678.2 | H11: 7726.6 | I11: 7599.4 | J11: 6924 | K11: 6957.6 | L11: 7131.3 | M11: 7175.2 | N11: 7251 | O11: 7292 | P11: 7329.6 | Q11: 7564.8 | R11: 7594.8 | S11: 7574.3 | T11: 7750.9 | U11: 8026.2 | V11: 8116.1 | W11: 8782.5 | X11: 9282.2 | Y11: 9665
A12: backlog YoY % | N12: =IFERROR(N11/B11-1,"") -> -0.10889629 | O12: =IFERROR(O11/C11-1,"") -> -0.089103469 | P12: =IFERROR(P11/D11-1,"") -> -0.045276924 | Q12: =IFERROR(Q11/E11-1,"") -> -0.024136018 | R12: =IFERROR(R11/F11-1,"") -> -0.013662338 | S12: =IFERROR(S11/G11-1,"") -> -0.013531817 | T12: =IFERROR(T11/H11-1,"") -> 0.0031449797 | U12: =IFERROR(U11/I11-1,"") -> 0.056162329 | ... Z12: =IFERROR(Z11/N11-1,"") -> -1
A14: JMTBA total 速報 (億) | V14: 1935.1 | W14: 1889.7 | X14: 1768.3 | Y14: 2035.2 | Z14: 1931
A15: total 速報 YoY % | N15: =IFERROR(N14/B14-1,"") | O15: =IFERROR(O14/C14-1,"") | P15: =IFERROR(P14/D14-1,"") | Q15: =IFERROR(Q14/E14-1,"") | R15: =IFERROR(R14/F14-1,"") | S15: =IFERROR(S14/G14-1,"") | T15: =IFERROR(T14/H14-1,"") | U15: =IFERROR(U14/I14-1,"") | ... Z15: =IFERROR(Z14/N14-1,"")
A16: JMTBA domestic 速報 (億) | V16: 505.1 | W16: 492.9 | X16: 450.4 | Y16: 580.2 | Z16: 532.4
A17: domestic 速報 YoY % | N17: =IFERROR(N16/B16-1,"") | O17: =IFERROR(O16/C16-1,"") | P17: =IFERROR(P16/D16-1,"") | Q17: =IFERROR(Q16/E16-1,"") | R17: =IFERROR(R16/F16-1,"") | S17: =IFERROR(S16/G16-1,"") | T17: =IFERROR(T16/H16-1,"") | U17: =IFERROR(U16/I16-1,"") | ... Z17: =IFERROR(Z16/N16-1,"")
A18: JMTBA foreign 速報 (億) | V18: 1430 | W18: 1396.8 | X18: 1318 | Y18: 1455 | Z18: 1398.6
A19: foreign 速報 YoY % | N19: =IFERROR(N18/B18-1,"") | O19: =IFERROR(O18/C18-1,"") | P19: =IFERROR(P18/D18-1,"") | Q19: =IFERROR(Q18/E18-1,"") | R19: =IFERROR(R18/F18-1,"") | S19: =IFERROR(S18/G18-1,"") | T19: =IFERROR(T18/H18-1,"") | U19: =IFERROR(U18/I18-1,"") | ... Z19: =IFERROR(Z18/N18-1,"")
A21: JMTBA 中国 (億) | B21: 294.9 | C21: 285.3 | D21: 274.2 | E21: 290 | F21: 293.2 | G21: 362.5 | H21: 276 | I21: 266.8 | J21: 360.9 | K21: 339.8 | L21: 309.5 | M21: 321.8 | N21: 319.5 | O21: 293.2 | P21: 342.8 | Q21: 317.9 | R21: 381.3 | S21: 371.2 | T21: 433 | U21: 374.6 | V21: 513.5 | W21: 533.3 | X21: 512.5 | Y21: 564.9
A22: 中国 YoY % | N22: =IFERROR(N21/B21-1,"") -> 0.083418108 | O22: =IFERROR(O21/C21-1,"") -> 0.027690151 | P22: =IFERROR(P21/D21-1,"") -> 0.25018235 | Q22: =IFERROR(Q21/E21-1,"") -> 0.096206897 | R22: =IFERROR(R21/F21-1,"") -> 0.30047749 | S22: =IFERROR(S21/G21-1,"") -> 0.024 | T22: =IFERROR(T21/H21-1,"") -> 0.56884058 | U22: =IFERROR(U21/I21-1,"") -> 0.40404798 | ... Z22: =IFERROR(Z21/N21-1,"") -> -1
A23: JMTBA アメリカ (億) | B23: 229.7 | C23: 205.1 | D23: 221.6 | E23: 174.2 | F23: 235.8 | G23: 289.4 | H23: 207.7 | I23: 230.3 | J23: 247 | K23: 272.3 | L23: 289.9 | M23: 249.3 | N23: 237.9 | O23: 240.8 | P23: 259 | Q23: 282.9 | R23: 263.9 | S23: 345.8 | T23: 310.9 | U23: 312.1 | V23: 392.6 | W23: 358.1 | X23: 303.5 | Y23: 360
A24: アメリカ YoY % | N24: =IFERROR(N23/B23-1,"") -> 0.035698737 | O24: =IFERROR(O23/C23-1,"") -> 0.17406143 | P24: =IFERROR(P23/D23-1,"") -> 0.16877256 | Q24: =IFERROR(Q23/E23-1,"") -> 0.62399541 | R24: =IFERROR(R23/F23-1,"") -> 0.11916879 | S24: =IFERROR(S23/G23-1,"") -> 0.19488597 | T24: =IFERROR(T23/H23-1,"") -> 0.49687049 | U24: =IFERROR(U23/I23-1,"") -> 0.35518888 | ... Z24: =IFERROR(Z23/N23-1,"") -> -1
A25: JMTBA インド (億) | B25: 49.9 | C25: 52.7 | D25: 55.3 | E25: 97.1 | F25: 55.6 | G25: 50.6 | H25: 83.9 | I25: 53.9 | J25: 98.2 | K25: 47.4 | L25: 45.3 | M25: 51.4 | N25: 61.1 | O25: 49.8 | P25: 53.2 | Q25: 49 | R25: 59 | S25: 63.9 | T25: 58.4 | U25: 78.8 | V25: 116.6 | W25: 76.6 | X25: 57.7 | Y25: 91.6
A26: インド YoY % | N26: =IFERROR(N25/B25-1,"") -> 0.2244489 | O26: =IFERROR(O25/C25-1,"") -> -0.055028463 | P26: =IFERROR(P25/D25-1,"") -> -0.037974684 | Q26: =IFERROR(Q25/E25-1,"") -> -0.4953656 | R26: =IFERROR(R25/F25-1,"") -> 0.061151079 | S26: =IFERROR(S25/G25-1,"") -> 0.26284585 | T26: =IFERROR(T25/H25-1,"") -> -0.30393325 | U26: =IFERROR(U25/I25-1,"") -> 0.4619666 | ... Z26: =IFERROR(Z25/N25-1,"") -> -1
A27: JMTBA 台湾 (億) | B27: 21.8 | C27: 11.3 | D27: 23.2 | E27: 16.8 | F27: 10.3 | G27: 16.4 | H27: 12.8 | I27: 16.8 | J27: 21.8 | K27: 18.2 | L27: 16.2 | M27: 12.7 | N27: 15.5 | O27: 11.2 | P27: 14.9 | Q27: 21.4 | R27: 18.1 | S27: 13.3 | T27: 33.6 | U27: 19 | V27: 22 | W27: 33.8 | X27: 49.4 | Y27: 35.8
A28: 台湾 YoY % | N28: =IFERROR(N27/B27-1,"") -> -0.28899083 | O28: =IFERROR(O27/C27-1,"") -> -0.0088495575 | P28: =IFERROR(P27/D27-1,"") -> -0.35775862 | Q28: =IFERROR(Q27/E27-1,"") -> 0.27380952 | R28: =IFERROR(R27/F27-1,"") -> 0.75728155 | S28: =IFERROR(S27/G27-1,"") -> -0.18902439 | T28: =IFERROR(T27/H27-1,"") -> 1.625 | U28: =IFERROR(U27/I27-1,"") -> 0.13095238 | ... Z28: =IFERROR(Z27/N27-1,"") -> -1
A29: JMTBA 韓国 (億) | B29: 22.4 | C29: 38.3 | D29: 20.4 | E29: 28.4 | F29: 15.1 | G29: 24 | H29: 26.3 | I29: 30.4 | J29: 25.9 | K29: 32.4 | L29: 24 | M29: 19.4 | N29: 18.4 | O29: 20.9 | P29: 25.3 | Q29: 43.1 | R29: 28.4 | S29: 19.2 | T29: 28.4 | U29: 30 | V29: 26.6 | W29: 37.5 | X29: 19.8 | Y29: 33.5
A30: 韓国 YoY % | N30: =IFERROR(N29/B29-1,"") -> -0.17857143 | O30: =IFERROR(O29/C29-1,"") -> -0.45430809 | P30: =IFERROR(P29/D29-1,"") -> 0.24019608 | Q30: =IFERROR(Q29/E29-1,"") -> 0.51760563 | R30: =IFERROR(R29/F29-1,"") -> 0.8807947 | S30: =IFERROR(S29/G29-1,"") -> -0.2 | T30: =IFERROR(T29/H29-1,"") -> 0.079847909 | U30: =IFERROR(U29/I29-1,"") -> -0.013157895 | ... Z30: =IFERROR(Z29/N29-1,"") -> -1
A31: JMTBA ドイツ (億) | B31: 36.8 | C31: 25.3 | D31: 35.8 | E31: 26.1 | F31: 27.8 | G31: 29.1 | H31: 30.4 | I31: 37.9 | J31: 34.8 | K31: 33.8 | L31: 36.3 | M31: 35.5 | N31: 34.4 | O31: 27.2 | P31: 36 | Q31: 43 | R31: 41.6 | S31: 42.8 | T31: 38.1 | U31: 39.5 | V31: 42.9 | W31: 44.7 | X31: 32.2 | Y31: 32.6
A32: ドイツ YoY % | N32: =IFERROR(N31/B31-1,"") -> -0.065217391 | O32: =IFERROR(O31/C31-1,"") -> 0.075098814 | P32: =IFERROR(P31/D31-1,"") -> 0.0055865922 | Q32: =IFERROR(Q31/E31-1,"") -> 0.64750958 | R32: =IFERROR(R31/F31-1,"") -> 0.49640288 | S32: =IFERROR(S31/G31-1,"") -> 0.47079038 | T32: =IFERROR(T31/H31-1,"") -> 0.25328947 | U32: =IFERROR(U31/I31-1,"") -> 0.042216359 | ... Z32: =IFERROR(Z31/N31-1,"") -> -1
A33: JMTBA うち自動車部品 (億) | B33: 41 | C33: 50.9 | D33: 54.1 | E33: 44.9 | F33: 35.1 | G33: 52.6 | H33: 36.8 | I33: 53.6 | J33: 71.6 | K33: 32.6 | L33: 34.4 | M33: 43 | N33: 55.2 | O33: 45.6 | P33: 50.8 | Q33: 43.4 | R33: 42.5 | S33: 59.3 | T33: 40.4 | U33: 59.4 | V33: 61.8 | W33: 76.9 | X33: 55.9 | Y33: 85.9
A34: うち自動車部品 YoY % | N34: =IFERROR(N33/B33-1,"") -> 0.34634146 | O34: =IFERROR(O33/C33-1,"") -> -0.10412574 | P34: =IFERROR(P33/D33-1,"") -> -0.060998152 | Q34: =IFERROR(Q33/E33-1,"") -> -0.033407572 | R34: =IFERROR(R33/F33-1,"") -> 0.21082621 | S34: =IFERROR(S33/G33-1,"") -> 0.12737643 | T34: =IFERROR(T33/H33-1,"") -> 0.097826087 | U34: =IFERROR(U33/I33-1,"") -> 0.10820896 | ... Z34: =IFERROR(Z33/N33-1,"") -> -1
A35: JMTBA 電気・精密 計 (億) | B35: 52.2 | C35: 26.1 | D35: 59.6 | E35: 42 | F35: 40.6 | G35: 48.5 | H35: 43.3 | I35: 32.4 | J35: 53.4 | K35: 48.3 | L35: 48.2 | M35: 58.6 | N35: 40.3 | O35: 33.3 | P35: 53.7 | Q35: 39.6 | R35: 34.9 | S35: 39.2 | T35: 52.2 | U35: 57.7 | V35: 73.8 | W35: 78 | X35: 51.3 | Y35: 97.3
A36: 電気・精密 計 YoY % | N36: =IFERROR(N35/B35-1,"") -> -0.22796935 | O36: =IFERROR(O35/C35-1,"") -> 0.27586207 | P36: =IFERROR(P35/D35-1,"") -> -0.098993289 | Q36: =IFERROR(Q35/E35-1,"") -> -0.057142857 | R36: =IFERROR(R35/F35-1,"") -> -0.14039409 | S36: =IFERROR(S35/G35-1,"") -> -0.19175258 | T36: =IFERROR(T35/H35-1,"") -> 0.20554273 | U36: =IFERROR(U35/I35-1,"") -> 0.7808642 | ... Z36: =IFERROR(Z35/N35-1,"") -> -1
A38: MOF Robot Exp HS 8479 (億) | C38: 819.7 | D38: 831.6 | E38: 852.8 | F38: 781.9 | G38: 988.7 | H38: 666.6 | I38: 877 | J38: 969.1 | K38: 824.4 | L38: 874.8 | M38: 893.6 | N38: 975.8 | O38: 803.5 | P38: 843.7 | Q38: 959.1 | R38: 898.4 | S38: 1061.1 | T38: 849.7 | U38: 849.4 | V38: 1089.9 | W38: 1055.3 | X38: 983.6 | Y38: 1015.5 | Z38: 1160.1
A39: MOF Robot Exp HS 8479 YoY % | N39: =IFERROR(N38/B38-1,"") | O39: =IFERROR(O38/C38-1,"") -> -0.019763328 | P39: =IFERROR(P38/D38-1,"") -> 0.014550265 | Q39: =IFERROR(Q38/E38-1,"") -> 0.12464822 | R39: =IFERROR(R38/F38-1,"") -> 0.14899604 | S39: =IFERROR(S38/G38-1,"") -> 0.07322747 | T39: =IFERROR(T38/H38-1,"") -> 0.27467747 | U39: =IFERROR(U38/I38-1,"") -> -0.031470924 | ... Z39: =IFERROR(Z38/N38-1,"") -> 0.18887067
A40: MOF Semi-Eq Exp HS 8486 (億) | C40: 3429.3 | D40: 3970.3 | E40: 4076 | F40: 3743.4 | G40: 4502.6 | H40: 2879 | I40: 3962.5 | J40: 4984.1 | K40: 3735.3 | L40: 3319.8 | M40: 3877.8 | N40: 3509.4 | O40: 3494.9 | P40: 3844 | Q40: 3635.4 | R40: 3792.2 | S40: 4436.8 | T40: 3156.7 | U40: 3290.9 | V40: 5259 | W40: 3932.1 | X40: 3654.5 | Y40: 4601.4 | Z40: 4939.5
A41: MOF Semi-Eq Exp HS 8486 YoY % | N41: =IFERROR(N40/B40-1,"") | O41: =IFERROR(O40/C40-1,"") -> 0.019129268 | P41: =IFERROR(P40/D40-1,"") -> -0.031811198 | Q41: =IFERROR(Q40/E40-1,"") -> -0.10809617 | R41: =IFERROR(R40/F40-1,"") -> 0.013036277 | S41: =IFERROR(S40/G40-1,"") -> -0.014613779 | T41: =IFERROR(T40/H40-1,"") -> 0.096457103 | U41: =IFERROR(U40/I40-1,"") -> -0.16948896 | ... Z41: =IFERROR(Z40/N40-1,"") -> 0.40750556
A42: MOF CNC Tool Exp HS 8459 (億) | C42: 12.3 | D42: 13.4 | E42: 7.1 | F42: 15.9 | G42: 15.3 | H42: 8.8 | I42: 18.3 | J42: 13.6 | K42: 9.9 | L42: 5.1 | M42: 11.3 | N42: 20.8 | O42: 10.4 | P42: 11.6 | Q42: 7.2 | R42: 4.6 | S42: 14.1 | T42: 5.5 | U42: 8.9 | V42: 11.4 | W42: 13.3 | X42: 9.7 | Y42: 9.5 | Z42: 7.2
A43: MOF CNC Tool Exp HS 8459 YoY % | N43: =IFERROR(N42/B42-1,"") | O43: =IFERROR(O42/C42-1,"") -> -0.15447154 | P43: =IFERROR(P42/D42-1,"") -> -0.13432836 | Q43: =IFERROR(Q42/E42-1,"") -> 0.014084507 | R43: =IFERROR(R42/F42-1,"") -> -0.71069182 | S43: =IFERROR(S42/G42-1,"") -> -0.078431373 | T43: =IFERROR(T42/H42-1,"") -> -0.375 | U43: =IFERROR(U42/I42-1,"") -> -0.5136612 | ... Z43: =IFERROR(Z42/N42-1,"") -> -0.65384615

Sheet Comp
A1: Peer Comparables for SMC (62730) — common multiples
A2: Source: J-Quants daily_bars × fins_summary FY (split-adjusted BPS). P/E(fwd) = Nikkei QUICK consensus for the CURRENT FY — near a company's FY-end that is nearly trailing.
A4: Code | B4: Name | C4: Period | D4: Price | E4: MCap (億) | F4: Sales | G4: OP | H4: NP | I4: EPS | J4: BPS | K4: P/E (fwd) | L4: P/B | M4: OPM % | N4: ROE % | O4: Sales YoY %
A5: 62730 | B5: ＳＭＣ | C5: Consensus 2027/3連予 (n=10) | D5: 67890 | E5: 43023 | F5: 10573 | G5: 2609 | H5: 2101 | I5: 3353.99 | J5: 33498.9 | K5: 20.2 | L5: 2.03 | M5: 24.7 | N5: 9.9 | O5: 25.5
A6: 64070 | B6: ＣＫＤ | C6: Consensus 2027/3連予 (n=9) | D6: 5310 | E6: 3548 | F6: 2006 | G6: 315 | H6: 215 | I6: 321.91 | J6: 2297.3 | K6: 16.5 | L6: 2.31 | M6: 15.7 | N6: 14 | O6: 27
A7: 64810 | B7: ＴＨＫ | C7: Consensus 2026/12連I予 (n=6) | D7: 6149 | E7: 6947 | F7: 3168 | G7: 477 | H7: 513 | I7: 457.74 | J7: 2332.9 | K7: 13.4 | L7: 2.64 | M7: 15.1 | N7: 19.3 | O7: 31.8
A8: 68610 | B8: キーエンス | C8: Consensus 2027/3連予 (n=12) | D8: 76280 | E8: 184998 | F8: 14505 | G8: 7778 | H8: 5692 | I8: 2346.85 | J8: 14313.9 | K8: 32.5 | L8: 5.33 | M8: 53.6 | N8: 16.4 | O8: 24
A9: 66450 | B9: オムロン | C9: Consensus 2027/3連I予 (n=4) | D9: 6037 | E9: 11877 | F9: 9028 | G9: 920 | H9: 584 | I9: 297.12 | J9: 4251.1 | K9: 20.3 | L9: 1.42 | M9: 10.2 | N9: 5.8 | O9: 17.7
A10: 69540 | B10: ファナック | C10: Consensus 2027/3連予 (n=12) | D10: 5848 | E10: 54571 | F10: 9783 | G10: 2301 | H10: 2091 | I10: 224.07 | J10: 1998.4 | K10: 26.1 | L10: 2.93 | M10: 23.5 | N10: 11.1 | O10: 14
A11: 65060 | B11: 安川電機 | C11: Consensus 2027/2連I予 (n=15) | D11: 4503 | E11: 11679 | F11: 5927 | G11: 618 | H11: 476 | I11: 183.7 | J11: 1864.3 | K11: 24.5 | L11: 2.42 | M11: 10.4 | N11: 9.7 | O11: 9.3
A12: 62680 | B12: ナブテスコ | C12: Consensus 2026/12連I予 (n=5) | D12: 4530 | E12: 5404 | F12: 3481 | G12: 338 | H12: 253 | I12: 217.87 | J12: 2320.4 | K12: 20.8 | L12: 1.95 | M12: 9.7 | N12: 8.8 | O12: 13
A14: MEDIAN (peers) | K14: 20.8 | L14: 2.42 | M14: 15.1 | N14: 11.1 | O14: 17.7

Sheet Summary
A1: SMC (62730) — Model Summary [BLUE=input, BLACK=formula, GREEN=cross-sheet, YELLOW=key tunable]
A3: Metric | B3: Hist FY | C3: Model FY+1 | D3: Model FY+2 | E3: Company Guide | F3: vs Guide %
A4: Sales (億) | B4: =FS!F4+FS!G4+FS!H4+FS!E4 -> 8425.4 | C4: =FS!I4+FS!J4+FS!K4+FS!L4 -> 10814.373 | D4: =FS!N4+FS!O4+FS!P4+FS!M4 -> 11580.043 | E4: 10000 | F4: =C4/E4-1 -> 0.081437257
A5: OP (億) | B5: =FS!F9+FS!G9+FS!H9+FS!E9 -> 1905.5 | C5: =FS!I9+FS!J9+FS!K9+FS!L9 -> 2956.3723 | D5: =FS!N9+FS!O9+FS!P9+FS!M9 -> 3126.6117 | E5: 2190 | F5: =C5/E5-1 -> 0.34994169
A6: OPM % | B6: =B5/B4*100 -> 22.616137 | C6: =C5/C4*100 -> 27.337437 | D6: =D5/D4*100 -> 27 | E6: 21.9 | F6: =C6/E6-1 -> 0.2482848
A7: NP (億) | B7: =FS!F18+FS!G18+FS!H18+FS!E18 -> 1673 | C7: =FS!I18+FS!J18+FS!K18+FS!L18 -> 2254.5118 | D7: =FS!N18+FS!O18+FS!P18+FS!M18 -> 2689.8553 | E7: 1700 | F7: =C7/E7-1 -> 0.32618341
A8: EPS (¥) | B8: =FS!F22+FS!G22+FS!H22+FS!E22 -> 2634.0189 | C8: =FS!J22+FS!K22+FS!L22+FS!I22 -> 3587.9185 | D8: =FS!N22+FS!O22+FS!P22+FS!M22 -> 4333.7872 | E8: 2692.46 | F8: =C8/E8-1 -> 0.33258006
A12: Cases | B12: Target Price | C12: Odds | D12: Comment
A13: Bull | B13: =4000*25 -> 100000 | C13: =0.333333333333333%*100 -> 0.33333333 | D13: EPS 4000@25x
A14: Base | B14: =3500*25 -> 87500 | C14: =0.333333333333333%*100 -> 0.33333333 | D14: EPS 3500@25x
A15: Bear | B15: =3000*20 -> 60000 | C15: =0.333333333333333%*100 -> 0.33333333 | D15: EPS 3000@20x
A16: Expected | B16: =SUMPRODUCT(B13:B15,C13:C15) -> 82500 | C16: =SUM(C13:C15) -> 1
A17: Current | B17: 67890
A18: Upside | B18: =B16/B17-1 -> 0.21520106

Sheet Cycle
A1: SMC — Cycle Multiple Bands (full history, PIT, split-adjusted)
A2: UPCYCLE → read P/E. BOTTOM → read P/B (trough EPS makes P/E meaningless). Phase clock is DESCRIPTIVE (full-sample OPM median), never a signal.
A4: 0. P/B comparability gate — cash ÷ equity (FY-end)
A5: range 21.5%-40.7%, mean 28.7%, first3→last3 drift -2.0pp → P/B COMPARABLE across time
A7: 1. Full-history band (monthly, TTM basis)
A8: Metric | B8: n | C8: min | D8: p10 | E8: p25 | F8: median | G8: p75 | H8: p90 | I8: max
A9: P/E | B9: 204 | C9: 14.36 | D9: 17.13 | E9: 19.8 | F9: 22.11 | G9: 26.38 | H9: 33.25 | I9: 188.31
A10: P/B | B10: 208 | C10: 1.35 | D10: 1.55 | E10: 1.85 | F10: 2.28 | G10: 2.75 | H10: 3.11 | I10: 3.72
A12: 2. By cycle phase (OPM median split = 27.44%)
A13: Phase | B13: months | C13: OPM med % | D13: P/E p25 | E13: P/E med | F13: P/E p75 | G13: P/B min | H13: P/B p25 | I13: P/B med | J13: P/B p75 | K13: P/B max
A14: 1 Recovery (低OPM・回升) | B14: 43 | C14: 25.3 | D14: 19.2 | E14: 21.6 | F14: 23.3 | G14: 1.41 | H14: 1.7 | I14: 1.98 | J14: 2.49 | K14: 3.12
A15: 2 Expansion (高OPM・上行) | B15: 78 | C15: 30.5 | D15: 18.2 | E15: 20.7 | F15: 22.7 | G15: 1.59 | H15: 2.18 | I15: 2.57 | J15: 2.85 | K15: 3.72
A16: 3 Early-down (高OPM・转跌) | B16: 27 | C16: 28.4 | D16: 22.8 | E16: 27.4 | F16: 30.3 | G16: 1.94 | H16: 2.26 | I16: 2.56 | J16: 2.88 | K16: 3.42
A17: 4 Trough (低OPM・下行) | B17: 48 | C17: 24.1 | D17: 20.9 | E17: 22.2 | F17: 30 | G17: 1.44 | H17: 1.74 | I17: 2 | J17: 2.38 | K17: 3.53
A19: 3. Cycle extremes (±12M local, PIT). 'prov' = inside the last 12M, no right-hand side yet
A20: Event | B20: Date | C20: Price | D20: TTM OP (億) | E20: OPM % | F20: TTM EPS | G20: BPS | H20: P/E | I20: P/B | J20: confirmed
A21: 盈利峰 OP peak | B21: 2009-05 | C21: 10150 | D21: 497 | E21: 17.5 | F21: 379 | G21: 7109 | H21: 26.8 | I21: 1.43 | J21: yes
A22: 盈利峰 OP peak | B22: 2011-11 | C22: 12520 | D22: 932 | E22: 27.6 | F22: 790 | G22: 7812 | H22: 15.9 | I22: 1.6 | J22: yes
A23: 盈利峰 OP peak | B23: 2016-02 | C23: 26130 | D23: 1373 | E23: 28.7 | F23: 1541 | G23: 13682 | H23: 17 | I23: 1.91 | J23: yes
A24: 盈利峰 OP peak | B24: 2018-08 | C24: 36970 | D24: 1989 | E24: 33.1 | F24: 2120 | G24: 17067 | H24: 17.4 | I24: 2.17 | J24: yes
A25: 盈利峰 OP peak | B25: 2023-05 | C25: 75080 | D25: 2582 | E25: 31.3 | F25: 3449 | G25: 26332 | H25: 21.8 | I25: 2.85 | J25: yes
A26: 盈利峰 OP peak | B26: 2026-08 | C26: 70300 | D26: 2201 | E26: 24.1 | F26: 3179 | G26: 33499 | H26: 22.1 | I26: 2.1 | J26: prov
A28: 盈利谷 OP trough | B28: 2010-02 | C28: 11090 | D28: 75 | E28: 3.8 | F28: 67 | G28: 7221 | H28: 164.6 | I28: 1.54 | J28: yes
A29: 盈利谷 OP trough | B29: 2013-02 | C29: 16080 | D29: 742 | E29: 22.5 | F29: 904 | G29: 8535 | H29: 17.8 | I29: 1.88 | J29: yes
A30: 盈利谷 OP trough | B30: 2016-11 | C30: 32520 | D30: 1314 | E30: 28.4 | F30: 1251 | G30: 13981 | H30: 26 | I30: 2.33 | J30: yes
A31: 盈利谷 OP trough | B31: 2020-11 | C31: 66320 | D31: 1378 | E31: 26.8 | F31: 1551 | G31: 18795 | H31: 42.8 | I31: 3.53 | J31: yes
A32: 盈利谷 OP trough | B32: 2025-11 | C32: 54880 | D32: 1815 | E32: 22.8 | F32: 2474 | G32: 30255 | H32: 22.2 | I32: 1.81 | J32: prov
A34: 股价顶 Price top | B34: 2011-04 | C34: 14750 | D34: 784 | E34: 25.3 | F34: 721 | G34: 7630 | H34: 20.4 | I34: 1.93 | J34: yes
... A45: 股价底 Price bottom | B45: 2025-09 | C45: 45430 | D45: 1823 | E45: 23.1 | F45: 2231 | G45: 30255 | H45: 20.4 | I45: 1.5 | J45: prov
A47: 4. Current reading
A48: As of | B48: 2026-08-28
A49: Price (¥) | B49: 70300
A50: TTM EPS (¥) | B50: 3179
A51: BPS (¥) | B51: 33499
A52: TTM OPM % | B52: 24.1
A53: TTM OP YoY % | B53: 20.7
A54: P/E | B54: 22.1
A55: P/B | B55: 2.1
A56: Phase (mechanical) | B56: 1 Recovery (低OPM・回升)
A58: 5. ONE-YEAR-FORWARD price = band × model NTM EPS / NTM BPS (live off Valuation). NOT a fair value today: the bands above are measured on TRAILING EPS/BPS, so applying them to NTM figures prices the stock 12M out AT THAT MULTIPLE. Band × CURRENT TTM EPS/BPS is the today-fair-value read.
A59: NTM EPS (¥) — Valuation!B32 | B59: =Valuation!B32 -> 3920.7771
A60: NTM BPS (¥) — Valuation!B45 | B60: =Valuation!B45 -> 36279.627
A62: Band | B62: P/E x | C62: → price | D62: P/B x | E62: → price
A63: Full-history p25 | B63: 19.8 | C63: =B63*$B$59 -> 77631.386 | D63: 1.85 | E63: =D63*$B$60 -> 67117.309
A64: Full-history median | B64: 22.11 | C64: =B64*$B$59 -> 86688.381 | D64: 2.28 | E64: =D64*$B$60 -> 82717.548
A65: Full-history p75 | B65: 26.38 | C65: =B65*$B$59 -> 103430.1 | D65: 2.75 | E65: =D65*$B$60 -> 99768.973
A66: Full-history p90 | B66: 33.25 | C66: =B66*$B$59 -> 130365.84 | D66: 3.11 | E66: =D66*$B$60 -> 112829.64
A67: 1 Recovery (低OPM・回升) median | B67: 21.57 | C67: =B67*$B$59 -> 84571.162 | D67: 1.98 | E67: =D67*$B$60 -> 71833.661
A68: 2 Expansion (高OPM・上行) median | B68: 20.72 | C68: =B68*$B$59 -> 81238.501 | D68: 2.57 | E68: =D68*$B$60 -> 93238.64
A69: 3 Early-down (高OPM・转跌) median | B69: 27.36 | C69: =B69*$B$59 -> 107272.46 | D69: 2.56 | E69: =D69*$B$60 -> 92875.844
A70: 4 Trough (低OPM・下行) median | B70: 22.16 | C70: =B70*$B$59 -> 86884.42 | D70: 2 | E70: =D70*$B$60 -> 72559.253
A73: 6. FORWARD P/E on 会社予想 (company guidance), full history, PIT
A74: A CONSENSUS forward band is not buildable here — PIT consensus snapshots only start 2026-04-09 (~5 months). Company guidance is carried PIT in fins_summary since 2008, and 会社予想PER is the multiple the JP market actually quotes. The sandbag is handled explicitly by the beat table below, not left implicit in the multiple.
A76: Guide horizon (compare LIKE FOR LIKE) | B76: n | C76: min | D76: p10 | E76: p25 | F76: median | G76: p75 | H76: p90 | I76: max
A77: 9-11M left (期初 4-6月) | B77: 34 | C77: 14.2 | D77: 16.9 | E77: 20.5 | F77: 22.7 | G77: 25.6 | H77: 32 | I77: 51
A78: 6-8M left (1Q後 7-9月) ← CURRENT | B78: 50 | C78: 12.6 | D78: 15.6 | E78: 19.9 | F78: 22.5 | G78: 24.8 | H78: 30.9 | I78: 54
A79: 3-5M left (2Q後 10-12月) | B79: 51 | C79: 13.7 | D79: 16.5 | E79: 20.2 | F79: 23.1 | G79: 26.5 | H79: 42.5 | I79: 120.5
A80: 0-2M left (3Q後 1-3月) | B80: 54 | C80: 13 | D80: 17.9 | E80: 20.1 | F80: 23.1 | G80: 27 | H80: 38.2 | I80: 125
A81: All horizons pooled | B81: 189 | C81: 12.6 | D81: 17.1 | E81: 20.1 | F81: 22.8 | G81: 25.7 | H81: 33.7 | I81: 125
A83: Guide EPS in force (¥) | B83: 2692.46
A84: Guided FY end | B84: 2027-03
A85: Months of guide left | B85: 7
A86: CURRENT 会社予想 fwd P/E | B86: 26.11
A87: percentile within the SAME horizon bucket | B87: 77.4
A89: Sandbag check — actual FY EPS ÷ the FIRST guide issued for that FY
A90: Stat | B90: n | C90: min | D90: p25 | E90: median | F90: p75 | G90: max | H90: beat rate %
A91: guide → actual factor | B91: 17 | C91: 0.808 | D91: 0.968 | E91: 1.197 | F91: 1.379 | G91: 9.8 | H91: 65
A92: Read: a factor of 1.20 means the company came in 20% above its own opening guide. The max is a post-crash artefact (guide reset to near-zero), so use the median.
A94: Same price, four EPS vintages — this is what the 'P/E' argument is really about
A95: EPS vintage | B95: FY EPS (¥) | C95: fwd P/E | D95: implied beat vs guide
A96: 会社 guide (fins_summary) | B96: 2692.46 | C96: =IFERROR(70300/B96,"") -> 26.109951 | D96: =IFERROR(B96/B96,"") -> 1
A97: 街道 consensus (Comp sheet) | B97: =IFERROR(INDEX(Comp!I:I,MATCH("62730",Comp!A:A,0)),"") -> 3353.99 | C97: =IFERROR(70300/B97,"") -> 20.96011 | D97: =IFERROR(B97/B96,"") -> 1.2456972
A98: guide × historical median beat | B98: =B96*1.1972 -> 3223.4131 | C98: =IFERROR(70300/B98,"") -> 21.809181 | D98: =IFERROR(B98/B96,"") -> 1.1972
A99: 本模型 this model (FY guide-year) | B99: =FS!V22 -> 3587.9185 | C99: =IFERROR(70300/B99,"") -> 19.593533 | D99: =IFERROR(B99/B96,"") -> 1.3325801
A100: Price used: ¥70,300 (2026-08-28). The 'implied beat' column says what each EPS vintage assumes about the sandbag — compare it against the beat-factor distribution above before believing any of them.

Sheet Checks
A1: SMC — Integrity Checks. All cells should be 0. Master cell at top.
A3: MASTER STATUS | B3: =IF(SUMPRODUCT(ABS(IFERROR(B6:Q12,0)))<0.5,"✓ ALL CHECKS PASS","✗ ERRORS DETECTED — review red cells below") -> ✓ ALL CHECKS PASS
A5: Check | B5: FY24Q2 | C5: FY24Q3 | D5: FY24Q4 | E5: FY25Q1 | F5: FY25Q2 | G5: FY25Q3 | H5: FY25Q4 | I5: FY26Q1 | J5: FY26Q2 | K5: FY26Q3 | L5: FY26Q4 | M5: FY27Q1 | N5: FY27Q2 | O5: FY27Q3 | P5: FY27Q4 | Q5: FY28Q1
A6: BS: TA - TL - TE | B6: =FS!B50 -> 0 | C6: =FS!C50 -> 0.1 | D6: =FS!D50 -> 0.1 | E6: =FS!E50 -> 0 | F6: =FS!F50 -> 0 | G6: =FS!G50 -> 0 | H6: =FS!H50 -> 0 | I6: =FS!I50 -> 0.1 | ... Q6: =FS!Q50 -> 0.1
A7: Cash tie: BS Cash - (Prior Cash + CF NetΔ) | C7: =FS!C30 - (FS!B30 + FS!C66) -> 436.64736 | D7: =FS!D30 - (FS!C30 + FS!D66) -> -425.5 | E7: =FS!E30 - (FS!D30 + FS!E66) -> -87.28208 | F7: =FS!F30 - (FS!E30 + FS!F66) -> -70.9 | G7: =FS!G30 - (FS!F30 + FS!G66) -> 215.81024 | H7: =FS!H30 - (FS!G30 + FS!H66) -> 208.4 | I7: =FS!I30 - (FS!H30 + FS!I66) -> 571.72736 | J7: =FS!J30 - (FS!I30 + FS!J66) -> 0 | ... Q7: =FS!Q30 - (FS!P30 + FS!Q66) -> 0
A8: NI link: PL NI - CF NI | B8: =FS!B18 - FS!B69 -> 0 | C8: =FS!C18 - FS!C69 -> 0 | D8: =FS!D18 - FS!D69 -> 0 | E8: =FS!E18 - FS!E69 -> 0 | F8: =FS!F18 - FS!F69 -> 0 | G8: =FS!G18 - FS!G69 -> 0 | H8: =FS!H18 - FS!H69 -> 0 | I8: =FS!I18 - FS!I69 -> 0 | ... Q8: =FS!Q18 - FS!Q69 -> 0
A9: RE roll: ΔRE - (NI - Div - Buyback) | C9: =FS!C46 - (FS!B46 + FS!C18 - FS!C75 - FS!C76) -> -319.9 | D9: =FS!D46 - (FS!C46 + FS!D18 - FS!D75 - FS!D76) -> 473.5 | E9: =FS!E46 - (FS!D46 + FS!E18 - FS!E75 - FS!E76) -> -2348.1 | F9: =FS!F46 - (FS!E46 + FS!F18 - FS!F75 - FS!F76) -> 537.2 | G9: =FS!G46 - (FS!F46 + FS!G18 - FS!G75 - FS!G76) -> -312.4 | H9: =FS!H46 - (FS!G46 + FS!H18 - FS!H75 - FS!H76) -> 399 | I9: =FS!I46 - (FS!H46 + FS!I18 - FS!I75 - FS!I76) -> -315.8 | J9: =FS!J46 - (FS!I46 + FS!J18 - FS!J75 - FS!J76) -> 0 | ... Q9: =FS!Q46 - (FS!P46 + FS!Q18 - FS!Q75 - FS!Q76) -> 0
A10: ΔWC tie: CF ΔWC vs BS ΔAR/Inv/AP | C10: =FS!C71 - (-(FS!C31-FS!B31) - (FS!C32-FS!B32) + (FS!C40-FS!B40)) -> 0 | D10: =FS!D71 - (-(FS!D31-FS!C31) - (FS!D32-FS!C32) + (FS!D40-FS!C40)) -> 0 | E10: =FS!E71 - (-(FS!E31-FS!D31) - (FS!E32-FS!D32) + (FS!E40-FS!D40)) -> 0 | F10: =FS!F71 - (-(FS!F31-FS!E31) - (FS!F32-FS!E32) + (FS!F40-FS!E40)) -> 0 | G10: =FS!G71 - (-(FS!G31-FS!F31) - (FS!G32-FS!F32) + (FS!G40-FS!F40)) -> 0 | H10: =FS!H71 - (-(FS!H31-FS!G31) - (FS!H32-FS!G32) + (FS!H40-FS!G40)) -> 0 | I10: =FS!I71 - (-(FS!I31-FS!H31) - (FS!I32-FS!H32) + (FS!I40-FS!H40)) -> 0 | J10: =FS!J71 - (-(FS!J31-FS!I31) - (FS!J32-FS!I32) + (FS!J40-FS!I40)) -> 0 | ... Q10: =FS!Q71 - (-(FS!Q31-FS!P31) - (FS!Q32-FS!P32) + (FS!Q40-FS!P40)) -> 0
A11: CapEx tie: CF Capex - Assumption | J11: =FS!J73 - FS!$B$95 -> 0 | K11: =FS!K73 - FS!$B$95 -> 0 | L11: =FS!L73 - FS!$B$95 -> 0 | M11: =FS!M73 - FS!$B$95 -> 0 | N11: =FS!N73 - FS!$B$95 -> 0 | O11: =FS!O73 - FS!$B$95 -> 0 | P11: =FS!P73 - FS!$B$95 -> 0 | Q11: =FS!Q73 - FS!$B$95 -> 0
A12: Buyback tie: CF Buyback - Assumption | J12: =FS!J76 - FS!$B$96 -> 0 | K12: =FS!K76 - FS!$B$96 -> 0 | L12: =FS!L76 - FS!$B$96 -> 0 | M12: =FS!M76 - FS!$B$96 -> 0 | N12: =FS!N76 - FS!$B$96 -> 0 | O12: =FS!O76 - FS!$B$96 -> 0 | P12: =FS!P76 - FS!$B$96 -> 0 | Q12: =FS!Q76 - FS!$B$96 -> 0
A15: Sign convention reminder:
A16: CFO ΔAR (asset increase) = NEGATIVE (use of cash)
A17: CFO ΔAP (liability increase) = POSITIVE (source of cash)
A18: CFI Capex = NEGATIVE outflow (stored as positive in row 14, sign on FCF formula)
A19: CFF Dividend / Buyback stored as POSITIVE (outflow); FCF = -Div - Buyback + DebtIss
A20: Cash tie: BS Cash[N] = BS Cash[N-1] + CF (OCF + ICF + FCF)
A21: RE roll: BS RE[N] = BS RE[N-1] + PL NI[N] - CF Div[N] - CF Buyback[N]
