Workbook

Sheet Drivers
A1: Meidensha 65080 — Drivers
A2: BLUE = input/actual; BLACK = same-sheet formula; GREEN = cross-sheet; YELLOW bg = forecast cell
A4: 1. Sales QoQ Growth Assumptions (%) — adjust to flex PL forecast
B5: FY24Q1 | C5: FY24Q2 | D5: FY24Q3 | E5: FY24Q4 | F5: FY25Q1 | G5: FY25Q2 | H5: FY25Q3 | I5: FY25Q4 | J5: FY26Q1 | K5: FY26Q2 | L5: FY26Q3 | M5: FY26Q4 | N5: FY27Q1 | O5: FY27Q2 | P5: FY27Q3 | Q5: FY27Q4 | R5: FY28Q1 | U5: FY24 | V5: FY25 | W5: FY26 | X5: FY27 | Y5: FY28
A6: Power_Infrastructure | K6: 11.14 | L6: -4.05 | M6: 68.25 | N6: -40 | O6: 11.14 | P6: -4.05 | Q6: 68.25 | R6: -40
A7: Social_Systems | K7: 11.14 | L7: -4.05 | M7: 68.25 | N7: -40 | O7: 11.14 | P7: -4.05 | Q7: 68.25 | R7: -40
A8: Industrial_Mobility | K8: 11.14 | L8: -4.05 | M8: 68.25 | N8: -40 | O8: 11.14 | P8: -4.05 | Q8: 68.25 | R8: -40
A9: Field_Engineering | K9: 11.14 | L9: -4.05 | M9: 68.25 | N9: -40 | O9: 11.14 | P9: -4.05 | Q9: 68.25 | R9: -40
A10: Real_Estate | K10: 11.14 | L10: -4.05 | M10: 68.25 | N10: -40 | O10: 11.14 | P10: -4.05 | Q10: 68.25 | R10: -40
A11: Other | K11: 11.14 | L11: -4.05 | M11: 68.25 | N11: -40 | O11: 11.14 | P11: -4.05 | Q11: 68.25 | R11: -40
A13: Consolidated OPM (%) — drives OP (Sales × OPM) | K13: 4.09 | L13: 5.63 | M13: 15.63 | N13: 5.5 | O13: 5 | P13: 6 | Q13: 16 | R13: 5.5
A15: 2. Sales by Segment (億円) — historical actuals from deck
B16: FY24Q1 | C16: FY24Q2 | D16: FY24Q3 | E16: FY24Q4 | F16: FY25Q1 | G16: FY25Q2 | H16: FY25Q3 | I16: FY25Q4 | J16: FY26Q1 | U16: FY24 | V16: FY25 | W16: FY26
A17: Power_Infrastructure | E17: 864.37 | I17: 1008.44 | U17: =IF(COUNT(B17:E17)=0,"",SUM(B17:E17)) | V17: =IF(COUNT(F17:I17)=0,"",SUM(F17:I17)) | W17: =IF(COUNT(J17:M17)=0,"",SUM(J17:M17)) | X17: =IF(COUNT(N17:Q17)=0,"",SUM(N17:Q17)) | Y17: =IF(COUNT(R17:R17)=0,"",SUM(R17:R17))
A18: Social_Systems | E18: 963.23 | I18: 1045.55 | U18: =IF(COUNT(B18:E18)=0,"",SUM(B18:E18)) | V18: =IF(COUNT(F18:I18)=0,"",SUM(F18:I18)) | W18: =IF(COUNT(J18:M18)=0,"",SUM(J18:M18)) | X18: =IF(COUNT(N18:Q18)=0,"",SUM(N18:Q18)) | Y18: =IF(COUNT(R18:R18)=0,"",SUM(R18:R18))
A19: Industrial_Mobility | E19: 720.79 | I19: 693.08 | U19: =IF(COUNT(B19:E19)=0,"",SUM(B19:E19)) | V19: =IF(COUNT(F19:I19)=0,"",SUM(F19:I19)) | W19: =IF(COUNT(J19:M19)=0,"",SUM(J19:M19)) | X19: =IF(COUNT(N19:Q19)=0,"",SUM(N19:Q19)) | Y19: =IF(COUNT(R19:R19)=0,"",SUM(R19:R19))
A20: Field_Engineering | E20: 495.67 | I20: 570.07 | U20: =IF(COUNT(B20:E20)=0,"",SUM(B20:E20)) | V20: =IF(COUNT(F20:I20)=0,"",SUM(F20:I20)) | W20: =IF(COUNT(J20:M20)=0,"",SUM(J20:M20)) | X20: =IF(COUNT(N20:Q20)=0,"",SUM(N20:Q20)) | Y20: =IF(COUNT(R20:R20)=0,"",SUM(R20:R20))
A21: Real_Estate | E21: 32.35 | I21: 32.33 | U21: =IF(COUNT(B21:E21)=0,"",SUM(B21:E21)) | V21: =IF(COUNT(F21:I21)=0,"",SUM(F21:I21)) | W21: =IF(COUNT(J21:M21)=0,"",SUM(J21:M21)) | X21: =IF(COUNT(N21:Q21)=0,"",SUM(N21:Q21)) | Y21: =IF(COUNT(R21:R21)=0,"",SUM(R21:R21))
A22: Other | E22: 86.72 | I22: 89.2 | U22: =IF(COUNT(B22:E22)=0,"",SUM(B22:E22)) | V22: =IF(COUNT(F22:I22)=0,"",SUM(F22:I22)) | W22: =IF(COUNT(J22:M22)=0,"",SUM(J22:M22)) | X22: =IF(COUNT(N22:Q22)=0,"",SUM(N22:Q22)) | Y22: =IF(COUNT(R22:R22)=0,"",SUM(R22:R22))
A23: TOTAL | B23: =SUM(B17:B22) | C23: =SUM(C17:C22) | D23: =SUM(D17:D22) | E23: =SUM(E17:E22) | F23: =SUM(F17:F22) | G23: =SUM(G17:G22) | H23: =SUM(H17:H22) | I23: =SUM(I17:I22) | J23: =SUM(J17:J22) | U23: =IF(COUNT(B23:E23)=0,"",SUM(B23:E23)) | V23: =IF(COUNT(F23:I23)=0,"",SUM(F23:I23)) | W23: =IF(COUNT(J23:M23)=0,"",SUM(J23:M23)) | X23: =IF(COUNT(N23:Q23)=0,"",SUM(N23:Q23)) | Y23: =IF(COUNT(R23:R23)=0,"",SUM(R23:R23))
A25: ↳ Segment OP (factbook 営業利益, 億)
A26: Power_Infrastructure OP | U26: =IF(COUNT(B26:E26)=0,"",SUM(B26:E26)) | V26: =IF(COUNT(F26:I26)=0,"",SUM(F26:I26)) | W26: =IF(COUNT(J26:M26)=0,"",SUM(J26:M26)) | X26: =IF(COUNT(N26:Q26)=0,"",SUM(N26:Q26)) | Y26: =IF(COUNT(R26:R26)=0,"",SUM(R26:R26))
A27: Social_Systems OP | U27: =IF(COUNT(B27:E27)=0,"",SUM(B27:E27)) | V27: =IF(COUNT(F27:I27)=0,"",SUM(F27:I27)) | W27: =IF(COUNT(J27:M27)=0,"",SUM(J27:M27)) | X27: =IF(COUNT(N27:Q27)=0,"",SUM(N27:Q27)) | Y27: =IF(COUNT(R27:R27)=0,"",SUM(R27:R27))
A28: Industrial_Mobility OP | U28: =IF(COUNT(B28:E28)=0,"",SUM(B28:E28)) | V28: =IF(COUNT(F28:I28)=0,"",SUM(F28:I28)) | W28: =IF(COUNT(J28:M28)=0,"",SUM(J28:M28)) | X28: =IF(COUNT(N28:Q28)=0,"",SUM(N28:Q28)) | Y28: =IF(COUNT(R28:R28)=0,"",SUM(R28:R28))
A29: Field_Engineering OP | U29: =IF(COUNT(B29:E29)=0,"",SUM(B29:E29)) | V29: =IF(COUNT(F29:I29)=0,"",SUM(F29:I29)) | W29: =IF(COUNT(J29:M29)=0,"",SUM(J29:M29)) | X29: =IF(COUNT(N29:Q29)=0,"",SUM(N29:Q29)) | Y29: =IF(COUNT(R29:R29)=0,"",SUM(R29:R29))
A30: Real_Estate OP | U30: =IF(COUNT(B30:E30)=0,"",SUM(B30:E30)) | V30: =IF(COUNT(F30:I30)=0,"",SUM(F30:I30)) | W30: =IF(COUNT(J30:M30)=0,"",SUM(J30:M30)) | X30: =IF(COUNT(N30:Q30)=0,"",SUM(N30:Q30)) | Y30: =IF(COUNT(R30:R30)=0,"",SUM(R30:R30))
A31: Other OP | U31: =IF(COUNT(B31:E31)=0,"",SUM(B31:E31)) | V31: =IF(COUNT(F31:I31)=0,"",SUM(F31:I31)) | W31: =IF(COUNT(J31:M31)=0,"",SUM(J31:M31)) | X31: =IF(COUNT(N31:Q31)=0,"",SUM(N31:Q31)) | Y31: =IF(COUNT(R31:R31)=0,"",SUM(R31:R31))
A32: OP TOTAL (= consolidated) | B32: =SUM(B26:B31) | C32: =SUM(C26:C31) | D32: =SUM(D26:D31) | E32: =SUM(E26:E31) | F32: =SUM(F26:F31) | G32: =SUM(G26:G31) | H32: =SUM(H26:H31) | I32: =SUM(I26:I31) | J32: =SUM(J26:J31) | U32: =IF(COUNT(B32:E32)=0,"",SUM(B32:E32)) | V32: =IF(COUNT(F32:I32)=0,"",SUM(F32:I32)) | W32: =IF(COUNT(J32:M32)=0,"",SUM(J32:M32)) | X32: =IF(COUNT(N32:Q32)=0,"",SUM(N32:Q32)) | Y32: =IF(COUNT(R32:R32)=0,"",SUM(R32:R32))
A34: 4. Sales by Region (億円)
B35: FY24Q1 | C35: FY24Q2 | D35: FY24Q3 | E35: FY24Q4 | F35: FY25Q1 | G35: FY25Q2 | H35: FY25Q3 | I35: FY25Q4 | J35: FY26Q1 | U35: FY24 | V35: FY25 | W35: FY26
A36: Japan | U36: =IF(COUNT(B36:E36)=0,"",SUM(B36:E36)) | V36: =IF(COUNT(F36:I36)=0,"",SUM(F36:I36)) | W36: =IF(COUNT(J36:M36)=0,"",SUM(J36:M36)) | X36: =IF(COUNT(N36:Q36)=0,"",SUM(N36:Q36)) | Y36: =IF(COUNT(R36:R36)=0,"",SUM(R36:R36))
A37: Asia | U37: =IF(COUNT(B37:E37)=0,"",SUM(B37:E37)) | V37: =IF(COUNT(F37:I37)=0,"",SUM(F37:I37)) | W37: =IF(COUNT(J37:M37)=0,"",SUM(J37:M37)) | X37: =IF(COUNT(N37:Q37)=0,"",SUM(N37:Q37)) | Y37: =IF(COUNT(R37:R37)=0,"",SUM(R37:R37))
A38: Other_Overseas | U38: =IF(COUNT(B38:E38)=0,"",SUM(B38:E38)) | V38: =IF(COUNT(F38:I38)=0,"",SUM(F38:I38)) | W38: =IF(COUNT(J38:M38)=0,"",SUM(J38:M38)) | X38: =IF(COUNT(N38:Q38)=0,"",SUM(N38:Q38)) | Y38: =IF(COUNT(R38:R38)=0,"",SUM(R38:R38))
A39: TOTAL | B39: =SUM(B36:B38) | C39: =SUM(C36:C38) | D39: =SUM(D36:D38) | E39: =SUM(E36:E38) | F39: =SUM(F36:F38) | G39: =SUM(G36:G38) | H39: =SUM(H36:H38) | I39: =SUM(I36:I38) | J39: =SUM(J36:J38) | U39: =IF(COUNT(B39:E39)=0,"",SUM(B39:E39)) | V39: =IF(COUNT(F39:I39)=0,"",SUM(F39:I39)) | W39: =IF(COUNT(J39:M39)=0,"",SUM(J39:M39)) | X39: =IF(COUNT(N39:Q39)=0,"",SUM(N39:Q39)) | Y39: =IF(COUNT(R39:R39)=0,"",SUM(R39:R39))
A42: 6. Margin Assumptions (OP = Sales × per-Q consolidated OPM)
A43: Per-Segment GPM (reference)
A44: Segment | B44: GPM
A45: Power_Infrastructure | B45: 0.35
A46: Social_Systems | B46: 0.35
A47: Industrial_Mobility | B47: 0.35
A48: Field_Engineering | B48: 0.35
A49: Real_Estate | B49: 0.35
A50: Other | B50: 0.35
A52: Consolidated SG&A / Sales | B52: 0.2035

Sheet FS
A1: P&L (億円, EPS in JPY) — BLUE=actual/input, BLACK=formula, GREEN=cross-sheet, ORANGE=guide
A3: Line Item | B3: FY24Q1 | C3: FY24Q2 | D3: FY24Q3 | E3: FY24Q4 | F3: FY25Q1 | G3: FY25Q2 | H3: FY25Q3 | I3: FY25Q4 | J3: FY26Q1 | K3: FY26Q2 | L3: FY26Q3 | M3: FY26Q4 | N3: FY27Q1 | O3: FY27Q2 | P3: FY27Q3 | Q3: FY27Q4 | R3: FY28Q1 | U3: FY24 | V3: FY25 | W3: FY26 | X3: FY27 | Y3: FY28 | Z3: FY26 GUIDE | AA3: Model vs Guide | AB3: Forecast Formula (plain English)
A4: Sales | B4: 549.8 | C4: 651.2 | D4: 709.8 | E4: 1100.2 | F4: 583.9 | G4: 727.5 | H4: 727.1 | I4: 1223.4 | J4: 734.1 | K4: =J4*(1+11.14/100) | L4: =K4*(1+-4.05/100) | M4: =L4*(1+68.25/100) | N4: =M4*(1+-40.0/100) | O4: =N4*(1+11.14/100) | P4: =O4*(1+-4.05/100) | Q4: =P4*(1+68.25/100) | R4: =Q4*(1+-40.0/100) | U4: =IF(COUNTBLANK(B4:E4)>0,"",SUM(B4:E4)) | V4: =IF(COUNTBLANK(F4:I4)>0,"",SUM(F4:I4)) | W4: =IF(COUNTBLANK(J4:M4)>0,"",SUM(J4:M4)) | X4: =IF(COUNTBLANK(N4:Q4)>0,"",SUM(N4:Q4)) | Y4: =IF(COUNTBLANK(R4:R4)>0,"",SUM(R4:R4)) | AB4: prior Sales × QoQ growth (mean of cfg.order_growth_qoq across segments)
A5: COGS | B5: =B4-B6 | C5: =C4-C6 | D5: =D4-D6 | E5: =E4-E6 | F5: =F4-F6 | G5: =G4-G6 | H5: =H4-H6 | I5: =I4-I6 | ... R5: =R4-R6 | U5: =IF(COUNTBLANK(B5:E5)>0,"",SUM(B5:E5)) | V5: =IF(COUNTBLANK(F5:I5)>0,"",SUM(F5:I5)) | W5: =IF(COUNTBLANK(J5:M5)>0,"",SUM(J5:M5)) | X5: =IF(COUNTBLANK(N5:Q5)>0,"",SUM(N5:Q5)) | Y5: =IF(COUNTBLANK(R5:R5)>0,"",SUM(R5:R5)) | AB5: Sales − Gross Profit
A6: Gross Profit | B6: 134 | C6: 172.6 | D6: 192.7 | E6: 316.5 | F6: 152.5 | G6: 190.5 | H6: 206.6 | I6: 375.8 | J6: 217.6 | K6: =K9+K8 | L6: =L9+L8 | M6: =M9+M8 | N6: =N9+N8 | O6: =O9+O8 | P6: =P9+P8 | Q6: =Q9+Q8 | R6: =R9+R8 | U6: =IF(COUNTBLANK(B6:E6)>0,"",SUM(B6:E6)) | V6: =IF(COUNTBLANK(F6:I6)>0,"",SUM(F6:I6)) | W6: =IF(COUNTBLANK(J6:M6)>0,"",SUM(J6:M6)) | X6: =IF(COUNTBLANK(N6:Q6)>0,"",SUM(N6:Q6)) | Y6: =IF(COUNTBLANK(R6:R6)>0,"",SUM(R6:R6)) | AB6: OP + SG&A (OPM-driven: GP is derived, not an input)
A7: GPM % | B7: =B6/B4*100 | C7: =C6/C4*100 | D7: =D6/D4*100 | E7: =E6/E4*100 | F7: =F6/F4*100 | G7: =G6/G4*100 | H7: =H6/H4*100 | I7: =I6/I4*100 | ... R7: =R6/R4*100 | U7: =IF(OR(COUNTBLANK(B6:E6)>0,COUNTBLANK(B4:E4)>0),"",SUM(B6:E6)/SUM(B4:E4)*100) | V7: =IF(OR(COUNTBLANK(F6:I6)>0,COUNTBLANK(F4:I4)>0),"",SUM(F6:I6)/SUM(F4:I4)*100) | W7: =IF(OR(COUNTBLANK(J6:M6)>0,COUNTBLANK(J4:M4)>0),"",SUM(J6:M6)/SUM(J4:M4)*100) | X7: =IF(OR(COUNTBLANK(N6:Q6)>0,COUNTBLANK(N4:Q4)>0),"",SUM(N6:Q6)/SUM(N4:Q4)*100) | Y7: =IF(OR(COUNTBLANK(R6:R6)>0,COUNTBLANK(R4:R4)>0),"",SUM(R6:R6)/SUM(R4:R4)*100) | AB7: Gross Profit ÷ Sales
A8: SG&A | B8: =B6-B9 | C8: =C6-C9 | D8: =D6-D9 | E8: =E6-E9 | F8: =F6-F9 | G8: =G6-G9 | H8: =H6-H9 | I8: =I6-I9 | J8: =J6-J9 | K8: =K4*0.2035 | L8: =L4*0.2035 | M8: =M4*0.2035 | N8: =N4*0.2035 | O8: =O4*0.2035 | P8: =P4*0.2035 | Q8: =Q4*0.2035 | R8: =R4*0.2035 | U8: =IF(COUNTBLANK(B8:E8)>0,"",SUM(B8:E8)) | V8: =IF(COUNTBLANK(F8:I8)>0,"",SUM(F8:I8)) | W8: =IF(COUNTBLANK(J8:M8)>0,"",SUM(J8:M8)) | X8: =IF(COUNTBLANK(N8:Q8)>0,"",SUM(N8:Q8)) | Y8: =IF(COUNTBLANK(R8:R8)>0,"",SUM(R8:R8)) | AB8: Sales × 20.3% (yaml override (recent run-rate))
A9: Operating Profit | B9: -9 | C9: 28 | D9: 40.8 | E9: 155.2 | F9: 3.5 | G9: 24.4 | H9: 42.9 | I9: 200.4 | J9: 46.6 | K9: =K4*Drivers!K13/100 | L9: =L4*Drivers!L13/100 | M9: =M4*Drivers!M13/100 | N9: =N4*Drivers!N13/100 | O9: =O4*Drivers!O13/100 | P9: =P4*Drivers!P13/100 | Q9: =Q4*Drivers!Q13/100 | R9: =R4*Drivers!R13/100 | U9: =IF(COUNTBLANK(B9:E9)>0,"",SUM(B9:E9)) | V9: =IF(COUNTBLANK(F9:I9)>0,"",SUM(F9:I9)) | W9: =IF(COUNTBLANK(J9:M9)>0,"",SUM(J9:M9)) | X9: =IF(COUNTBLANK(N9:Q9)>0,"",SUM(N9:Q9)) | Y9: =IF(COUNTBLANK(R9:R9)>0,"",SUM(R9:R9)) | AB9: Sales × per-Q consolidated OPM (Drivers)
A10: OPM % | B10: =B9/B4*100 | C10: =C9/C4*100 | D10: =D9/D4*100 | E10: =E9/E4*100 | F10: =F9/F4*100 | G10: =G9/G4*100 | H10: =H9/H4*100 | I10: =I9/I4*100 | ... R10: =R9/R4*100 | U10: =IF(OR(COUNTBLANK(B9:E9)>0,COUNTBLANK(B4:E4)>0),"",SUM(B9:E9)/SUM(B4:E4)*100) | V10: =IF(OR(COUNTBLANK(F9:I9)>0,COUNTBLANK(F4:I4)>0),"",SUM(F9:I9)/SUM(F4:I4)*100) | W10: =IF(OR(COUNTBLANK(J9:M9)>0,COUNTBLANK(J4:M4)>0),"",SUM(J9:M9)/SUM(J4:M4)*100) | X10: =IF(OR(COUNTBLANK(N9:Q9)>0,COUNTBLANK(N4:Q4)>0),"",SUM(N9:Q9)/SUM(N4:Q4)*100) | Y10: =IF(OR(COUNTBLANK(R9:R9)>0,COUNTBLANK(R4:R4)>0),"",SUM(R9:R9)/SUM(R4:R4)*100) | AB10: OP ÷ Sales
A11: ± Non-Op / 特別 (net) | B11: =B12-B9 | C11: =C12-C9 | D11: =D12-D9 | E11: =E12-E9 | F11: =F12-F9 | G11: =G12-G9 | H11: =H12-H9 | I11: =I12-I9 | J11: =J12-J9 | K11: =K9*FS!$B$86/100 | L11: =L9*FS!$B$86/100 | M11: =M9*FS!$B$86/100 | N11: =N9*FS!$B$86/100 | O11: =O9*FS!$B$86/100 | P11: =P9*FS!$B$86/100 | Q11: =Q9*FS!$B$86/100 | R11: =R9*FS!$B$86/100 | U11: =IF(COUNTBLANK(B11:E11)>0,"",SUM(B11:E11)) | V11: =IF(COUNTBLANK(F11:I11)>0,"",SUM(F11:I11)) | W11: =IF(COUNTBLANK(J11:M11)>0,"",SUM(J11:M11)) | X11: =IF(COUNTBLANK(N11:Q11)>0,"",SUM(N11:Q11)) | Y11: =IF(COUNTBLANK(R11:R11)>0,"",SUM(R11:R11)) | AB11: Hist: Pretax−OP (実際 金融/持分法/特別); Fcst: OP × -0.2%
A12: Pretax Profit (税前) | B12: 14.2 | C12: 14.3 | D12: 56.2 | E12: 153.7 | F12: 5.6 | G12: 24 | H12: 106 | I12: 172.5 | J12: 70 | K12: =K9+K11 | L12: =L9+L11 | M12: =M9+M11 | N12: =N9+N11 | O12: =O9+O11 | P12: =P9+P11 | Q12: =Q9+Q11 | R12: =R9+R11 | U12: =IF(COUNTBLANK(B12:E12)>0,"",SUM(B12:E12)) | V12: =IF(COUNTBLANK(F12:I12)>0,"",SUM(F12:I12)) | W12: =IF(COUNTBLANK(J12:M12)>0,"",SUM(J12:M12)) | X12: =IF(COUNTBLANK(N12:Q12)>0,"",SUM(N12:Q12)) | Y12: =IF(COUNTBLANK(R12:R12)>0,"",SUM(R12:R12)) | AB12: Pretax (税前): Hist=disclosed actual; Fcst=OP + Non-Op
A13: Pretax M % | B13: =B12/B4*100 | C13: =C12/C4*100 | D13: =D12/D4*100 | E13: =E12/E4*100 | F13: =F12/F4*100 | G13: =G12/G4*100 | H13: =H12/H4*100 | I13: =I12/I4*100 | ... R13: =R12/R4*100 | U13: =IF(OR(COUNTBLANK(B12:E12)>0,COUNTBLANK(B4:E4)>0),"",SUM(B12:E12)/SUM(B4:E4)*100) | V13: =IF(OR(COUNTBLANK(F12:I12)>0,COUNTBLANK(F4:I4)>0),"",SUM(F12:I12)/SUM(F4:I4)*100) | W13: =IF(OR(COUNTBLANK(J12:M12)>0,COUNTBLANK(J4:M4)>0),"",SUM(J12:M12)/SUM(J4:M4)*100) | X13: =IF(OR(COUNTBLANK(N12:Q12)>0,COUNTBLANK(N4:Q4)>0),"",SUM(N12:Q12)/SUM(N4:Q4)*100) | Y13: =IF(OR(COUNTBLANK(R12:R12)>0,COUNTBLANK(R4:R4)>0),"",SUM(R12:R12)/SUM(R4:R4)*100) | AB13: Pretax ÷ Sales
A14: − Income Tax | B14: 3.7 | C14: 3.6 | D14: 15.5 | E14: 26.8 | F14: 0.9 | G14: 7.6 | H14: 28.9 | I14: 30.7 | J14: 19 | K14: =K12*FS!$B$85/100 | L14: =L12*FS!$B$85/100 | M14: =M12*FS!$B$85/100 | N14: =N12*FS!$B$85/100 | O14: =O12*FS!$B$85/100 | P14: =P12*FS!$B$85/100 | Q14: =Q12*FS!$B$85/100 | R14: =R12*FS!$B$85/100 | U14: =IF(COUNTBLANK(B14:E14)>0,"",SUM(B14:E14)) | V14: =IF(COUNTBLANK(F14:I14)>0,"",SUM(F14:I14)) | W14: =IF(COUNTBLANK(J14:M14)>0,"",SUM(J14:M14)) | X14: =IF(COUNTBLANK(N14:Q14)>0,"",SUM(N14:Q14)) | Y14: =IF(COUNTBLANK(R14:R14)>0,"",SUM(R14:R14)) | AB14: Hist: actual 法人税等; Fcst: Pretax × 24.2% (auto)
A15: Tax rate % | B15: =IF(B12=0,"",B14/B12*100) | C15: =IF(C12=0,"",C14/C12*100) | D15: =IF(D12=0,"",D14/D12*100) | E15: =IF(E12=0,"",E14/E12*100) | F15: =IF(F12=0,"",F14/F12*100) | G15: =IF(G12=0,"",G14/G12*100) | H15: =IF(H12=0,"",H14/H12*100) | I15: =IF(I12=0,"",I14/I12*100) | J15: =IF(J12=0,"",J14/J12*100) | K15: =FS!$B$85 | L15: =FS!$B$85 | M15: =FS!$B$85 | N15: =FS!$B$85 | O15: =FS!$B$85 | P15: =FS!$B$85 | Q15: =FS!$B$85 | R15: =FS!$B$85 | U15: =IF(OR(COUNTBLANK(B14:E14)>0,COUNTBLANK(B12:E12)>0),"",SUM(B14:E14)/SUM(B12:E12)*100) | V15: =IF(OR(COUNTBLANK(F14:I14)>0,COUNTBLANK(F12:I12)>0),"",SUM(F14:I14)/SUM(F12:I12)*100) | W15: =IF(OR(COUNTBLANK(J14:M14)>0,COUNTBLANK(J12:M12)>0),"",SUM(J14:M14)/SUM(J12:M12)*100) | X15: =IF(OR(COUNTBLANK(N14:Q14)>0,COUNTBLANK(N12:Q12)>0),"",SUM(N14:Q14)/SUM(N12:Q12)*100) | Y15: =IF(OR(COUNTBLANK(R14:R14)>0,COUNTBLANK(R12:R12)>0),"",SUM(R14:R14)/SUM(R12:R12)*100) | AB15: Hist: Income Tax ÷ Pretax (実効税率); Fcst: flat 24.2% assumption (Summary)
A16: − Minority Int. (NCI) | B16: =B12-B14-B18 | C16: =C12-C14-C18 | D16: =D12-D14-D18 | E16: =E12-E14-E18 | F16: =F12-F14-F18 | G16: =G12-G14-G18 | H16: =H12-H14-H18 | I16: =I12-I14-I18 | J16: =J12-J14-J18 | K16: =K12*FS!$B$101/100 | L16: =L12*FS!$B$101/100 | M16: =M12*FS!$B$101/100 | N16: =N12*FS!$B$101/100 | O16: =O12*FS!$B$101/100 | P16: =P12*FS!$B$101/100 | Q16: =Q12*FS!$B$101/100 | R16: =R12*FS!$B$101/100 | U16: =IF(COUNTBLANK(B16:E16)>0,"",SUM(B16:E16)) | V16: =IF(COUNTBLANK(F16:I16)>0,"",SUM(F16:I16)) | W16: =IF(COUNTBLANK(J16:M16)>0,"",SUM(J16:M16)) | X16: =IF(COUNTBLANK(N16:Q16)>0,"",SUM(N16:Q16)) | Y16: =IF(COUNTBLANK(R16:R16)>0,"",SUM(R16:R16)) | AB16: Hist: Pretax−Tax−NP; Fcst: Pretax × 1.2%
A18: Net Income | B18: 10.2 | C18: 10.8 | D18: 38.4 | E18: 125.6 | F18: 4.6 | G18: 15.6 | H18: 76.1 | I18: 139.9 | J18: 50.6 | K18: =K12-K14-K16 | L18: =L12-L14-L16 | M18: =M12-M14-M16 | N18: =N12-N14-N16 | O18: =O12-O14-O16 | P18: =P12-P14-P16 | Q18: =Q12-Q14-Q16 | R18: =R12-R14-R16 | U18: =IF(COUNTBLANK(B18:E18)>0,"",SUM(B18:E18)) | V18: =IF(COUNTBLANK(F18:I18)>0,"",SUM(F18:I18)) | W18: =IF(COUNTBLANK(J18:M18)>0,"",SUM(J18:M18)) | X18: =IF(COUNTBLANK(N18:Q18)>0,"",SUM(N18:Q18)) | Y18: =IF(COUNTBLANK(R18:R18)>0,"",SUM(R18:R18)) | AB18: Pretax − Tax − Minority (親会社株主帰属)
A19: NPM % | B19: =B18/B4*100 | C19: =C18/C4*100 | D19: =D18/D4*100 | E19: =E18/E4*100 | F19: =F18/F4*100 | G19: =G18/G4*100 | H19: =H18/H4*100 | I19: =I18/I4*100 | ... R19: =R18/R4*100 | U19: =IF(OR(COUNTBLANK(B18:E18)>0,COUNTBLANK(B4:E4)>0),"",SUM(B18:E18)/SUM(B4:E4)*100) | V19: =IF(OR(COUNTBLANK(F18:I18)>0,COUNTBLANK(F4:I4)>0),"",SUM(F18:I18)/SUM(F4:I4)*100) | W19: =IF(OR(COUNTBLANK(J18:M18)>0,COUNTBLANK(J4:M4)>0),"",SUM(J18:M18)/SUM(J4:M4)*100) | X19: =IF(OR(COUNTBLANK(N18:Q18)>0,COUNTBLANK(N4:Q4)>0),"",SUM(N18:Q18)/SUM(N4:Q4)*100) | Y19: =IF(OR(COUNTBLANK(R18:R18)>0,COUNTBLANK(R4:R4)>0),"",SUM(R18:R18)/SUM(R4:R4)*100) | AB19: NP ÷ Sales
A21: Diluted Shares (M) | B21: 45.4 | C21: 45.4 | D21: 45.4 | E21: 45.4 | F21: 45.4 | G21: 45.4 | H21: 45.4 | I21: 45.4 | J21: 45.4 | K21: =J21-FS!K76*100/FS!$B$99 | L21: =K21-FS!L76*100/FS!$B$99 | M21: =L21-FS!M76*100/FS!$B$99 | N21: =M21-FS!N76*100/FS!$B$99 | O21: =N21-FS!O76*100/FS!$B$99 | P21: =O21-FS!P76*100/FS!$B$99 | Q21: =P21-FS!Q76*100/FS!$B$99 | R21: =Q21-FS!R76*100/FS!$B$99 | U21: =IF(ISBLANK(E21),"",E21) | V21: =IF(ISBLANK(I21),"",I21) | W21: =IF(ISBLANK(M21),"",M21) | X21: =IF(ISBLANK(Q21),"",Q21) | Y21: =IF(ISBLANK(R21),"",R21) | AB21: Hist: per-Q AvgSh from fins_summary; Fcst: prior − Buyback×100÷AvgPx (B26)
A22: EPS (¥) | B22: =B18*100/B21 | C22: =C18*100/C21 | D22: =D18*100/D21 | E22: =E18*100/E21 | F22: =F18*100/F21 | G22: =G18*100/G21 | H22: =H18*100/H21 | I22: =I18*100/I21 | ... R22: =R18*100/R21 | U22: =IF(COUNTBLANK(B22:E22)>0,"",SUM(B22:E22)) | V22: =IF(COUNTBLANK(F22:I22)>0,"",SUM(F22:I22)) | W22: =IF(COUNTBLANK(J22:M22)>0,"",SUM(J22:M22)) | X22: =IF(COUNTBLANK(N22:Q22)>0,"",SUM(N22:Q22)) | Y22: =IF(COUNTBLANK(R22:R22)>0,"",SUM(R22:R22)) | AB22: NP × 100 ÷ Shares (oku → yen)
A23: DPS (¥) | B23: 0 | C23: 35 | D23: 0 | E23: 88 | F23: 0 | G23: 47 | H23: 0 | I23: 110 | J23: 0 | K23: 83 | L23: 0 | M23: =M22*FS!$B$88/100 | N23: =N22*FS!$B$88/100 | O23: =O22*FS!$B$88/100 | P23: =P22*FS!$B$88/100 | Q23: =Q22*FS!$B$88/100 | R23: =R22*FS!$B$88/100 | U23: =IF(COUNTBLANK(B23:E23)>0,"",SUM(B23:E23)) | V23: =IF(COUNTBLANK(F23:I23)>0,"",SUM(F23:I23)) | W23: =IF(COUNTBLANK(J23:M23)>0,"",SUM(J23:M23)) | X23: =IF(COUNTBLANK(N23:Q23)>0,"",SUM(N23:Q23)) | Y23: =IF(COUNTBLANK(R23:R23)>0,"",SUM(R23:R23)) | AB23: Disclosed DPS (実績/会社予想): interim@Q2, year-end@Q4; else EPS×payout
A24: Payout % | B24: =IF(B22=0,"",B23/B22*100) | C24: =IF(C22=0,"",C23/C22*100) | D24: =IF(D22=0,"",D23/D22*100) | E24: =IF(E22=0,"",E23/E22*100) | F24: =IF(F22=0,"",F23/F22*100) | G24: =IF(G22=0,"",G23/G22*100) | H24: =IF(H22=0,"",H23/H22*100) | I24: =IF(I22=0,"",I23/I22*100) | ... R24: =IF(R22=0,"",R23/R22*100) | U24: =IF(OR(COUNTBLANK(B23:E23)>0,COUNTBLANK(B22:E22)>0),"",SUM(B23:E23)/SUM(B22:E22)*100) | V24: =IF(OR(COUNTBLANK(F23:I23)>0,COUNTBLANK(F22:I22)>0),"",SUM(F23:I23)/SUM(F22:I22)*100) | W24: =IF(OR(COUNTBLANK(J23:M23)>0,COUNTBLANK(J22:M22)>0),"",SUM(J23:M23)/SUM(J22:M22)*100) | X24: =IF(OR(COUNTBLANK(N23:Q23)>0,COUNTBLANK(N22:Q22)>0),"",SUM(N23:Q23)/SUM(N22:Q22)*100) | Y24: =IF(OR(COUNTBLANK(R23:R23)>0,COUNTBLANK(R22:R22)>0),"",SUM(R23:R23)/SUM(R22:R22)*100) | AB24: DPS ÷ EPS
A27: Balance Sheet (億) — BLUE=actual/input, BLACK=formula, GREEN=cross-sheet, ORANGE=guide/end-of-FY
A29: Line Item | B29: FY24Q1 | C29: FY24Q2 | D29: FY24Q3 | E29: FY24Q4 | F29: FY25Q1 | G29: FY25Q2 | H29: FY25Q3 | I29: FY25Q4 | J29: FY26Q1 | K29: FY26Q2 | L29: FY26Q3 | M29: FY26Q4 | N29: FY27Q1 | O29: FY27Q2 | P29: FY27Q3 | Q29: FY27Q4 | R29: FY28Q1 | U29: FY24 | V29: FY25 | W29: FY26 | X29: FY27 | Y29: FY28 | Z29: FY26 EoFY | AB29: Forecast Formula (plain English)
A30: Cash & Equivalents | B30: 279.9 | C30: 230.1 | D30: 314 | E30: 306.8 | F30: 409 | G30: 292.3 | H30: 312.2 | I30: 318.3 | J30: 470.4 | K30: =J30+FS!K63+FS!K64+FS!K65 | L30: =K30+FS!L63+FS!L64+FS!L65 | M30: =L30+FS!M63+FS!M64+FS!M65 | N30: =M30+FS!N63+FS!N64+FS!N65 | O30: =N30+FS!O63+FS!O64+FS!O65 | P30: =O30+FS!P63+FS!P64+FS!P65 | Q30: =P30+FS!Q63+FS!Q64+FS!Q65 | R30: =Q30+FS!R63+FS!R64+FS!R65 | U30: =IF(ISBLANK(E30),"",E30) | V30: =IF(ISBLANK(I30),"",I30) | W30: =IF(ISBLANK(M30),"",M30) | X30: =IF(ISBLANK(Q30),"",Q30) | Y30: =IF(ISBLANK(R30),"",R30) | Z30: =R30 | AB30: Prior Cash + OCF + ICF + Financing CF (rolled from CF sheet; NOT Free CF — that is the separate OCF+ICF row)
A31: Trade Receivables | B31: 687.7 | C31: 745.4 | D31: 753 | E31: 1045.9 | F31: 657.6 | G31: 774 | H31: 858.1 | I31: 1217.3 | J31: 813.8 | K31: =K55*FS!K4/91 | L31: =L55*FS!L4/91 | M31: =M55*FS!M4/91 | N31: =N55*FS!N4/91 | O31: =O55*FS!O4/91 | P31: =P55*FS!P4/91 | Q31: =Q55*FS!Q4/91 | R31: =R55*FS!R4/91 | U31: =IF(ISBLANK(E31),"",E31) | V31: =IF(ISBLANK(I31),"",I31) | W31: =IF(ISBLANK(M31),"",M31) | X31: =IF(ISBLANK(Q31),"",Q31) | Y31: =IF(ISBLANK(R31),"",R31) | AB31: Sales × DSO / 91 (or actual when available)
A32: Inventory | B32: 783.2 | C32: 807.8 | D32: 898 | E32: 678.1 | F32: 748.3 | G32: 758.4 | H32: 873.7 | I32: 697 | J32: 769.5 | K32: =K56*FS!K5/91 | L32: =L56*FS!L5/91 | M32: =M56*FS!M5/91 | N32: =N56*FS!N5/91 | O32: =O56*FS!O5/91 | P32: =P56*FS!P5/91 | Q32: =Q56*FS!Q5/91 | R32: =R56*FS!R5/91 | U32: =IF(ISBLANK(E32),"",E32) | V32: =IF(ISBLANK(I32),"",I32) | W32: =IF(ISBLANK(M32),"",M32) | X32: =IF(ISBLANK(Q32),"",Q32) | Y32: =IF(ISBLANK(R32),"",R32) | AB32: COGS × DIO / 91
A33: Other CA | B33: 156.4 | C33: 135.2 | D33: 156.8 | E33: 140.4 | F33: 168.4 | G33: 165.3 | H33: 188.6 | I33: 170.1 | J33: 184.6 | K33: =J33 | L33: =K33 | M33: =L33 | N33: =M33 | O33: =N33 | P33: =O33 | Q33: =P33 | R33: =Q33 | U33: =IF(ISBLANK(E33),"",E33) | V33: =IF(ISBLANK(I33),"",I33) | W33: =IF(ISBLANK(M33),"",M33) | X33: =IF(ISBLANK(Q33),"",Q33) | Y33: =IF(ISBLANK(R33),"",R33) | AB33: Held constant from prior (roll-forward, NOT zeroed)
A34: Current Assets | B34: =B30+B31+B32+B33 | C34: =C30+C31+C32+C33 | D34: =D30+D31+D32+D33 | E34: =E30+E31+E32+E33 | F34: =F30+F31+F32+F33 | G34: =G30+G31+G32+G33 | H34: =H30+H31+H32+H33 | I34: =I30+I31+I32+I33 | ... R34: =R30+R31+R32+R33 | U34: =IF(ISBLANK(E34),"",E34) | V34: =IF(ISBLANK(I34),"",I34) | W34: =IF(ISBLANK(M34),"",M34) | X34: =IF(ISBLANK(Q34),"",Q34) | Y34: =IF(ISBLANK(R34),"",R34) | AB34: Cash + AR + Inv + OtherCA
A36: PPE (rolled) | B36: 754.9 | C36: 745.8 | D36: 753 | E36: 750.6 | F36: 753.4 | G36: 760 | H36: 779.1 | I36: 755.7 | J36: 793 | K36: =J36-FS!K64-J36*FS!$B$100 | L36: =K36-FS!L64-K36*FS!$B$100 | M36: =L36-FS!M64-L36*FS!$B$100 | N36: =M36-FS!N64-M36*FS!$B$100 | O36: =N36-FS!O64-N36*FS!$B$100 | P36: =O36-FS!P64-O36*FS!$B$100 | Q36: =P36-FS!Q64-P36*FS!$B$100 | R36: =Q36-FS!R64-Q36*FS!$B$100 | U36: =IF(ISBLANK(E36),"",E36) | V36: =IF(ISBLANK(I36),"",I36) | W36: =IF(ISBLANK(M36),"",M36) | X36: =IF(ISBLANK(Q36),"",Q36) | Y36: =IF(ISBLANK(R36),"",R36) | AB36: Prior PPE + Capex − D&A (Prior PPE × 3.94%/Q (calibrated to the disclosed guide 31億/Q at the latest PPE; rises with PPE thereafter))
A37: Other NCA | B37: =B38-B34-B36 | C37: =C38-C34-C36 | D37: =D38-D34-D36 | E37: =E38-E34-E36 | F37: =F38-F34-F36 | G37: =G38-G34-G36 | H37: =H38-H34-H36 | I37: =I38-I34-I36 | J37: =J38-J34-J36 | K37: =J37 | L37: =K37 | M37: =L37 | N37: =M37 | O37: =N37 | P37: =O37 | Q37: =P37 | R37: =Q37 | U37: =IF(ISBLANK(E37),"",E37) | V37: =IF(ISBLANK(I37),"",I37) | W37: =IF(ISBLANK(M37),"",M37) | X37: =IF(ISBLANK(Q37),"",Q37) | Y37: =IF(ISBLANK(R37),"",R37) | AB37: Held constant from prior
A38: TOTAL ASSETS | B38: 3157.7 | C38: 3141.6 | D38: 3349.5 | E38: 3413.5 | F38: 3245 | G38: 3289.9 | H38: 3567.2 | I38: 3736.7 | J38: 3610.7 | K38: =K34+K36+K37 | L38: =L34+L36+L37 | M38: =M34+M36+M37 | N38: =N34+N36+N37 | O38: =O34+O36+O37 | P38: =P34+P36+P37 | Q38: =Q34+Q36+Q37 | R38: =R34+R36+R37 | U38: =IF(ISBLANK(E38),"",E38) | V38: =IF(ISBLANK(I38),"",I38) | W38: =IF(ISBLANK(M38),"",M38) | X38: =IF(ISBLANK(Q38),"",Q38) | Y38: =IF(ISBLANK(R38),"",R38) | Z38: =R38 | AB38: CA + PPE + OtherNCA
A40: Trade Payables | B40: 302.9 | C40: 316.6 | D40: 318.2 | E40: 345 | F40: 274.1 | G40: 282.2 | H40: 300.1 | I40: 335.6 | J40: 279.8 | K40: =K57*FS!K5/91 | L40: =L57*FS!L5/91 | M40: =M57*FS!M5/91 | N40: =N57*FS!N5/91 | O40: =O57*FS!O5/91 | P40: =P57*FS!P5/91 | Q40: =Q57*FS!Q5/91 | R40: =R57*FS!R5/91 | U40: =IF(ISBLANK(E40),"",E40) | V40: =IF(ISBLANK(I40),"",I40) | W40: =IF(ISBLANK(M40),"",M40) | X40: =IF(ISBLANK(Q40),"",Q40) | Y40: =IF(ISBLANK(R40),"",R40) | AB40: COGS × DPO / 91 (or actual)
A41: Debt | B41: 429.7 | C41: 370.6 | D41: 368.2 | E41: 385.6 | F41: 389.1 | G41: 365.3 | H41: 377.7 | I41: 394 | J41: 388.7 | K41: =J41+FS!K77 | L41: =K41+FS!L77 | M41: =L41+FS!M77 | N41: =M41+FS!N77 | O41: =N41+FS!O77 | P41: =O41+FS!P77 | Q41: =P41+FS!Q77 | R41: =Q41+FS!R77 | U41: =IF(ISBLANK(E41),"",E41) | V41: =IF(ISBLANK(I41),"",I41) | W41: =IF(ISBLANK(M41),"",M41) | X41: =IF(ISBLANK(Q41),"",Q41) | Y41: =IF(ISBLANK(R41),"",R41) | AB41: Prior Debt + Net Debt Issuance (held flat unless a schedule is set)
A42: Other Liab | B42: =B43-B40-B41 | C42: =C43-C40-C41 | D42: =D43-D40-D41 | E42: =E43-E40-E41 | F42: =F43-F40-F41 | G42: =G43-G40-G41 | H42: =H43-H40-H41 | I42: =I43-I40-I41 | J42: =J43-J40-J41 | K42: =J42 | L42: =K42 | M42: =L42 | N42: =M42 | O42: =N42 | P42: =O42 | Q42: =P42 | R42: =Q42 | U42: =IF(ISBLANK(E42),"",E42) | V42: =IF(ISBLANK(I42),"",I42) | W42: =IF(ISBLANK(M42),"",M42) | X42: =IF(ISBLANK(Q42),"",Q42) | Y42: =IF(ISBLANK(R42),"",R42) | AB42: Held constant from prior (roll-forward)
A43: TOTAL LIAB | B43: 1866.3 | C43: 1877.8 | D43: 2033.2 | E43: 1991.3 | F43: 1841.3 | G43: 1830.1 | H43: 2000.2 | I43: 1951.4 | J43: 1801.5 | K43: =K40+K41+K42 | L43: =L40+L41+L42 | M43: =M40+M41+M42 | N43: =N40+N41+N42 | O43: =O40+O41+O42 | P43: =P40+P41+P42 | Q43: =Q40+Q41+Q42 | R43: =R40+R41+R42 | U43: =IF(ISBLANK(E43),"",E43) | V43: =IF(ISBLANK(I43),"",I43) | W43: =IF(ISBLANK(M43),"",M43) | X43: =IF(ISBLANK(Q43),"",Q43) | Y43: =IF(ISBLANK(R43),"",R43) | AB43: AP + Debt + OtherL (independent components)
A45: Shareholders Eq | B45: 1259.9 | C45: 1231.5 | D45: 1282.8 | E45: 1389.3 | F45: 1369.4 | G45: 1424.5 | H45: 1533.9 | I45: 1748.8 | J45: 1772.8 | K45: =J45+FS!K18-FS!K23*FS!K21/100-FS!K76 | L45: =K45+FS!L18-FS!L23*FS!L21/100-FS!L76 | M45: =L45+FS!M18-FS!M23*FS!M21/100-FS!M76 | N45: =M45+FS!N18-FS!N23*FS!N21/100-FS!N76 | O45: =N45+FS!O18-FS!O23*FS!O21/100-FS!O76 | P45: =O45+FS!P18-FS!P23*FS!P21/100-FS!P76 | Q45: =P45+FS!Q18-FS!Q23*FS!Q21/100-FS!Q76 | R45: =Q45+FS!R18-FS!R23*FS!R21/100-FS!R76 | U45: =IF(ISBLANK(E45),"",E45) | V45: =IF(ISBLANK(I45),"",I45) | W45: =IF(ISBLANK(M45),"",M45) | X45: =IF(ISBLANK(Q45),"",Q45) | Y45: =IF(ISBLANK(R45),"",R45) | Z45: =R45 | AB45: Prior Eq + NI − Dividends − Buyback
A46: Retained Earnings | B46: 773.9 | C46: 784.7 | D46: 807.2 | E46: 932.7 | F46: 897.5 | G46: 913.1 | H46: 967.9 | I46: 1107.7 | J46: 1108.4 | K46: =J46+FS!K18-FS!K75-FS!K76 | L46: =K46+FS!L18-FS!L75-FS!L76 | M46: =L46+FS!M18-FS!M75-FS!M76 | N46: =M46+FS!N18-FS!N75-FS!N76 | O46: =N46+FS!O18-FS!O75-FS!O76 | P46: =O46+FS!P18-FS!P75-FS!P76 | Q46: =P46+FS!Q18-FS!Q75-FS!Q76 | R46: =Q46+FS!R18-FS!R75-FS!R76 | U46: =IF(ISBLANK(E46),"",E46) | V46: =IF(ISBLANK(I46),"",I46) | W46: =IF(ISBLANK(M46),"",M46) | X46: =IF(ISBLANK(Q46),"",Q46) | Y46: =IF(ISBLANK(R46),"",R46) | AB46: Prior RE + NI − Dividends − Buyback
A47: Non-controlling | B47: 31.5 | C47: 32.3 | D47: 33.4 | E47: 32.8 | F47: 34.3 | G47: 35.3 | H47: 33.1 | I47: 36.5 | J47: 36.4 | K47: =J47 | L47: =K47 | M47: =L47 | N47: =M47 | O47: =N47 | P47: =O47 | Q47: =P47 | R47: =Q47 | U47: =IF(ISBLANK(E47),"",E47) | V47: =IF(ISBLANK(I47),"",I47) | W47: =IF(ISBLANK(M47),"",M47) | X47: =IF(ISBLANK(Q47),"",Q47) | Y47: =IF(ISBLANK(R47),"",R47) | AB47: Held constant from prior (roll-forward, NOT zeroed)
A48: TOTAL EQUITY | B48: =B45+B47 | C48: =C45+C47 | D48: =D45+D47 | E48: =E45+E47 | F48: =F45+F47 | G48: =G45+G47 | H48: =H45+H47 | I48: =I45+I47 | ... R48: =R45+R47 | U48: =IF(ISBLANK(E48),"",E48) | V48: =IF(ISBLANK(I48),"",I48) | W48: =IF(ISBLANK(M48),"",M48) | X48: =IF(ISBLANK(Q48),"",Q48) | Y48: =IF(ISBLANK(R48),"",R48) | AB48: Eq + NCI
A50: BS Check (TA-TL-TE) | B50: =B38-B43-B48 | C50: =C38-C43-C48 | D50: =D38-D43-D48 | E50: =E38-E43-E48 | F50: =F38-F43-F48 | G50: =G38-G43-G48 | H50: =H38-H43-H48 | I50: =I38-I43-I48 | ... R50: =R38-R43-R48 | AB50: TA − TL − TE (must = 0; non-zero ⇒ roll-forward inconsistency)
A53: WC Days (Historical = formula from BS÷PL; Forecast = key input)
B54: FY24Q1 | C54: FY24Q2 | D54: FY24Q3 | E54: FY24Q4 | F54: FY25Q1 | G54: FY25Q2 | H54: FY25Q3 | I54: FY25Q4 | J54: FY26Q1 | K54: FY26Q2 | L54: FY26Q3 | M54: FY26Q4 | N54: FY27Q1 | O54: FY27Q2 | P54: FY27Q3 | Q54: FY27Q4 | R54: FY28Q1 | U54: FY24 | V54: FY25 | W54: FY26 | X54: FY27 | Y54: FY28
A55: DSO (AR÷Sales×91) | B55: =FS!B31/FS!B4*91 | C55: =FS!C31/FS!C4*91 | D55: =FS!D31/FS!D4*91 | E55: =FS!E31/FS!E4*91 | F55: =FS!F31/FS!F4*91 | G55: =FS!G31/FS!G4*91 | H55: =FS!H31/FS!H4*91 | I55: =FS!I31/FS!I4*91 | J55: =FS!J31/FS!J4*91 | K55: 98 | L55: 107 | M55: 88 | N55: 112 | O55: 98 | P55: 107 | Q55: 88 | R55: 112 | U55: =IF(ISBLANK(E55),"",E55) | V55: =IF(ISBLANK(I55),"",I55) | W55: =IF(ISBLANK(M55),"",M55) | X55: =IF(ISBLANK(Q55),"",Q55) | Y55: =IF(ISBLANK(R55),"",R55) | AB55: Key user input (yellow); historical = AR ÷ Sales × 91
A56: DIO (Inv÷COGS×91) | B56: =FS!B32/FS!B5*91 | C56: =FS!C32/FS!C5*91 | D56: =FS!D32/FS!D5*91 | E56: =FS!E32/FS!E5*91 | F56: =FS!F32/FS!F5*91 | G56: =FS!G32/FS!G5*91 | H56: =FS!H32/FS!H5*91 | I56: =FS!I32/FS!I5*91 | J56: =FS!J32/FS!J5*91 | K56: 129 | L56: 153 | M56: 75 | N56: 145 | O56: 129 | P56: 153 | Q56: 75 | R56: 145 | U56: =IF(ISBLANK(E56),"",E56) | V56: =IF(ISBLANK(I56),"",I56) | W56: =IF(ISBLANK(M56),"",M56) | X56: =IF(ISBLANK(Q56),"",Q56) | Y56: =IF(ISBLANK(R56),"",R56) | AB56: Key user input (yellow); historical = Inv ÷ COGS × 91
A57: DPO (AP÷COGS×91) | B57: =FS!B40/FS!B5*91 | C57: =FS!C40/FS!C5*91 | D57: =FS!D40/FS!D5*91 | E57: =FS!E40/FS!E5*91 | F57: =FS!F40/FS!F5*91 | G57: =FS!G40/FS!G5*91 | H57: =FS!H40/FS!H5*91 | I57: =FS!I40/FS!I5*91 | J57: =FS!J40/FS!J5*91 | K57: 59 | L57: 63 | M57: 43 | N57: 66 | O57: 59 | P57: 63 | Q57: 43 | R57: 66 | U57: =IF(ISBLANK(E57),"",E57) | V57: =IF(ISBLANK(I57),"",I57) | W57: =IF(ISBLANK(M57),"",M57) | X57: =IF(ISBLANK(Q57),"",Q57) | Y57: =IF(ISBLANK(R57),"",R57) | AB57: Key user input (yellow); historical = AP ÷ COGS × 91
A60: Cash Flow (億) — JP cos report CF only at H1+FY. BLUE=actual, BLACK=formula, GREEN=cross-sheet, ORANGE=disclosed-FY.
A62: Line Item | B62: FY24Q1 | C62: FY24Q2 | D62: FY24Q3 | E62: FY24Q4 | F62: FY25Q1 | G62: FY25Q2 | H62: FY25Q3 | I62: FY25Q4 | J62: FY26Q1 | K62: FY26Q2 | L62: FY26Q3 | M62: FY26Q4 | N62: FY27Q1 | O62: FY27Q2 | P62: FY27Q3 | Q62: FY27Q4 | R62: FY28Q1 | U62: FY24 | V62: FY25 | W62: FY26 | X62: FY27 | Y62: FY28 | Z62: FY26 TOTAL | AB62: Forecast Formula (plain English)
A63: OCF (営業CF) | B63: 231.2 | C63: -26 | D63: 7.5 | E63: 141.9 | F63: 232.7 | G63: -47.6 | H63: -104.2 | I63: 94 | J63: 307 | K63: =K69+K70+K71 | L63: =L69+L70+L71 | M63: =M69+M70+M71 | N63: =N69+N70+N71 | O63: =O69+O70+O71 | P63: =P69+P70+P71 | Q63: =Q69+Q70+Q71 | R63: =R69+R70+R71 | U63: 354.5 | V63: 175 | W63: =IF(AND(ISBLANK(K63),ISBLANK(M63)),"",SUM(J63:M63)) | X63: =IF(AND(ISBLANK(O63),ISBLANK(Q63)),"",SUM(N63:Q63)) | Y63: =IF(COUNTBLANK(R63:R63)>0,"",SUM(R63:R63)) | Z63: =K63+L63+M63+N63+O63+P63+Q63+R63 | AB63: NI + D&A + ΔWC
A64: ICF (投資CF) | B64: -1.1 | C64: -26.7 | D64: -24 | E64: -38.8 | F64: -56.5 | G64: -29.8 | H64: -1 | I64: -84.1 | J64: -58.9 | K64: =-K73 | L64: =-L73 | M64: =-M73 | N64: =-N73 | O64: =-O73 | P64: =-P73 | Q64: =-Q73 | R64: =-R73 | U64: -90.7 | V64: -171.3 | W64: =IF(AND(ISBLANK(K64),ISBLANK(M64)),"",SUM(J64:M64)) | X64: =IF(AND(ISBLANK(O64),ISBLANK(Q64)),"",SUM(N64:Q64)) | Y64: =IF(COUNTBLANK(R64:R64)>0,"",SUM(R64:R64)) | Z64: =K64+L64+M64+N64+O64+P64+Q64+R64 | AB64: − Capex
A65: Financing CF (財務CF) | B65: -144 | C65: 4.9 | D65: 95.1 | E65: -101.4 | F65: -92.8 | G65: -32.2 | H65: 108 | I65: -60.8 | J65: -104.8 | K65: =-K75-K76+K77 | L65: =-L75-L76+L77 | M65: =-M75-M76+M77 | N65: =-N75-N76+N77 | O65: =-O75-O76+O77 | P65: =-P75-P76+P77 | Q65: =-Q75-Q76+Q77 | R65: =-R75-R76+R77 | U65: -145.4 | V65: -77.8 | W65: =IF(AND(ISBLANK(K65),ISBLANK(M65)),"",SUM(J65:M65)) | X65: =IF(AND(ISBLANK(O65),ISBLANK(Q65)),"",SUM(N65:Q65)) | Y65: =IF(COUNTBLANK(R65:R65)>0,"",SUM(R65:R65)) | Z65: =K65+L65+M65+N65+O65+P65+Q65+R65 | AB65: Financing CF (財務CF): − Dividends − Buyback + Net Debt Issuance
A66: Net Δcash | B66: =B63+B64+B65 | C66: =C63+C64+C65 | D66: =D63+D64+D65 | E66: =E63+E64+E65 | F66: =F63+F64+F65 | G66: =G63+G64+G65 | H66: =H63+H64+H65 | I66: =I63+I64+I65 | ... R66: =R63+R64+R65 | U66: =IF(AND(ISBLANK(C66),ISBLANK(E66)),"",SUM(B66:E66)) | V66: =IF(AND(ISBLANK(G66),ISBLANK(I66)),"",SUM(F66:I66)) | W66: =IF(AND(ISBLANK(K66),ISBLANK(M66)),"",SUM(J66:M66)) | X66: =IF(AND(ISBLANK(O66),ISBLANK(Q66)),"",SUM(N66:Q66)) | Y66: =IF(COUNTBLANK(R66:R66)>0,"",SUM(R66:R66)) | Z66: =K66+L66+M66+N66+O66+P66+Q66+R66 | AB66: OCF + ICF + Financing CF
A67: Free CF (OCF+ICF) | B67: =B63+B64 | C67: =C63+C64 | D67: =D63+D64 | E67: =E63+E64 | F67: =F63+F64 | G67: =G63+G64 | H67: =H63+H64 | I67: =I63+I64 | ... R67: =R63+R64 | U67: =U63+U64 | V67: =V63+V64 | W67: =W63+W64 | X67: =X63+X64 | Y67: =Y63+Y64 | Z67: =Z63+Z64 | AB67: Free CF = OCF + ICF (= 会社フリーCF)
A69: + NI | B69: =FS!B18 | C69: =FS!C18 | D69: =FS!D18 | E69: =FS!E18 | F69: =FS!F18 | G69: =FS!G18 | H69: =FS!H18 | I69: =FS!I18 | ... R69: =FS!R18 | U69: =IF(AND(ISBLANK(C69),ISBLANK(E69)),"",SUM(B69:E69)) | V69: =IF(AND(ISBLANK(G69),ISBLANK(I69)),"",SUM(F69:I69)) | W69: =IF(AND(ISBLANK(K69),ISBLANK(M69)),"",SUM(J69:M69)) | X69: =IF(AND(ISBLANK(O69),ISBLANK(Q69)),"",SUM(N69:Q69)) | Y69: =IF(COUNTBLANK(R69:R69)>0,"",SUM(R69:R69)) | AB69: from PL Net Income
A70: + D&A | B70: 25.3 | C70: 24.5 | D70: 27.1 | E70: 27.7 | F70: 25 | G70: 26.7 | H70: 29.4 | I70: 30.6 | J70: 26.9 | K70: =FS!J36*FS!$B$100 | L70: =FS!K36*FS!$B$100 | M70: =FS!L36*FS!$B$100 | N70: =FS!M36*FS!$B$100 | O70: =FS!N36*FS!$B$100 | P70: =FS!O36*FS!$B$100 | Q70: =FS!P36*FS!$B$100 | R70: =FS!Q36*FS!$B$100 | U70: =IF(AND(ISBLANK(C70),ISBLANK(E70)),"",SUM(B70:E70)) | V70: =IF(AND(ISBLANK(G70),ISBLANK(I70)),"",SUM(F70:I70)) | W70: =IF(AND(ISBLANK(K70),ISBLANK(M70)),"",SUM(J70:M70)) | X70: =IF(AND(ISBLANK(O70),ISBLANK(Q70)),"",SUM(N70:Q70)) | Y70: =IF(COUNTBLANK(R70:R70)>0,"",SUM(R70:R70)) | AB70: Prior PPE × 3.94%/Q (calibrated to the disclosed guide 31億/Q at the latest PPE; rises with PPE thereafter) (depreciation)
A71: + ΔWC | C71: =-(FS!C31-FS!B31)-(FS!C32-FS!B32)+(FS!C40-FS!B40) | D71: =-(FS!D31-FS!C31)-(FS!D32-FS!C32)+(FS!D40-FS!C40) | E71: =-(FS!E31-FS!D31)-(FS!E32-FS!D32)+(FS!E40-FS!D40) | F71: =-(FS!F31-FS!E31)-(FS!F32-FS!E32)+(FS!F40-FS!E40) | G71: =-(FS!G31-FS!F31)-(FS!G32-FS!F32)+(FS!G40-FS!F40) | H71: =-(FS!H31-FS!G31)-(FS!H32-FS!G32)+(FS!H40-FS!G40) | I71: =-(FS!I31-FS!H31)-(FS!I32-FS!H32)+(FS!I40-FS!H40) | J71: =-(FS!J31-FS!I31)-(FS!J32-FS!I32)+(FS!J40-FS!I40) | ... R71: =-(FS!R31-FS!Q31)-(FS!R32-FS!Q32)+(FS!R40-FS!Q40) | U71: =IF(AND(ISBLANK(C71),ISBLANK(E71)),"",SUM(B71:E71)) | V71: =IF(AND(ISBLANK(G71),ISBLANK(I71)),"",SUM(F71:I71)) | W71: =IF(AND(ISBLANK(K71),ISBLANK(M71)),"",SUM(J71:M71)) | X71: =IF(AND(ISBLANK(O71),ISBLANK(Q71)),"",SUM(N71:Q71)) | Y71: =IF(COUNTBLANK(R71:R71)>0,"",SUM(R71:R71)) | AB71: − ΔAR − ΔInv + ΔAP (working capital change)
A73: − Capex | K73: =$B$80 | L73: =$B$80 | M73: =$B$80 | N73: =$B$80 | O73: =$B$80 | P73: =$B$80 | Q73: =$B$80 | R73: =$B$80 | U73: =IF(AND(ISBLANK(C73),ISBLANK(E73)),"",SUM(B73:E73)) | V73: =IF(AND(ISBLANK(G73),ISBLANK(I73)),"",SUM(F73:I73)) | W73: =IF(AND(ISBLANK(K73),ISBLANK(M73)),"",SUM(J73:M73)) | X73: =IF(AND(ISBLANK(O73),ISBLANK(Q73)),"",SUM(N73:Q73)) | Y73: =IF(COUNTBLANK(R73:R73)>0,"",SUM(R73:R73)) | Z73: =K73+L73+M73+N73+O73+P73+Q73+R73 | AB73: Capex/Q assumption (80.0億, edit on Summary)
A75: − Dividends | B75: 20.3 | C75: 2.3 | D75: 15.4 | E75: 0.5 | F75: 36 | G75: 3.8 | H75: 19.4 | I75: 1.9 | J75: 45.5 | K75: =FS!K23*FS!K21/100 | L75: =FS!L23*FS!L21/100 | M75: =FS!M23*FS!M21/100 | N75: =FS!N23*FS!N21/100 | O75: =FS!O23*FS!O21/100 | P75: =FS!P23*FS!P21/100 | Q75: =FS!Q23*FS!Q21/100 | R75: =FS!R23*FS!R21/100 | U75: =IF(AND(ISBLANK(C75),ISBLANK(E75)),"",SUM(B75:E75)) | V75: =IF(AND(ISBLANK(G75),ISBLANK(I75)),"",SUM(F75:I75)) | W75: =IF(AND(ISBLANK(K75),ISBLANK(M75)),"",SUM(J75:M75)) | X75: =IF(AND(ISBLANK(O75),ISBLANK(Q75)),"",SUM(N75:Q75)) | Y75: =IF(COUNTBLANK(R75:R75)>0,"",SUM(R75:R75)) | Z75: =K75+L75+M75+N75+O75+P75+Q75+R75 | AB75: DPS × Shares (M) / 100
A76: − Buyback | K76: =$B$81 | L76: =$B$81 | M76: =$B$81 | N76: =$B$81 | O76: =$B$81 | P76: =$B$81 | Q76: =$B$81 | R76: =$B$81 | U76: =IF(AND(ISBLANK(C76),ISBLANK(E76)),"",SUM(B76:E76)) | V76: =IF(AND(ISBLANK(G76),ISBLANK(I76)),"",SUM(F76:I76)) | W76: =IF(AND(ISBLANK(K76),ISBLANK(M76)),"",SUM(J76:M76)) | X76: =IF(AND(ISBLANK(O76),ISBLANK(Q76)),"",SUM(N76:Q76)) | Y76: =IF(COUNTBLANK(R76:R76)>0,"",SUM(R76:R76)) | AB76: Buyback/Q assumption (edit on Summary; seeded from tdnet when announced)
A77: + Net Debt Iss | C77: =FS!C41-FS!B41 | D77: =FS!D41-FS!C41 | E77: =FS!E41-FS!D41 | F77: =FS!F41-FS!E41 | G77: =FS!G41-FS!F41 | H77: =FS!H41-FS!G41 | I77: =FS!I41-FS!H41 | J77: =FS!J41-FS!I41 | K77: 0 | L77: 0 | M77: 0 | N77: 0 | O77: 0 | P77: 0 | Q77: 0 | R77: 0 | U77: =IF(AND(ISBLANK(C77),ISBLANK(E77)),"",SUM(B77:E77)) | V77: =IF(AND(ISBLANK(G77),ISBLANK(I77)),"",SUM(F77:I77)) | W77: =IF(AND(ISBLANK(K77),ISBLANK(M77)),"",SUM(J77:M77)) | X77: =IF(AND(ISBLANK(O77),ISBLANK(Q77)),"",SUM(N77:Q77)) | Y77: =IF(COUNTBLANK(R77:R77)>0,"",SUM(R77:R77)) | AB77: Held = 0
A80: Capex per Q (億) [edit on Summary B22] | B80: =FS!$B$95
A81: Buyback per Q (億) [edit on Summary B23] | B81: =FS!$B$96
A84: Live Assumptions ─ edit cells in column B; only forward periods recompute
A85: Tax rate % | B85: 24.2 | C85: ΣTax/ΣPretax actual (ratio-of-sums), n=15
A86: NonOp/OP % | B86: -0.2 | C86: 5y ΣOdP/ΣOP−1 (ratio-of-sums), n=18
A87: SG&A/Sales % | B87: 20.35 | C87: yaml override (recent run-rate)
A88: Payout % | B88: 30 | C88: config: fixed policy
A89: Shares (M) | B89: 45.4 | C89: fins_summary ShOutFY(46M)-TrShFY(0M)
A90: PPE/TA ratio | B90: 0.24 | C90: 5y mean PPE/TA from fins_details, n=19
A91: RE/Eq ratio | B91: 0.611 | C91: 5y mean RE/Eq from fins_details, n=19
A92: DSO (days) | B92: 100 | C92: 5y mean AR÷Sales×91, n=19
A93: DIO (days) | B93: 152 | C93: 5y mean Inv÷COGSproxy×91, n=19
A94: DPO (days) | B94: 67 | C94: 5y mean AP÷COGSproxy×91, n=19
A95: Capex/Q (億) | B95: 80 | C95: yaml override (disclosed)
A96: Buyback/Q (億) | B96: 0 | C96: default (no announcement)
... A101: Minority/Pretax % | B101: 1.2 | C101: Σ(Pretax-Tax-NP)/ΣPretax, n=15

Sheet Valuation
A1: Meidensha Valuation — LEFT=DCF/PE/PB + verdict; RIGHT=5y multiples history
A2: BLUE=input, BLACK=formula, GREEN=cross-sheet
A3: Method 1: DCF (FCFF, equity-only) | F3: MULTIPLES HISTORY (5y, split-adjusted)
A4: FY+1 FCF (億, OCF+ICF) | B4: =IFERROR((FS!J63+FS!K63+FS!L63+FS!M63)+(FS!J64+FS!K64+FS!L64+FS!M64),"") | F4: Stat | G4: P/E | H4: P/B
A5: FCF growth Y2-Y5 % | B5: 5 | F5: Mean | G5: 14.1 | H5: 1.43
A6: Terminal growth % | B6: 2 | F6: Median | G6: 13.82 | H6: 1.26
A7: Rf % (10y JGB) | B7: 1.5 | F7: StdDev | G7: 2.23 | H7: 0.61
A8: ERP % (JP equity premium) | B8: 5 | F8: Mean +1SD | G8: 16.33 | H8: 2.04
A9: Beta (5y vs TOPIX) | B9: 1.36 | F9: Mean −1SD | G9: 11.87 | H9: 0.83
A10: WACC % = Rf + β × ERP | B10: =B7+B9*B8 | F10: CURRENT | G10: 16.94 | H10: 2.73
A11: Stub: days to FY end ÷ 365.25 | B11: =(DATE(YEAR(TODAY())+IF(MONTH(TODAY())>3,1,0),3+1,0)-TODAY())/365.25 | F11: Pct Rank % | G11: 90.71 | H11: 95.4
A12: Mid-year convention: Y1 discount=stub/2, Yn≥2 = stub + (n-1) - 0.5
A13: Y1 | B13: =B4 | C13: =1/(1+$B$10/100)^($B$11/2) | D13: =B13*C13 | F13: Current Price (¥) | G13: 10540
A14: Y2 | B14: =B13*(1+$B$5/100) | C14: =1/(1+$B$10/100)^($B$11+2-1-0.5) | D14: =B14*C14 | F14: Current TTM EPS (¥) | G14: 622.06
A15: Y3 | B15: =B14*(1+$B$5/100) | C15: =1/(1+$B$10/100)^($B$11+3-1-0.5) | D15: =B15*C15 | F15: Current BPS (¥) | G15: 3855.2
A16: Y4 | B16: =B15*(1+$B$5/100) | C16: =1/(1+$B$10/100)^($B$11+4-1-0.5) | D16: =B16*C16
A17: Y5 | B17: =B16*(1+$B$5/100) | C17: =1/(1+$B$10/100)^($B$11+5-1-0.5) | D17: =B17*C17 | F17: Recent 30 days
F18: Date | G18: Close | H18: TTM EPS | I18: BPS | J18: P/E | K18: P/B
A19: Terminal (discounted at end-of-Y5 = stub + 4.5) | B19: =B17*(1+$B$6/100)/(($B$10-$B$6)/100) | C19: =1/(1+$B$10/100)^($B$11+4.5) | D19: =B19*C19 | F19: 2026-08-05 | G19: 11250 | H19: 622.06 | I19: 3855.2 | J19: 18.09 | K19: 2.92
F20: 2026-08-06 | G20: 11140 | H20: 622.06 | I20: 3855.2 | J20: 17.91 | K20: 2.89
A21: Enterprise Value (億) | B21: =SUM(D13:D17)+D19 | F21: 2026-08-07 | G21: 10850 | H21: 622.06 | I21: 3855.2 | J21: 17.44 | K21: 2.81
A22: Net Cash = Cash − Debt (FY26Q1 actual) | B22: =FS!J30-FS!J41 | F22: 2026-08-10 | G22: 10790 | H22: 622.06 | I22: 3855.2 | J22: 17.35 | K22: 2.8
A23: Equity Value (億) | B23: =B21+B22 | F23: 2026-08-12 | G23: 11400 | H23: 622.06 | I23: 3855.2 | J23: 18.33 | K23: 2.96
A24: Shares (M) | B24: 45.364 | F24: 2026-08-13 | G24: 11880 | H24: 622.06 | I24: 3855.2 | J24: 19.1 | K24: 3.08
A25: DCF implied price (¥) | B25: =B23*100/B24 | F25: 2026-08-14 | G25: 12370 | H25: 622.06 | I25: 3855.2 | J25: 19.89 | K25: 3.21
A26: Net Cash floor (¥) | B26: =B22*100/B24 | F26: 2026-08-17 | G26: 12660 | H26: 622.06 | I26: 3855.2 | J26: 20.35 | K26: 3.28
F27: 2026-08-18 | G27: 12250 | H27: 622.06 | I27: 3855.2 | J27: 19.69 | K27: 3.18
A28: Method 2: P/E range (NTM blend) | F28: 2026-08-19 | G28: 11310 | H28: 622.06 | I28: 3855.2 | J28: 18.18 | K28: 2.93
A29: Blend weight on FY+1 (auto = days→FY end / 365) | B29: =MAX(0,MIN(1,1-(TODAY()-DATE(YEAR(TODAY())-IF(MONTH(TODAY())>3,0,1),3+1,0))/365.25)) | F29: 2026-08-20 | G29: 11230 | H29: 622.06 | I29: 3855.2 | J29: 18.05 | K29: 2.91
A30: FY+1 EPS forecast (¥, sum of 4Q) | B30: =FS!J22+FS!K22+FS!L22+FS!M22 | F30: 2026-08-21 | G30: 11480 | H30: 622.06 | I30: 3855.2 | J30: 18.45 | K30: 2.98
A31: FY+2 EPS forecast (¥, sum of 4Q) | B31: =FS!N22+FS!O22+FS!P22+FS!Q22 | F31: 2026-08-24 | G31: 11660 | H31: 622.06 | I31: 3855.2 | J31: 18.74 | K31: 3.02
A32: NTM EPS = w·FY+1 + (1−w)·FY+2 | B32: =B29*B30+(1-B29)*B31 | F32: 2026-08-25 | G32: 11580 | H32: 622.06 | I32: 3855.2 | J32: 18.62 | K32: 3
A33: 5y mean P/E | B33: =Valuation!G5 | F33: 2026-08-26 | G33: 11750 | H33: 622.06 | I33: 3855.2 | J33: 18.89 | K33: 3.05
A34: 5y +1SD P/E | B34: =Valuation!G8 | F34: 2026-08-27 | G34: 11960 | H34: 622.06 | I34: 3855.2 | J34: 19.23 | K34: 3.1
A35: 5y −1SD P/E | B35: =Valuation!G9 | F35: 2026-08-28 | G35: 11720 | H35: 622.06 | I35: 3855.2 | J35: 18.84 | K35: 3.04
A36: Implied @mean (NTM) | B36: =B32*B33 | F36: 2026-08-31 | G36: 11870 | H36: 622.06 | I36: 3855.2 | J36: 19.08 | K36: 3.08
A37: Implied @+1SD | B37: =B32*B34 | F37: 2026-09-01 | G37: 11260 | H37: 622.06 | I37: 3855.2 | J37: 18.1 | K37: 2.92
A38: Implied @−1SD | B38: =B32*B35 | F38: 2026-09-02 | G38: 10680 | H38: 622.06 | I38: 3855.2 | J38: 17.17 | K38: 2.77
F39: 2026-09-03 | G39: 10530 | H39: 622.06 | I39: 3855.2 | J39: 16.93 | K39: 2.73
F40: 2026-09-04 | G40: 10800 | H40: 622.06 | I40: 3855.2 | J40: 17.36 | K40: 2.8
A41: Method 3: P/B range (NTM blend) | F41: 2026-09-07 | G41: 11200 | H41: 622.06 | I41: 3855.2 | J41: 18 | K41: 2.91
A42: Current BPS (latest, ¥/share) | B42: =Valuation!G15 | F42: 2026-09-08 | G42: 10410 | H42: 622.06 | I42: 3855.2 | J42: 16.73 | K42: 2.7
A43: + FY+1 ΔBPS (4Q NI × retention / shares) | B43: =(FS!K18+FS!L18+FS!M18)*(1-FS!B88/100)*100/FS!B89 | F43: 2026-09-09 | G43: 10810 | H43: 622.06 | I43: 3855.2 | J43: 17.38 | K43: 2.8
A44: + FY+2 ΔBPS (only when blend leans to FY+2) | B44: =(FS!N18+FS!O18+FS!P18+FS!Q18)*(1-FS!B88/100)*100/FS!B89 | F44: 2026-09-10 | G44: 10670 | H44: 622.06 | I44: 3855.2 | J44: 17.15 | K44: 2.77
A45: NTM BPS = (current + ΔFY1 + (1−w)·ΔFY2) | B45: =B42+B43+(1-B29)*B44 | F45: 2026-09-11 | G45: 10320 | H45: 622.06 | I45: 3855.2 | J45: 16.59 | K45: 2.68
A46: 5y mean P/B | B46: =Valuation!H5 | F46: 2026-09-14 | G46: 10430 | H46: 622.06 | I46: 3855.2 | J46: 16.77 | K46: 2.71
A47: 5y +1SD P/B | B47: =Valuation!H8 | F47: 2026-09-15 | G47: 10400 | H47: 622.06 | I47: 3855.2 | J47: 16.72 | K47: 2.7
A48: 5y −1SD P/B | B48: =Valuation!H9 | F48: 2026-09-16 | G48: 10540 | H48: 622.06 | I48: 3855.2 | J48: 16.94 | K48: 2.73
A49: Implied @mean (NTM) | B49: =B45*B46
A50: Implied @+1SD | B50: =B45*B47
A51: Implied @−1SD | B51: =B45*B48
A54: VERDICT (NTM target)
A55: Current Price (¥) | B55: =Valuation!G13
A56: DCF target | B56: =B25 | C56: =IF(B55<B56*0.9,"Cheap",IF(B55>B56*1.1,"Rich","Fair"))
A57: P/E target (NTM) | B57: =B36 | C57: =IF(B55<B38,"Cheap",IF(B55>B37,"Rich","Fair"))
A58: P/B target (NTM) | B58: =B49 | C58: =IF(B55<B51,"Cheap",IF(B55>B50,"Rich","Fair"))
A59: Composite | B59: =IF(AND(C56="Cheap",C57="Cheap",C58="Cheap"),"CHEAP — buy",IF(AND(C56="Rich",C57="Rich",C58="Rich"),"RICH — sell",IF(OR(C56="Rich",C57="Rich",C58="Rich"),"Mixed-rich","Fair / Mixed-cheap")))

Sheet Industry
A1: Industry / Macro Indicators — context for Meidensha (¥億, monthly)
A2: Rows = indicators; Cols = months (latest right). Easy to plot. Sources: JMTBA + MOF 貿易統計
A4: Indicator | B4: 202408 | C4: 202409 | D4: 202410 | E4: 202411 | F4: 202412 | G4: 202501 | H4: 202502 | I4: 202503 | J4: 202504 | K4: 202505 | L4: 202506 | M4: 202507 | N4: 202508 | O4: 202509 | P4: 202510 | Q4: 202511 | R4: 202512 | S4: 202601 | T4: 202602 | U4: 202603 | V4: 202604 | W4: 202605 | X4: 202606 | Y4: 202607 | Z4: 202608
A5: JMTBA total (億) | B5: 1107.7 | C5: 1253.6 | D5: 1225.5 | E5: 1193.3 | F5: 1430.9 | G5: 1161.5 | H5: 1182 | I5: 1511 | J5: 1302.1 | K5: 1287.2 | L5: 1331.6 | M5: 1283.6 | N5: 1201.7 | O5: 1391.5 | P5: 1434.6 | Q5: 1370 | R5: 1586.4 | S5: 1455.8 | T5: 1467.4 | U5: 1934.7 | V5: 1889.7 | W5: 1770.1 | X5: 2033.8 | Y5: 1930.9
A6: total YoY % | N6: =IFERROR(N5/B5-1,"") | O6: =IFERROR(O5/C5-1,"") | P6: =IFERROR(P5/D5-1,"") | Q6: =IFERROR(Q5/E5-1,"") | R6: =IFERROR(R5/F5-1,"") | S6: =IFERROR(S5/G5-1,"") | T6: =IFERROR(T5/H5-1,"") | U6: =IFERROR(U5/I5-1,"") | ... Z6: =IFERROR(Z5/N5-1,"")
A7: JMTBA domestic (億) | B7: 321.9 | C7: 415.3 | D7: 334.4 | E7: 343.3 | F7: 399.2 | G7: 320 | H7: 337.7 | I7: 492.6 | J7: 343.8 | K7: 330.2 | L7: 398.7 | M7: 354.5 | N7: 318.9 | O7: 436.4 | P7: 356.9 | Q7: 319.9 | R7: 399.1 | S7: 326.2 | T7: 371.6 | U7: 504.7 | V7: 492.9 | W7: 453.3 | X7: 580.2 | Y7: 532.4
A8: domestic YoY % | N8: =IFERROR(N7/B7-1,"") | O8: =IFERROR(O7/C7-1,"") | P8: =IFERROR(P7/D7-1,"") | Q8: =IFERROR(Q7/E7-1,"") | R8: =IFERROR(R7/F7-1,"") | S8: =IFERROR(S7/G7-1,"") | T8: =IFERROR(T7/H7-1,"") | U8: =IFERROR(U7/I7-1,"") | ... Z8: =IFERROR(Z7/N7-1,"")
A9: JMTBA foreign (億) | B9: 785.8 | C9: 838.3 | D9: 891.1 | E9: 850 | F9: 1031.7 | G9: 841.5 | H9: 844.3 | I9: 1018.4 | J9: 958.4 | K9: 957 | L9: 932.9 | M9: 929.1 | N9: 882.8 | O9: 955 | P9: 1077.6 | Q9: 1050.2 | R9: 1187.4 | S9: 1129.5 | T9: 1095.8 | U9: 1430 | V9: 1396.8 | W9: 1316.8 | X9: 1453.5 | Y9: 1398.5
A10: foreign YoY % | N10: =IFERROR(N9/B9-1,"") | O10: =IFERROR(O9/C9-1,"") | P10: =IFERROR(P9/D9-1,"") | Q10: =IFERROR(Q9/E9-1,"") | R10: =IFERROR(R9/F9-1,"") | S10: =IFERROR(S9/G9-1,"") | T10: =IFERROR(T9/H9-1,"") | U10: =IFERROR(U9/I9-1,"") | ... Z10: =IFERROR(Z9/N9-1,"")
A11: JMTBA backlog (億) | B11: 8005.3 | C11: 7677.2 | D11: 7751.9 | E11: 7700 | F11: 7678.2 | G11: 7726.6 | H11: 7599.4 | I11: 6924 | J11: 6957.6 | K11: 7131.3 | L11: 7175.2 | M11: 7251 | N11: 7292 | O11: 7329.6 | P11: 7564.8 | Q11: 7594.8 | R11: 7574.3 | S11: 7750.9 | T11: 8026.2 | U11: 8116.1 | V11: 8782.5 | W11: 9282.2 | X11: 9665 | Y11: 10091.4
A12: backlog YoY % | N12: =IFERROR(N11/B11-1,"") | O12: =IFERROR(O11/C11-1,"") | P12: =IFERROR(P11/D11-1,"") | Q12: =IFERROR(Q11/E11-1,"") | R12: =IFERROR(R11/F11-1,"") | S12: =IFERROR(S11/G11-1,"") | T12: =IFERROR(T11/H11-1,"") | U12: =IFERROR(U11/I11-1,"") | ... Z12: =IFERROR(Z11/N11-1,"")
A14: JMTBA total 速報 (億) | U14: 1935.1 | V14: 1889.7 | W14: 1768.3 | X14: 2035.2 | Y14: 1931 | Z14: 1978.8
A15: total 速報 YoY % | N15: =IFERROR(N14/B14-1,"") | O15: =IFERROR(O14/C14-1,"") | P15: =IFERROR(P14/D14-1,"") | Q15: =IFERROR(Q14/E14-1,"") | R15: =IFERROR(R14/F14-1,"") | S15: =IFERROR(S14/G14-1,"") | T15: =IFERROR(T14/H14-1,"") | U15: =IFERROR(U14/I14-1,"") | ... Z15: =IFERROR(Z14/N14-1,"")
A16: JMTBA domestic 速報 (億) | U16: 505.1 | V16: 492.9 | W16: 450.4 | X16: 580.2 | Y16: 532.4 | Z16: 515.3
A17: domestic 速報 YoY % | N17: =IFERROR(N16/B16-1,"") | O17: =IFERROR(O16/C16-1,"") | P17: =IFERROR(P16/D16-1,"") | Q17: =IFERROR(Q16/E16-1,"") | R17: =IFERROR(R16/F16-1,"") | S17: =IFERROR(S16/G16-1,"") | T17: =IFERROR(T16/H16-1,"") | U17: =IFERROR(U16/I16-1,"") | ... Z17: =IFERROR(Z16/N16-1,"")
A18: JMTBA foreign 速報 (億) | U18: 1430 | V18: 1396.8 | W18: 1318 | X18: 1455 | Y18: 1398.6 | Z18: 1463.5
A19: foreign 速報 YoY % | N19: =IFERROR(N18/B18-1,"") | O19: =IFERROR(O18/C18-1,"") | P19: =IFERROR(P18/D18-1,"") | Q19: =IFERROR(Q18/E18-1,"") | R19: =IFERROR(R18/F18-1,"") | S19: =IFERROR(S18/G18-1,"") | T19: =IFERROR(T18/H18-1,"") | U19: =IFERROR(U18/I18-1,"") | ... Z19: =IFERROR(Z18/N18-1,"")
A21: JMTBA 中国 (億) | B21: 285.3 | C21: 274.2 | D21: 290 | E21: 293.2 | F21: 362.5 | G21: 276 | H21: 266.8 | I21: 360.9 | J21: 339.8 | K21: 309.5 | L21: 321.8 | M21: 319.5 | N21: 293.2 | O21: 342.8 | P21: 317.9 | Q21: 381.3 | R21: 371.2 | S21: 433 | T21: 374.6 | U21: 513.5 | V21: 533.3 | W21: 512.5 | X21: 564.9 | Y21: 486.3
A22: 中国 YoY % | N22: =IFERROR(N21/B21-1,"") | O22: =IFERROR(O21/C21-1,"") | P22: =IFERROR(P21/D21-1,"") | Q22: =IFERROR(Q21/E21-1,"") | R22: =IFERROR(R21/F21-1,"") | S22: =IFERROR(S21/G21-1,"") | T22: =IFERROR(T21/H21-1,"") | U22: =IFERROR(U21/I21-1,"") | ... Z22: =IFERROR(Z21/N21-1,"")
A23: JMTBA アメリカ (億) | B23: 205.1 | C23: 221.6 | D23: 174.2 | E23: 235.8 | F23: 289.4 | G23: 207.7 | H23: 230.3 | I23: 247 | J23: 272.3 | K23: 289.9 | L23: 249.3 | M23: 237.9 | N23: 240.8 | O23: 259 | P23: 282.9 | Q23: 263.9 | R23: 345.8 | S23: 310.9 | T23: 312.1 | U23: 392.6 | V23: 358.1 | W23: 303.5 | X23: 360 | Y23: 371.1
A24: アメリカ YoY % | N24: =IFERROR(N23/B23-1,"") | O24: =IFERROR(O23/C23-1,"") | P24: =IFERROR(P23/D23-1,"") | Q24: =IFERROR(Q23/E23-1,"") | R24: =IFERROR(R23/F23-1,"") | S24: =IFERROR(S23/G23-1,"") | T24: =IFERROR(T23/H23-1,"") | U24: =IFERROR(U23/I23-1,"") | ... Z24: =IFERROR(Z23/N23-1,"")
A25: JMTBA インド (億) | B25: 52.7 | C25: 55.3 | D25: 97.1 | E25: 55.6 | F25: 50.6 | G25: 83.9 | H25: 53.9 | I25: 98.2 | J25: 47.4 | K25: 45.3 | L25: 51.4 | M25: 61.1 | N25: 49.8 | O25: 53.2 | P25: 49 | Q25: 59 | R25: 63.9 | S25: 58.4 | T25: 78.8 | U25: 116.6 | V25: 76.6 | W25: 57.7 | X25: 91.6 | Y25: 72.8
A26: インド YoY % | N26: =IFERROR(N25/B25-1,"") | O26: =IFERROR(O25/C25-1,"") | P26: =IFERROR(P25/D25-1,"") | Q26: =IFERROR(Q25/E25-1,"") | R26: =IFERROR(R25/F25-1,"") | S26: =IFERROR(S25/G25-1,"") | T26: =IFERROR(T25/H25-1,"") | U26: =IFERROR(U25/I25-1,"") | ... Z26: =IFERROR(Z25/N25-1,"")
A27: JMTBA 台湾 (億) | B27: 11.3 | C27: 23.2 | D27: 16.8 | E27: 10.3 | F27: 16.4 | G27: 12.8 | H27: 16.8 | I27: 21.8 | J27: 18.2 | K27: 16.2 | L27: 12.7 | M27: 15.5 | N27: 11.2 | O27: 14.9 | P27: 21.4 | Q27: 18.1 | R27: 13.3 | S27: 33.6 | T27: 19 | U27: 22 | V27: 33.8 | W27: 49.4 | X27: 35.8 | Y27: 40.5
A28: 台湾 YoY % | N28: =IFERROR(N27/B27-1,"") | O28: =IFERROR(O27/C27-1,"") | P28: =IFERROR(P27/D27-1,"") | Q28: =IFERROR(Q27/E27-1,"") | R28: =IFERROR(R27/F27-1,"") | S28: =IFERROR(S27/G27-1,"") | T28: =IFERROR(T27/H27-1,"") | U28: =IFERROR(U27/I27-1,"") | ... Z28: =IFERROR(Z27/N27-1,"")
A29: JMTBA 韓国 (億) | B29: 38.3 | C29: 20.4 | D29: 28.4 | E29: 15.1 | F29: 24 | G29: 26.3 | H29: 30.4 | I29: 25.9 | J29: 32.4 | K29: 24 | L29: 19.4 | M29: 18.4 | N29: 20.9 | O29: 25.3 | P29: 43.1 | Q29: 28.4 | R29: 19.2 | S29: 28.4 | T29: 30 | U29: 26.6 | V29: 37.5 | W29: 19.8 | X29: 33.5 | Y29: 50
A30: 韓国 YoY % | N30: =IFERROR(N29/B29-1,"") | O30: =IFERROR(O29/C29-1,"") | P30: =IFERROR(P29/D29-1,"") | Q30: =IFERROR(Q29/E29-1,"") | R30: =IFERROR(R29/F29-1,"") | S30: =IFERROR(S29/G29-1,"") | T30: =IFERROR(T29/H29-1,"") | U30: =IFERROR(U29/I29-1,"") | ... Z30: =IFERROR(Z29/N29-1,"")
A31: JMTBA ドイツ (億) | B31: 25.3 | C31: 35.8 | D31: 26.1 | E31: 27.8 | F31: 29.1 | G31: 30.4 | H31: 37.9 | I31: 34.8 | J31: 33.8 | K31: 36.3 | L31: 35.5 | M31: 34.4 | N31: 27.2 | O31: 36 | P31: 43 | Q31: 41.6 | R31: 42.8 | S31: 38.1 | T31: 39.5 | U31: 42.9 | V31: 44.7 | W31: 32.2 | X31: 32.6 | Y31: 46.8
A32: ドイツ YoY % | N32: =IFERROR(N31/B31-1,"") | O32: =IFERROR(O31/C31-1,"") | P32: =IFERROR(P31/D31-1,"") | Q32: =IFERROR(Q31/E31-1,"") | R32: =IFERROR(R31/F31-1,"") | S32: =IFERROR(S31/G31-1,"") | T32: =IFERROR(T31/H31-1,"") | U32: =IFERROR(U31/I31-1,"") | ... Z32: =IFERROR(Z31/N31-1,"")
A33: JMTBA うち自動車部品 (億) | B33: 50.9 | C33: 54.1 | D33: 44.9 | E33: 35.1 | F33: 52.6 | G33: 36.8 | H33: 53.6 | I33: 71.6 | J33: 32.6 | K33: 34.4 | L33: 43 | M33: 55.2 | N33: 45.6 | O33: 50.8 | P33: 43.4 | Q33: 42.5 | R33: 59.3 | S33: 40.4 | T33: 59.4 | U33: 61.8 | V33: 76.9 | W33: 55.9 | X33: 85.9 | Y33: 72.3
A34: うち自動車部品 YoY % | N34: =IFERROR(N33/B33-1,"") | O34: =IFERROR(O33/C33-1,"") | P34: =IFERROR(P33/D33-1,"") | Q34: =IFERROR(Q33/E33-1,"") | R34: =IFERROR(R33/F33-1,"") | S34: =IFERROR(S33/G33-1,"") | T34: =IFERROR(T33/H33-1,"") | U34: =IFERROR(U33/I33-1,"") | ... Z34: =IFERROR(Z33/N33-1,"")
A35: JMTBA 電気・精密 計 (億) | B35: 26.1 | C35: 59.6 | D35: 42 | E35: 40.6 | F35: 48.5 | G35: 43.3 | H35: 32.4 | I35: 53.4 | J35: 48.3 | K35: 48.2 | L35: 58.6 | M35: 40.3 | N35: 33.3 | O35: 53.7 | P35: 39.6 | Q35: 34.9 | R35: 39.2 | S35: 52.2 | T35: 57.7 | U35: 73.8 | V35: 78 | W35: 51.3 | X35: 97.3 | Y35: 82.2
A36: 電気・精密 計 YoY % | N36: =IFERROR(N35/B35-1,"") | O36: =IFERROR(O35/C35-1,"") | P36: =IFERROR(P35/D35-1,"") | Q36: =IFERROR(Q35/E35-1,"") | R36: =IFERROR(R35/F35-1,"") | S36: =IFERROR(S35/G35-1,"") | T36: =IFERROR(T35/H35-1,"") | U36: =IFERROR(U35/I35-1,"") | ... Z36: =IFERROR(Z35/N35-1,"")
A38: MOF Robot Exp HS 8479 (億) | B38: 819.7 | C38: 831.6 | D38: 852.8 | E38: 781.9 | F38: 988.7 | G38: 666.6 | H38: 877 | I38: 969.1 | J38: 824.4 | K38: 874.8 | L38: 893.6 | M38: 975.8 | N38: 803.5 | O38: 843.7 | P38: 959.1 | Q38: 898.4 | R38: 1061.1 | S38: 849.7 | T38: 849.4 | U38: 1089.9 | V38: 1055.3 | W38: 983.6 | X38: 1015.5 | Y38: 1160.1
A39: MOF Robot Exp HS 8479 YoY % | N39: =IFERROR(N38/B38-1,"") | O39: =IFERROR(O38/C38-1,"") | P39: =IFERROR(P38/D38-1,"") | Q39: =IFERROR(Q38/E38-1,"") | R39: =IFERROR(R38/F38-1,"") | S39: =IFERROR(S38/G38-1,"") | T39: =IFERROR(T38/H38-1,"") | U39: =IFERROR(U38/I38-1,"") | ... Z39: =IFERROR(Z38/N38-1,"")
A40: MOF Semi-Eq Exp HS 8486 (億) | B40: 3429.3 | C40: 3970.3 | D40: 4076 | E40: 3743.4 | F40: 4502.6 | G40: 2879 | H40: 3962.5 | I40: 4984.1 | J40: 3735.3 | K40: 3319.8 | L40: 3877.8 | M40: 3509.4 | N40: 3494.9 | O40: 3844 | P40: 3635.4 | Q40: 3792.2 | R40: 4436.8 | S40: 3156.7 | T40: 3290.9 | U40: 5259 | V40: 3932.1 | W40: 3654.5 | X40: 4601.4 | Y40: 4939.5
A41: MOF Semi-Eq Exp HS 8486 YoY % | N41: =IFERROR(N40/B40-1,"") | O41: =IFERROR(O40/C40-1,"") | P41: =IFERROR(P40/D40-1,"") | Q41: =IFERROR(Q40/E40-1,"") | R41: =IFERROR(R40/F40-1,"") | S41: =IFERROR(S40/G40-1,"") | T41: =IFERROR(T40/H40-1,"") | U41: =IFERROR(U40/I40-1,"") | ... Z41: =IFERROR(Z40/N40-1,"")
A42: MOF CNC Tool Exp HS 8459 (億) | B42: 12.3 | C42: 13.4 | D42: 7.1 | E42: 15.9 | F42: 15.3 | G42: 8.8 | H42: 18.3 | I42: 13.6 | J42: 9.9 | K42: 5.1 | L42: 11.3 | M42: 20.8 | N42: 10.4 | O42: 11.6 | P42: 7.2 | Q42: 4.6 | R42: 14.1 | S42: 5.5 | T42: 8.9 | U42: 11.4 | V42: 13.3 | W42: 9.7 | X42: 9.5 | Y42: 7.2
A43: MOF CNC Tool Exp HS 8459 YoY % | N43: =IFERROR(N42/B42-1,"") | O43: =IFERROR(O42/C42-1,"") | P43: =IFERROR(P42/D42-1,"") | Q43: =IFERROR(Q42/E42-1,"") | R43: =IFERROR(R42/F42-1,"") | S43: =IFERROR(S42/G42-1,"") | T43: =IFERROR(T42/H42-1,"") | U43: =IFERROR(U42/I42-1,"") | ... Z43: =IFERROR(Z42/N42-1,"")

Sheet Comp
A1: Peer Comparables for Meidensha (65080) — common multiples
A2: Source: J-Quants daily_bars × fins_summary FY (split-adjusted BPS). P/E(fwd) = Nikkei QUICK consensus for the CURRENT FY — near a company's FY-end that is nearly trailing.
A4: Code | B4: Name | C4: Period | D4: Price | E4: MCap (億) | F4: Sales | G4: OP | H4: NP | I4: EPS | J4: BPS | K4: P/E (fwd) | L4: P/B | M4: OPM % | N4: ROE % | O4: Sales YoY %
A5: 65080 | B5: 明電舎 | C5: Consensus 2027/3連予 (n=5) | D5: 10540 | E5: 4781 | F5: 3661 | G5: 360 | H5: 274 | I5: 604.55 | J5: 3855.2 | K5: 17.4 | L5: 2.73 | M5: 9.8 | N5: 15.4 | O5: 12.2
A6: 65010 | B6: 日立製作所 | C6: Consensus 2027/3連I予 (n=15) | D6: 5372 | E6: 243852 | F6: 118106 | G6: 14695 | H6: 9472 | I6: 212.81 | J6: 1459.7 | K6: 25.2 | L6: 3.68 | M6: 12.4 | N6: 14 | O6: 11.6
A7: 65030 | B7: 三菱電機 | C7: Consensus 2027/3連I予 (n=16) | D7: 5160 | E7: 106098 | F7: 63896 | G7: 6732 | H7: 5354 | I7: 261.55 | J7: 2191.3 | K7: 19.7 | L7: 2.35 | M7: 10.5 | N7: 11.6 | O7: 8.4
A8: 65040 | B8: 富士電機 | C8: Consensus 2027/3連予 (n=9) | D8: 12815 | E8: 18886 | F8: 13173 | G8: 1592 | H8: 1159 | I8: 793.84 | J8: 5428.6 | K8: 16.1 | L8: 2.36 | M8: 12.1 | N8: 13.7 | O8: 7.3
A9: 66220 | B9: ダイヘン | C9: Consensus 2027/3連予 (n=6) | D9: 12350 | E9: 2947 | F9: 2848 | G9: 269 | H9: 185 | I9: 783.86 | J9: 6524.8 | K9: 15.8 | L9: 1.89 | M9: 9.4 | N9: 10.8 | O9: 19.8
A10: 58050 | B10: ＳＷＣＣ | C10: Consensus 2027/3連予 (n=6) | D10: 13010 | E10: 3851 | F10: 3350 | G10: 351 | H10: 234 | I10: 789.98 | J10: 3322.3 | K10: 16.5 | L10: 3.92 | M10: 10.5 | N10: 22.1 | O10: 20.6
A12: MEDIAN (peers) | K12: 16.5 | L12: 2.36 | M12: 10.5 | N12: 13.7 | O12: 11.6

Sheet Summary
A1: Meidensha (65080) — Model Summary [BLUE=input, BLACK=formula, GREEN=cross-sheet, YELLOW=key tunable]
A3: Metric | B3: Hist FY25 | C3: Model FY26E | D3: Model FY27E | E3: Company Guide | F3: vs Guide %
A4: Sales (億) | B4: =FS!F4+FS!G4+FS!H4+FS!I4 | C4: =FS!J4+FS!K4+FS!L4+FS!M4 | D4: =FS!N4+FS!O4+FS!P4+FS!Q4
A5: OP (億) | B5: =FS!F9+FS!G9+FS!H9+FS!I9 | C5: =FS!J9+FS!K9+FS!L9+FS!M9 | D5: =FS!N9+FS!O9+FS!P9+FS!Q9
A6: OPM % | B6: =B5/B4*100 | C6: =C5/C4*100 | D6: =D5/D4*100
A7: NP (億) | B7: =FS!F18+FS!G18+FS!H18+FS!I18 | C7: =FS!J18+FS!K18+FS!L18+FS!M18 | D7: =FS!N18+FS!O18+FS!P18+FS!Q18
A8: EPS (¥) | B8: =FS!F22+FS!G22+FS!H22+FS!I22 | C8: =FS!J22+FS!K22+FS!L22+FS!M22 | D8: =FS!N22+FS!O22+FS!P22+FS!Q22
A12: Daily Snapshot ─ overwritten by modeling.daily_refresh after EOD
A13: Current Price (¥) | B13: 10540 | C13: from daily_bars latest close
A14: DCF base (¥) | B14: 3051 | C14: target_prices.db base scenario
A15: DCF bull (¥) | B15: 4055 | C15: target_prices.db bull scenario
A16: DCF bear (¥) | B16: 2047 | C16: target_prices.db bear scenario
A17: Composite verdict | B17: Rich | C17: Cheap / Fair / Rich vs current
A18: Peer median P/E (x) | B18: 16.5 | C18: Comp sheet median
A19: Last refresh date | B19: 2026-09-17

Sheet Debt
A1: Meidensha — Debt Schedule + Credit Metrics. Auto-rendered when fins_details has interest-bearing debt.
B2: FY24Q1 | C2: FY24Q2 | D2: FY24Q3 | E2: FY24Q4 | F2: FY25Q1 | G2: FY25Q2 | H2: FY25Q3 | I2: FY25Q4 | J2: FY26Q1 | K2: FY26Q2 | L2: FY26Q3 | M2: FY26Q4 | N2: FY27Q1 | O2: FY27Q2 | P2: FY27Q3 | Q2: FY27Q4 | R2: FY28Q1
A4: Beginning of Period (BoP) | B4: =FS!B41 | C4: =FS!B41 | D4: =FS!C41 | E4: =FS!D41 | F4: =FS!E41 | G4: =FS!F41 | H4: =FS!G41 | I4: =FS!H41 | J4: =FS!I41 | ... R4: =FS!Q41
A5: + Issuance (CF row 18 if positive) | B5: =MAX(0,B7-B4) | C5: =MAX(0,C7-C4) | D5: =MAX(0,D7-D4) | E5: =MAX(0,E7-E4) | F5: =MAX(0,F7-F4) | G5: =MAX(0,G7-G4) | H5: =MAX(0,H7-H4) | I5: =MAX(0,I7-I4) | ... R5: =MAX(0,R7-R4)
A6: − Repayment (CF row 18 if negative) | B6: =MAX(0,B4-B7) | C6: =MAX(0,C4-C7) | D6: =MAX(0,D4-D7) | E6: =MAX(0,E4-E7) | F6: =MAX(0,F4-F7) | G6: =MAX(0,G4-G7) | H6: =MAX(0,H4-H7) | I6: =MAX(0,I4-I7) | ... R6: =MAX(0,R4-R7)
A7: End of Period (EoP) — links to BS row 15 | B7: =FS!B41 | C7: =FS!C41 | D7: =FS!D41 | E7: =FS!E41 | F7: =FS!F41 | G7: =FS!G41 | H7: =FS!H41 | I7: =FS!I41 | ... R7: =FS!R41
A8: Avg balance (BoP+EoP)/2 | B8: =(B4+B7)/2 | C8: =(C4+C7)/2 | D8: =(D4+D7)/2 | E8: =(E4+E7)/2 | F8: =(F4+F7)/2 | G8: =(G4+G7)/2 | H8: =(H4+H7)/2 | I8: =(I4+I7)/2 | ... R8: =(R4+R7)/2
A10: Interest rate (annual %) | B10: 1.5 | C10: (adjust; reflects current avg cost of debt)
A11: Interest expense (Avg × rate ÷ 4) | B11: =B8*$B$10/100/4 | C11: =C8*$B$10/100/4 | D11: =D8*$B$10/100/4 | E11: =E8*$B$10/100/4 | F11: =F8*$B$10/100/4 | G11: =G8*$B$10/100/4 | H11: =H8*$B$10/100/4 | I11: =I8*$B$10/100/4 | ... R11: =R8*$B$10/100/4
A12: Disclosed (fins_details, hist FY only)
A14: Credit Metrics
A15: Net Debt (Debt - Cash) | B15: =FS!B41-FS!B30 | C15: =FS!C41-FS!C30 | D15: =FS!D41-FS!D30 | E15: =FS!E41-FS!E30 | F15: =FS!F41-FS!F30 | G15: =FS!G41-FS!G30 | H15: =FS!H41-FS!H30 | I15: =FS!I41-FS!I30 | ... R15: =FS!R41-FS!R30
A16: Net Debt / EBITDA (x) | B16: =IFERROR(B15/((FS!B9+FS!B70)*4),0) | C16: =IFERROR(C15/((FS!C9+FS!C70)*4),0) | D16: =IFERROR(D15/((FS!D9+FS!D70)*4),0) | E16: =IFERROR(E15/((FS!E9+FS!E70)*4),0) | F16: =IFERROR(F15/((FS!F9+FS!F70)*4),0) | G16: =IFERROR(G15/((FS!G9+FS!G70)*4),0) | H16: =IFERROR(H15/((FS!H9+FS!H70)*4),0) | I16: =IFERROR(I15/((FS!I9+FS!I70)*4),0) | ... R16: =IFERROR(R15/((FS!R9+FS!R70)*4),0)
A17: Interest Coverage (EBITDA/Int) | B17: =IFERROR((FS!B9+FS!B70)/B11,"") | C17: =IFERROR((FS!C9+FS!C70)/C11,"") | D17: =IFERROR((FS!D9+FS!D70)/D11,"") | E17: =IFERROR((FS!E9+FS!E70)/E11,"") | F17: =IFERROR((FS!F9+FS!F70)/F11,"") | G17: =IFERROR((FS!G9+FS!G70)/G11,"") | H17: =IFERROR((FS!H9+FS!H70)/H11,"") | I17: =IFERROR((FS!I9+FS!I70)/I11,"") | ... R17: =IFERROR((FS!R9+FS!R70)/R11,"")
A18: Debt / Equity (x) | B18: =IFERROR(FS!B41/FS!B48,0) | C18: =IFERROR(FS!C41/FS!C48,0) | D18: =IFERROR(FS!D41/FS!D48,0) | E18: =IFERROR(FS!E41/FS!E48,0) | F18: =IFERROR(FS!F41/FS!F48,0) | G18: =IFERROR(FS!G41/FS!G48,0) | H18: =IFERROR(FS!H41/FS!H48,0) | I18: =IFERROR(FS!I41/FS!I48,0) | ... R18: =IFERROR(FS!R41/FS!R48,0)
A19: Debt / Total Cap (%) | B19: =IFERROR(FS!B41/(FS!B41+FS!B48)*100,0) | C19: =IFERROR(FS!C41/(FS!C41+FS!C48)*100,0) | D19: =IFERROR(FS!D41/(FS!D41+FS!D48)*100,0) | E19: =IFERROR(FS!E41/(FS!E41+FS!E48)*100,0) | F19: =IFERROR(FS!F41/(FS!F41+FS!F48)*100,0) | G19: =IFERROR(FS!G41/(FS!G41+FS!G48)*100,0) | H19: =IFERROR(FS!H41/(FS!H41+FS!H48)*100,0) | I19: =IFERROR(FS!I41/(FS!I41+FS!I48)*100,0) | ... R19: =IFERROR(FS!R41/(FS!R41+FS!R48)*100,0)
A20: Current Ratio (CA/CL) | B20: =IFERROR(FS!B34/(FS!B40+FS!B42),0) | C20: =IFERROR(FS!C34/(FS!C40+FS!C42),0) | D20: =IFERROR(FS!D34/(FS!D40+FS!D42),0) | E20: =IFERROR(FS!E34/(FS!E40+FS!E42),0) | F20: =IFERROR(FS!F34/(FS!F40+FS!F42),0) | G20: =IFERROR(FS!G34/(FS!G40+FS!G42),0) | H20: =IFERROR(FS!H34/(FS!H40+FS!H42),0) | I20: =IFERROR(FS!I34/(FS!I40+FS!I42),0) | ... R20: =IFERROR(FS!R34/(FS!R40+FS!R42),0)
A21: Quick Ratio (CA-Inv)/CL | B21: =IFERROR((FS!B34-FS!B32)/(FS!B40+FS!B42),0) | C21: =IFERROR((FS!C34-FS!C32)/(FS!C40+FS!C42),0) | D21: =IFERROR((FS!D34-FS!D32)/(FS!D40+FS!D42),0) | E21: =IFERROR((FS!E34-FS!E32)/(FS!E40+FS!E42),0) | F21: =IFERROR((FS!F34-FS!F32)/(FS!F40+FS!F42),0) | G21: =IFERROR((FS!G34-FS!G32)/(FS!G40+FS!G42),0) | H21: =IFERROR((FS!H34-FS!H32)/(FS!H40+FS!H42),0) | I21: =IFERROR((FS!I34-FS!I32)/(FS!I40+FS!I42),0) | ... R21: =IFERROR((FS!R34-FS!R32)/(FS!R40+FS!R42),0)

Sheet Customers
A1: Meidensha — Revenue by Customer (single-Q, 億円). Source: deck p5 得意先別売上収益 vision-extracted.
A3: No customer observations in decks DB.

Sheet Cycle
A1: Meidensha — Cycle Multiple Bands (full history, PIT, split-adjusted)
A2: UPCYCLE → read P/E. BOTTOM → read P/B (trough EPS makes P/E meaningless). Phase clock is DESCRIPTIVE (full-sample OPM median), never a signal.
A4: 0. P/B comparability gate — cash ÷ equity (FY-end)
A5: range 5.9%-23.7%, mean 15.4%, first3→last3 drift -0.8pp → P/B COMPARABLE across time
A7: 1. Full-history band (monthly, TTM basis)
A8: Metric | B8: n | C8: min | D8: p10 | E8: p25 | F8: median | G8: p75 | H8: p90 | I8: max
A9: P/E | B9: 193 | C9: 7.62 | D9: 10.38 | E9: 12.06 | F9: 14.03 | G9: 18.76 | H9: 40.32 | I9: 84.89
A10: P/B | B10: 209 | C10: 0.78 | D10: 0.89 | E10: 1.11 | F10: 1.34 | G10: 1.65 | H10: 1.94 | I10: 3.08
A12: 2. By cycle phase (OPM median split = 4.21%)
A13: Phase | B13: months | C13: OPM med % | D13: P/E p25 | E13: P/E med | F13: P/E p75 | G13: P/B min | H13: P/B p25 | I13: P/B med | J13: P/B p75 | K13: P/B max
A14: 1 Recovery (低OPM・回升) | B14: 50 | C14: 3.5 | D14: 16.9 | E14: 31.4 | F14: 51.6 | G14: 0.89 | H14: 1.31 | I14: 1.43 | J14: 1.61 | K14: 1.95
A15: 2 Expansion (高OPM・上行) | B15: 89 | C15: 5 | D15: 11.2 | E15: 13.2 | F15: 15.2 | G15: 0.78 | H15: 1.2 | I15: 1.48 | J15: 1.76 | K15: 3.08
A16: 3 Early-down (高OPM・转跌) | B16: 17 | C16: 4.3 | D16: 11.2 | E16: 12.1 | F16: 14.3 | G16: 0.82 | H16: 1.11 | I16: 1.18 | J16: 1.24 | K16: 1.51
A17: 4 Trough (低OPM・下行) | B17: 41 | C17: 3.8 | D17: 12.8 | E17: 14.6 | F17: 16.4 | G17: 0.78 | H17: 0.88 | I17: 1.1 | J17: 1.22 | K17: 1.59
A19: 3. Cycle extremes (±12M local, PIT). 'prov' = inside the last 12M, no right-hand side yet
A20: Event | B20: Date | C20: Price | D20: TTM OP (億) | E20: OPM % | F20: TTM EPS | G20: BPS | H20: P/E | I20: P/B | J20: confirmed
A21: 盈利峰 OP peak | B21: 2009-05 | C21: 1920 | D21: 41 | E21: 2.1 | F21: -24 | G21: 1117 | I21: 1.72 | J21: yes
A22: 盈利峰 OP peak | B22: 2016-01 | C22: 2310 | D22: 140 | E22: 5.8 | F22: 179 | G22: 1457 | H22: 12.9 | I22: 1.59 | J22: yes
A23: 盈利峰 OP peak | B23: 2019-01 | C23: 1466 | D23: 116 | E23: 4.8 | F23: 192 | G23: 1768 | H23: 7.6 | I23: 0.83 | J23: yes
A24: 盈利峰 OP peak | B24: 2021-01 | C24: 2429 | D24: 141 | E24: 5.7 | F24: 192 | G24: 1920 | H24: 12.6 | I24: 1.27 | J24: yes
A25: 盈利峰 OP peak | B25: 2026-07 | C25: 9620 | D25: 314 | E25: 9.2 | F25: 622 | G25: 3855 | H25: 15.5 | I25: 2.5 | J25: prov
A27: 盈利谷 OP trough | B27: 2009-10 | C27: 2320 | D27: 21 | E27: 1.2 | F27: -30 | G27: 1022 | I27: 2.27 | J27: yes
A28: 盈利谷 OP trough | B28: 2017-01 | C28: 1925 | D28: 74 | E28: 3.2 | F28: 108 | G28: 1488 | H28: 17.8 | I28: 1.29 | J28: yes
A29: 盈利谷 OP trough | B29: 2019-07 | C29: 1691 | D29: 102 | E29: 4.2 | F29: 172 | G29: 1845 | H29: 9.8 | I29: 0.92 | J29: yes
A30: 盈利谷 OP trough | B30: 2021-05 | C30: 2254 | D30: 84 | E30: 3.6 | F30: 161 | G30: 2128 | H30: 14 | I30: 1.06 | J30: yes
A31: 盈利谷 OP trough | B31: 2023-01 | C31: 1922 | D31: 59 | E31: 2.2 | F31: 118 | G31: 2247 | H31: 16.3 | I31: 0.86 | J31: yes
A33: 股价顶 Price top | B33: 2009-07 | C33: 2835 | D33: 35 | E33: 1.8 | F33: -19 | G33: 1054 | I33: 2.69 | J33: yes
A34: 股价顶 Price top | B34: 2014-03 | C34: 2285 | D34: 88 | E34: 4.2 | F34: 95 | G34: 1192 | H34: 24 | I34: 1.92 | J34: yes
A35: 股价顶 Price top | B35: 2016-03 | C35: 2565 | D35: 140 | E35: 5.8 | F35: 179 | G35: 1457 | H35: 14.3 | I35: 1.76 | J35: yes
A36: 股价顶 Price top | B36: 2017-12 | C36: 2330 | D36: 89 | E36: 3.9 | F36: 116 | G36: 1614 | H36: 20.2 | I36: 1.44 | J36: yes
A37: 股价顶 Price top | B37: 2019-12 | C37: 2422 | D37: 110 | E37: 4.4 | F37: 176 | G37: 1845 | H37: 13.7 | I37: 1.31 | J37: yes
A38: 股价顶 Price top | B38: 2021-12 | C38: 2740 | D38: 92 | E38: 3.8 | F38: 186 | G38: 2128 | H38: 14.7 | I38: 1.29 | J38: yes
A39: 股价顶 Price top | B39: 2026-08 | C39: 11870 | D39: 314 | E39: 9.2 | F39: 622 | G39: 3855 | H39: 19.1 | I39: 3.08 | J39: prov
A41: 股价底 Price bottom | B41: 2010-08 | C41: 1265 | D41: 42 | E41: 2.5 | F41: 32 | G41: 1033 | H41: 39.9 | I41: 1.22 | J41: yes
A42: 股价底 Price bottom | B42: 2011-12 | C42: 1295 | D42: 60 | E42: 3.3 | F42: 18 | G42: 978 | H42: 71.2 | I42: 1.32 | J42: yes
A43: 股价底 Price bottom | B43: 2015-01 | C43: 1770 | D43: 104 | E43: 4.6 | F43: 173 | G43: 1173 | H43: 10.2 | I43: 1.51 | J43: yes
A44: 股价底 Price bottom | B44: 2016-08 | C44: 1630 | D44: 100 | E44: 4.2 | F44: 137 | G44: 1488 | H44: 11.9 | I44: 1.1 | J44: yes
A45: 股价底 Price bottom | B45: 2018-12 | C45: 1383 | D45: 115 | E45: 4.8 | F45: 173 | G45: 1768 | H45: 8 | I45: 0.78 | J45: yes
A46: 股价底 Price bottom | B46: 2020-07 | C46: 1563 | D46: 133 | E46: 5.3 | F46: 182 | G46: 1920 | H46: 8.6 | I46: 0.81 | J46: yes
A47: 股价底 Price bottom | B47: 2023-04 | C47: 1839 | D47: 59 | E47: 2.2 | F47: 118 | G47: 2247 | H47: 15.6 | I47: 0.82 | J47: yes
A49: 4. Current reading
A50: As of | B50: 2026-09-16
A51: Price (¥) | B51: 10540
A52: TTM EPS (¥) | B52: 622
A53: BPS (¥) | B53: 3855
A54: TTM OPM % | B54: 9.2
A55: TTM OP YoY % | B55: 38.2
A56: P/E | B56: 16.9
A57: P/B | B57: 2.73
A58: Phase (mechanical) | B58: 2 Expansion (高OPM・上行)
A60: 5. ONE-YEAR-FORWARD price = band × model NTM EPS / NTM BPS (live off Valuation). NOT a fair value today: the bands above are measured on TRAILING EPS/BPS, so applying them to NTM figures prices the stock 12M out AT THAT MULTIPLE. Band × CURRENT TTM EPS/BPS is the today-fair-value read.
A61: NTM EPS (¥) — Valuation!B32 | B61: =Valuation!B32
A62: NTM BPS (¥) — Valuation!B45 | B62: =Valuation!B45
A64: Band | B64: P/E x | C64: → price | D64: P/B x | E64: → price
A65: Full-history p25 | B65: 12.06 | C65: =B65*$B$61 | D65: 1.11 | E65: =D65*$B$62
A66: Full-history median | B66: 14.03 | C66: =B66*$B$61 | D66: 1.34 | E66: =D66*$B$62
A67: Full-history p75 | B67: 18.76 | C67: =B67*$B$61 | D67: 1.65 | E67: =D67*$B$62
A68: Full-history p90 | B68: 40.32 | C68: =B68*$B$61 | D68: 1.94 | E68: =D68*$B$62
A69: 1 Recovery (低OPM・回升) median | B69: 31.44 | C69: =B69*$B$61 | D69: 1.43 | E69: =D69*$B$62
A70: 2 Expansion (高OPM・上行) median | B70: 13.17 | C70: =B70*$B$61 | D70: 1.48 | E70: =D70*$B$62
A71: 3 Early-down (高OPM・转跌) median | B71: 12.15 | C71: =B71*$B$61 | D71: 1.18 | E71: =D71*$B$62
A72: 4 Trough (低OPM・下行) median | B72: 14.57 | C72: =B72*$B$61 | D72: 1.1 | E72: =D72*$B$62
A75: 6. FORWARD P/E on 会社予想 (company guidance), full history, PIT
A76: A CONSENSUS forward band is not buildable here — PIT consensus snapshots only start 2026-04-09 (~5 months). Company guidance is carried PIT in fins_summary since 2008, and 会社予想PER is the multiple the JP market actually quotes. The sandbag is handled explicitly by the beat table below, not left implicit in the multiple.
A78: Guide horizon (compare LIKE FOR LIKE) | B78: n | C78: min | D78: p10 | E78: p25 | F78: median | G78: p75 | H78: p90 | I78: max
A79: 9-11M left (期初 4-6月) | B79: 35 | C79: 8.8 | D79: 10.9 | E79: 13 | F79: 15.3 | G79: 17.6 | H79: 32.1 | I79: 174.5
A80: 6-8M left (1Q後 7-9月) ← CURRENT | B80: 51 | C80: 9.8 | D80: 10.7 | E80: 12.2 | F80: 15 | G80: 16.6 | H80: 26.4 | I80: 139.5
A81: 3-5M left (2Q後 10-12月) | B81: 50 | C81: 8.7 | D81: 10.7 | E81: 13.4 | F81: 15.4 | G81: 17.5 | H81: 28.9 | I81: 189.1
A82: 0-2M left (3Q後 1-3月) | B82: 51 | C82: 9.2 | D82: 10.4 | E82: 13.3 | F82: 14.9 | G82: 18.1 | H82: 56 | I82: 189.1
A83: All horizons pooled | B83: 187 | C83: 8.7 | D83: 10.7 | E83: 13 | F83: 15.2 | G83: 17.5 | H83: 41.9 | I83: 189.1
A85: Guide EPS in force (¥) | B85: 551.1
A86: Guided FY end | B86: 2027-03
A87: Months of guide left | B87: 6
A88: CURRENT 会社予想 fwd P/E | B88: 19.13
A89: percentile within the SAME horizon bucket | B89: 81.5
A91: Sandbag check — actual FY EPS ÷ the FIRST guide issued for that FY
A92: Stat | B92: n | C92: min | D92: p25 | E92: median | F92: p75 | G92: max | H92: beat rate %
A93: guide → actual factor | B93: 17 | C93: 0.672 | D93: 0.962 | E93: 1.145 | F93: 1.688 | G93: 5.102 | H93: 71
A94: Read: a factor of 1.20 means the company came in 20% above its own opening guide. The max is a post-crash artefact (guide reset to near-zero), so use the median.
A96: Same price, four EPS vintages — this is what the 'P/E' argument is really about
A97: EPS vintage | B97: FY EPS (¥) | C97: fwd P/E | D97: implied beat vs guide
A98: 会社 guide (fins_summary) | B98: 551.1 | C98: =IFERROR(10540.0/B98,"") | D98: =IFERROR(B98/B98,"")
A99: 街道 consensus (Comp sheet) | B99: =IFERROR(INDEX(Comp!I:I,MATCH("65080",Comp!A:A,0)),"") | C99: =IFERROR(10540.0/B99,"") | D99: =IFERROR(B99/B98,"")
A100: guide × historical median beat | B100: =B98*1.1449 | C100: =IFERROR(10540.0/B100,"") | D100: =IFERROR(B100/B98,"")
A101: 本模型 this model (FY guide-year) | B101: =FS!W22 | C101: =IFERROR(10540.0/B101,"") | D101: =IFERROR(B101/B98,"")
A102: Price used: ¥10,540 (2026-09-16). The 'implied beat' column says what each EPS vintage assumes about the sandbag — compare it against the beat-factor distribution above before believing any of them.

Sheet Checks
A1: Meidensha — Integrity Checks. All cells should be 0. Master cell at top.
A3: MASTER STATUS | B3: =IF(SUMPRODUCT(ABS(IFERROR(B6:R12,0)))<0.5,"✓ ALL CHECKS PASS","✗ ERRORS DETECTED — review red cells below")
A5: Check | B5: FY24Q1 | C5: FY24Q2 | D5: FY24Q3 | E5: FY24Q4 | F5: FY25Q1 | G5: FY25Q2 | H5: FY25Q3 | I5: FY25Q4 | J5: FY26Q1 | K5: FY26Q2 | L5: FY26Q3 | M5: FY26Q4 | N5: FY27Q1 | O5: FY27Q2 | P5: FY27Q3 | Q5: FY27Q4 | R5: FY28Q1
A6: BS: TA - TL - TE | B6: =FS!B50 | C6: =FS!C50 | D6: =FS!D50 | E6: =FS!E50 | F6: =FS!F50 | G6: =FS!G50 | H6: =FS!H50 | I6: =FS!I50 | ... R6: =FS!R50
A7: Cash tie: BS Cash - (Prior Cash + CF NetΔ) | C7: =FS!C30 - (FS!B30 + FS!C66) | D7: =FS!D30 - (FS!C30 + FS!D66) | E7: =FS!E30 - (FS!D30 + FS!E66) | F7: =FS!F30 - (FS!E30 + FS!F66) | G7: =FS!G30 - (FS!F30 + FS!G66) | H7: =FS!H30 - (FS!G30 + FS!H66) | I7: =FS!I30 - (FS!H30 + FS!I66) | J7: =FS!J30 - (FS!I30 + FS!J66) | ... R7: =FS!R30 - (FS!Q30 + FS!R66)
A8: NI link: PL NI - CF NI | B8: =FS!B18 - FS!B69 | C8: =FS!C18 - FS!C69 | D8: =FS!D18 - FS!D69 | E8: =FS!E18 - FS!E69 | F8: =FS!F18 - FS!F69 | G8: =FS!G18 - FS!G69 | H8: =FS!H18 - FS!H69 | I8: =FS!I18 - FS!I69 | ... R8: =FS!R18 - FS!R69
A9: RE roll: ΔRE - (NI - Div - Buyback) | C9: =FS!C46 - (FS!B46 + FS!C18 - FS!C75 - FS!C76) | D9: =FS!D46 - (FS!C46 + FS!D18 - FS!D75 - FS!D76) | E9: =FS!E46 - (FS!D46 + FS!E18 - FS!E75 - FS!E76) | F9: =FS!F46 - (FS!E46 + FS!F18 - FS!F75 - FS!F76) | G9: =FS!G46 - (FS!F46 + FS!G18 - FS!G75 - FS!G76) | H9: =FS!H46 - (FS!G46 + FS!H18 - FS!H75 - FS!H76) | I9: =FS!I46 - (FS!H46 + FS!I18 - FS!I75 - FS!I76) | J9: =FS!J46 - (FS!I46 + FS!J18 - FS!J75 - FS!J76) | ... R9: =FS!R46 - (FS!Q46 + FS!R18 - FS!R75 - FS!R76)
A10: ΔWC tie: CF ΔWC vs BS ΔAR/Inv/AP | C10: =FS!C71 - (-(FS!C31-FS!B31) - (FS!C32-FS!B32) + (FS!C40-FS!B40)) | D10: =FS!D71 - (-(FS!D31-FS!C31) - (FS!D32-FS!C32) + (FS!D40-FS!C40)) | E10: =FS!E71 - (-(FS!E31-FS!D31) - (FS!E32-FS!D32) + (FS!E40-FS!D40)) | F10: =FS!F71 - (-(FS!F31-FS!E31) - (FS!F32-FS!E32) + (FS!F40-FS!E40)) | G10: =FS!G71 - (-(FS!G31-FS!F31) - (FS!G32-FS!F32) + (FS!G40-FS!F40)) | H10: =FS!H71 - (-(FS!H31-FS!G31) - (FS!H32-FS!G32) + (FS!H40-FS!G40)) | I10: =FS!I71 - (-(FS!I31-FS!H31) - (FS!I32-FS!H32) + (FS!I40-FS!H40)) | J10: =FS!J71 - (-(FS!J31-FS!I31) - (FS!J32-FS!I32) + (FS!J40-FS!I40)) | ... R10: =FS!R71 - (-(FS!R31-FS!Q31) - (FS!R32-FS!Q32) + (FS!R40-FS!Q40))
A11: CapEx tie: CF Capex - Assumption | K11: =FS!K73 - FS!$B$95 | L11: =FS!L73 - FS!$B$95 | M11: =FS!M73 - FS!$B$95 | N11: =FS!N73 - FS!$B$95 | O11: =FS!O73 - FS!$B$95 | P11: =FS!P73 - FS!$B$95 | Q11: =FS!Q73 - FS!$B$95 | R11: =FS!R73 - FS!$B$95
A12: Buyback tie: CF Buyback - Assumption | K12: =FS!K76 - FS!$B$96 | L12: =FS!L76 - FS!$B$96 | M12: =FS!M76 - FS!$B$96 | N12: =FS!N76 - FS!$B$96 | O12: =FS!O76 - FS!$B$96 | P12: =FS!P76 - FS!$B$96 | Q12: =FS!Q76 - FS!$B$96 | R12: =FS!R76 - FS!$B$96
A15: Sign convention reminder:
A16: CFO ΔAR (asset increase) = NEGATIVE (use of cash)
A17: CFO ΔAP (liability increase) = POSITIVE (source of cash)
A18: CFI Capex = NEGATIVE outflow (stored as positive in row 14, sign on FCF formula)
A19: CFF Dividend / Buyback stored as POSITIVE (outflow); FCF = -Div - Buyback + DebtIss
A20: Cash tie: BS Cash[N] = BS Cash[N-1] + CF (OCF + ICF + FCF)
A21: RE roll: BS RE[N] = BS RE[N-1] + PL NI[N] - CF Div[N] - CF Buyback[N]
